Workbook

Sheet Header & Notes
B6: 1 | C6: ID Bank
B8: 2 | C8: Nama bank | J8: Bank x
B10: 3 | C10: Tanggal pelaporan | J10: MM/DD/YYYY
B12: 4 | C12: Mata uang denominasi (select from list) | J12: IDR
B14: 5 | C14: Satuan | J14: Jutaan

Sheet Dashboard
H6: Analysis
H9: ='Header & Notes'!J8&" - "&(TEXT('Header & Notes'!J10,"DD/MM/YYYY")) -> Bank x - MM/DD/YYYY
H11: Day | K11: =TEXT(K12,"ddd") -> MM/DD/YYYY | L11: =TEXT(L12,"ddd") -> #VALUE! | M11: =TEXT(M12,"ddd") -> #VALUE!
H12: Date | K12: ='Header & Notes'!J10 -> MM/DD/YYYY | L12: =K12+1 -> #VALUE! | M12: =K12+1 -> #VALUE! | N12: =M12+1 -> #VALUE! | O12: =N12+1 -> #VALUE! | P12: =O12+1 -> #VALUE! | Q12: =P12+1 -> #VALUE! | R12: =Q12+1 -> #VALUE! | S12: =R12+1 -> #VALUE! | T12: =S12+1 -> #VALUE! | U12: =T12+1 -> #VALUE! | ... AP12: =AO12+1 -> #VALUE! | AQ12: =AP12+7 -> #VALUE! | AR12: =EOMONTH($K12,2) -> #VALUE! | AS12: =EOMONTH($K12,3) -> #VALUE! | AT12: =EOMONTH($K12,4) -> #VALUE! | AU12: =EOMONTH($K12,5) -> #VALUE! | AV12: =EOMONTH($K12,6) -> #VALUE! | AW12: =EOMONTH($K12,9) -> #VALUE! | AX12: =EOMONTH($K12,12) -> #VALUE! | AY12: =EOMONTH($K12,24) -> #VALUE! | AZ12: =EOMONTH($K12,60) -> #VALUE! | BA12: =EOMONTH($K12,72) -> #VALUE!
K13: Initial stock | L13: Tanpa Maturitas (Open) | M13: O/N | N13: Hari-2 | O13: Hari-3 | P13: Hari-4 | Q13: Hari-5 | R13: Hari-6 | S13: Hari-7 | T13: Hari-8 | U13: Hari-9 | V13: Hari-10 | W13: Hari-11 | X13: Hari-12 | Y13: Hari-13 | Z13: Hari-14 | AA13: Hari-15 | AB13: Hari-16 | AC13: Hari-17 | AD13: Hari-18 | AE13: Hari-19 | AF13: Hari-20 | AG13: Hari-21 | AH13: Hari-22 | AI13: Hari-23 | AJ13: Hari-24 | AK13: Hari-25 | AL13: Hari-26 | AM13: Hari-27 | AN13: Hari-28 | AO13: Hari-29 | AP13: Hari-30 | AQ13: > mg 4 s.d. mg 5 | AR13: > mg 5 s.d. 2 bln | AS13: > 2 bln s.d 3 bln | AT13: > 3 bln s.d 4 bln | AU13: > 4 bln s.d 5 bln | AV13: > 5 bln s.d 6 bln | AW13: > 6 bln s.d. 9 bln | AX13: > 9 bln s.d. 12 bln | AY13: > 12 bln s.d. 2 thn | AZ13: > 2 thn s.d. 5 thn | BA13: > 5 thn
M14: 1 | N14: 2 | O14: 3 | P14: 4 | Q14: 5 | R14: 6 | S14: 7 | T14: 8 | U14: 9 | V14: 10 | W14: 11 | X14: 12 | Y14: 13 | Z14: 14 | AA14: 15 | AB14: 16 | AC14: 17 | AD14: 18 | AE14: 19 | AF14: 20 | AG14: 21 | AH14: 22 | AI14: 23 | AJ14: 24 | AK14: 25 | AL14: 26 | AM14: 27 | AN14: 28 | AO14: 29 | AP14: 30
M15: =M12-$K12 -> #VALUE! | N15: =N12-$K12 -> #VALUE! | O15: =O12-$K12 -> #VALUE! | P15: =P12-$K12 -> #VALUE! | Q15: =Q12-$K12 -> #VALUE! | R15: =R12-$K12 -> #VALUE! | S15: =S12-$K12 -> #VALUE! | T15: =T12-$K12 -> #VALUE! | ... BA15: =BA12-$K12 -> #VALUE!
H16: Granular LCR / Benchmark
H17: HQLA (posisi awal) | K17: ='SPM Skenario Dasar'!K86+'SPM Skenario Dasar'!K87+'SPM Skenario Dasar'!K88+'SPM Skenario Dasar'!K92+'SPM Skenario Dasar'!K95 -> 0 | L17: =$K17 -> 0 | M17: =$K17 -> 0 | N17: =$K17 -> 0 | O17: =$K17 -> 0 | P17: =$K17 -> 0 | Q17: =$K17 -> 0 | R17: =$K17 -> 0 | S17: =$K17 -> 0 | ... BA17: =$K17 -> 0
H19: Arus masuk bruto | L19: ='SPM Skenario Dasar'!L82 -> 0 | M19: ='SPM Skenario Dasar'!M82 -> 0 | N19: ='SPM Skenario Dasar'!N82 -> 0 | O19: ='SPM Skenario Dasar'!O82 -> 0 | P19: ='SPM Skenario Dasar'!P82 -> 0 | Q19: ='SPM Skenario Dasar'!Q82 -> 0 | R19: ='SPM Skenario Dasar'!R82 -> 0 | S19: ='SPM Skenario Dasar'!S82 -> 0 | ... BA19: ='SPM Skenario Dasar'!BA82 -> 0
H20: Arus keluar bruto | L20: =SUM('SPM Skenario Dasar'!L51,'SPM Skenario Dasar'!L108,'SPM Skenario Dasar'!L115,'SPM Skenario Dasar'!L118,'SPM Skenario Dasar'!L123,'SPM Skenario Dasar'!L128,'SPM Skenario Dasar'!L132) -> 0 | M20: =SUM('SPM Skenario Dasar'!M51,'SPM Skenario Dasar'!M108,'SPM Skenario Dasar'!M115,'SPM Skenario Dasar'!M118,'SPM Skenario Dasar'!M123,'SPM Skenario Dasar'!M128,'SPM Skenario Dasar'!M132) -> 0 | N20: =SUM('SPM Skenario Dasar'!N51,'SPM Skenario Dasar'!N108,'SPM Skenario Dasar'!N115,'SPM Skenario Dasar'!N118,'SPM Skenario Dasar'!N123,'SPM Skenario Dasar'!N128,'SPM Skenario Dasar'!N132) -> 0 | O20: =SUM('SPM Skenario Dasar'!O51,'SPM Skenario Dasar'!O108,'SPM Skenario Dasar'!O115,'SPM Skenario Dasar'!O118,'SPM Skenario Dasar'!O123,'SPM Skenario Dasar'!O128,'SPM Skenario Dasar'!O132) -> 0 | P20: =SUM('SPM Skenario Dasar'!P51,'SPM Skenario Dasar'!P108,'SPM Skenario Dasar'!P115,'SPM Skenario Dasar'!P118,'SPM Skenario Dasar'!P123,'SPM Skenario Dasar'!P128,'SPM Skenario Dasar'!P132) -> 0 | Q20: =SUM('SPM Skenario Dasar'!Q51,'SPM Skenario Dasar'!Q108,'SPM Skenario Dasar'!Q115,'SPM Skenario Dasar'!Q118,'SPM Skenario Dasar'!Q123,'SPM Skenario Dasar'!Q128,'SPM Skenario Dasar'!Q132) -> 0 | R20: =SUM('SPM Skenario Dasar'!R51,'SPM Skenario Dasar'!R108,'SPM Skenario Dasar'!R115,'SPM Skenario Dasar'!R118,'SPM Skenario Dasar'!R123,'SPM Skenario Dasar'!R128,'SPM Skenario Dasar'!R132) -> 0 | S20: =SUM('SPM Skenario Dasar'!S51,'SPM Skenario Dasar'!S108,'SPM Skenario Dasar'!S115,'SPM Skenario Dasar'!S118,'SPM Skenario Dasar'!S123,'SPM Skenario Dasar'!S128,'SPM Skenario Dasar'!S132) -> 0 | ... BA20: =SUM('SPM Skenario Dasar'!BA51,'SPM Skenario Dasar'!BA108,'SPM Skenario Dasar'!BA115,'SPM Skenario Dasar'!BA118,'SPM Skenario Dasar'!BA123,'SPM Skenario Dasar'!BA128,'SPM Skenario Dasar'!BA132) -> 0
H21: Kumulatif arus masuk bruto | L21: =L19 -> 0 | M21: =M19+L21 -> 0 | N21: =N19+M21 -> 0 | O21: =O19+N21 -> 0 | P21: =P19+O21 -> 0 | Q21: =Q19+P21 -> 0 | R21: =R19+Q21 -> 0 | S21: =S19+R21 -> 0 | T21: =T19+S21 -> 0 | ... BA21: =BA19+AZ21 -> 0
H22: Kumulatif arus keluar bruto | L22: =L20 -> 0 | M22: =M20+L22 -> 0 | N22: =N20+M22 -> 0 | O22: =O20+N22 -> 0 | P22: =P20+O22 -> 0 | Q22: =Q20+P22 -> 0 | R22: =R20+Q22 -> 0 | S22: =S20+R22 -> 0 | T22: =T20+S22 -> 0 | ... BA22: =BA20+AZ22 -> 0
H23: FX swap arus masuk (memo) | L23: ='SPM Skenario Dasar'!L76 -> 0 | M23: ='SPM Skenario Dasar'!M76 -> 0 | N23: ='SPM Skenario Dasar'!N76 -> 0 | O23: ='SPM Skenario Dasar'!O76 -> 0 | P23: ='SPM Skenario Dasar'!P76 -> 0 | Q23: ='SPM Skenario Dasar'!Q76 -> 0 | R23: ='SPM Skenario Dasar'!R76 -> 0 | S23: ='SPM Skenario Dasar'!S76 -> 0 | ... BA23: ='SPM Skenario Dasar'!BA76 -> 0
H24: FX swap arus keluar (memo) | L24: ='SPM Skenario Dasar'!L48 -> 0 | M24: ='SPM Skenario Dasar'!M48 -> 0 | N24: ='SPM Skenario Dasar'!N48 -> 0 | O24: ='SPM Skenario Dasar'!O48 -> 0 | P24: ='SPM Skenario Dasar'!P48 -> 0 | Q24: ='SPM Skenario Dasar'!Q48 -> 0 | R24: ='SPM Skenario Dasar'!R48 -> 0 | S24: ='SPM Skenario Dasar'!S48 -> 0 | ... BA24: ='SPM Skenario Dasar'!BA48 -> 0
H25: Add-on Pillar 2 | L25: =('SPM Skenario Dasar'!L180) -> 0 | M25: =('SPM Skenario Dasar'!M180) -> 0 | N25: =('SPM Skenario Dasar'!N180) -> 0 | O25: =('SPM Skenario Dasar'!O180) -> 0 | P25: =('SPM Skenario Dasar'!P180) -> 0 | Q25: =('SPM Skenario Dasar'!Q180) -> 0 | R25: =('SPM Skenario Dasar'!R180) -> 0 | S25: =('SPM Skenario Dasar'!S180) -> 0 | ... BA25: =('SPM Skenario Dasar'!BA180) -> 0
H26: Kumulatif arus keluar bruto (incl. Pillar 2) | L26: =L22+L25 -> 0 | M26: =M22+SUM($L25:M25) -> 0 | N26: =N22+SUM($L25:N25) -> 0 | O26: =O22+SUM($L25:O25) -> 0 | P26: =P22+SUM($L25:P25) -> 0 | Q26: =Q22+SUM($L25:Q25) -> 0 | R26: =R22+SUM($L25:R25) -> 0 | S26: =S22+SUM($L25:S25) -> 0 | T26: =T22+SUM($L25:T25) -> 0 | ... BA26: =BA22+SUM($L25:BA25) -> 0
H27: Kumulatif arus netto (incl. Pillar 2) | L27: =L21+L26 -> 0 | M27: =M21+M26 -> 0 | N27: =N21+N26 -> 0 | O27: =O21+O26 -> 0 | P27: =P21+P26 -> 0 | Q27: =Q21+Q26 -> 0 | R27: =R21+R26 -> 0 | S27: =S21+S26 -> 0 | ... BA27: =BA21+BA26 -> 0
H28: Kumulatif arus netto (excl. Pillar 2) | L28: =L22+L21 -> 0 | M28: =M22+M21 -> 0 | N28: =N22+N21 -> 0 | O28: =O22+O21 -> 0 | P28: =P22+P21 -> 0 | Q28: =Q22+Q21 -> 0 | R28: =R22+R21 -> 0 | S28: =S22+S21 -> 0 | ... BA28: =BA22+BA21 -> 0
H29: Posisi likuiditas kumulatif (HQLA + arus masuk - [arus keluar + P2]) | L29: =L17+L27 -> 0 | M29: =M17+M27 -> 0 | N29: =N17+N27 -> 0 | O29: =O17+O27 -> 0 | P29: =P17+P27 -> 0 | Q29: =Q17+Q27 -> 0 | R29: =R17+R27 -> 0 | S29: =S17+S27 -> 0 | ... BA29: =BA17+BA27 -> 0
H30: LCR (Calculated) | L30: =K17/(ABS(AP22)-MIN(AP21,ABS(AP22)*75%)) -> #DIV/0!
H31: LCR (Pillar 2) | L31: =K17/(ABS(AP26)-MIN(AP21,ABS(AP26)*75%)) -> #DIV/0!
H32: Target LCR | L32: =(ABS(AP26)-MIN(AP21,ABS(AP26)*75%))/(ABS(AP22)-MIN(AP21,ABS(AP22)*75%)) -> #DIV/0!
H34: Granular LCR stress (30d)
H35: Posisi likuiditas netto terkecil (dalam 1 bln ke depan) | K35: =MIN(Dashboard!M$29:AP$29) -> 0
H36: Hari atau bucket waktu di mana posisi likuiditas netto terkecil (dalam 1 bln ke depan) | K36: =INDEX(Dashboard!$M$13:$AP$13,1,MATCH(K35,Dashboard!M29:AP29,0)) -> O/N
H37: Kumulatif arus kas keluar tertinggi (arus kas dalam 1 bln tanpa HQLA) | K37: =MIN(Dashboard!M$27:AP$27) -> 0
H38: Posisi likuiditas netto terkecil (arus kas + HQLA, dalam 15 hari) | K38: =MIN(M$29:AA$29) -> 0
H39: Tanggal kegagalan likuiditas | K39: =IF(SUM(Dashboard!M$39:AP$39)>0,INDEX(Dashboard!M$12:AP$12,1,MATCH(1,Dashboard!M$39:AP$39,0)),"Di luar zona 30h") -> Di luar zona 30h | L39: =IF(Dashboard!L29>=0,0,1) -> 0 | M39: =IF(Dashboard!M29>=0,0,1) -> 0 | N39: =IF(Dashboard!N29>=0,0,1) -> 0 | O39: =IF(Dashboard!O29>=0,0,1) -> 0 | P39: =IF(Dashboard!P29>=0,0,1) -> 0 | Q39: =IF(Dashboard!Q29>=0,0,1) -> 0 | R39: =IF(Dashboard!R29>=0,0,1) -> 0 | S39: =IF(Dashboard!S29>=0,0,1) -> 0 | ... BA39: =IF(Dashboard!BA29>=0,0,1) -> 0
H40: Survival period | K40: =IF(K39="Di luar zona 30h",">30 hari",K39-Dashboard!K$12-1 & " hari") -> >30 hari
H41: Posisi likuiditas netto pada saat kegagalan likuiditas | K41: =IF(SUM(Dashboard!M$39:AP$39)>0,INDEX(Dashboard!M$29:AP$29,1,MATCH(1,Dashboard!M$39:AP$39,0)),"N/A") -> N/A
H43: Benchmark Stress (3 bulan)
H44: Posisi likuiditas netto terkecil (dalam 3 bln ke depan) | K44: =MIN(Dashboard!M$29:AS$29) -> 0
H45: Hari atau bucket waktu di mana posisi likuiditas netto terkecil (dalam 3 bln ke depan) | K45: =INDEX(Dashboard!$M$13:$AS$13,1,MATCH(K44,Dashboard!M29:AS29,0)) -> O/N
H46: Kumulatif arus kas keluar tertinggi (arus kas dalam 3 bln tanpa HQLA) | K46: =MIN(Dashboard!M$27:AQ$27) -> 0
H47: Posisi likuiditas netto terkecil (arus kas + HQLA, dalam 2 bln ke depan) | K47: =MIN(M$29:AR$29) -> 0
H48: Tanggal kegagalan likuiditas | K48: =IF(SUM(Dashboard!M$48:AS$48)>0,INDEX(Dashboard!M$12:AS$12,1,MATCH(1,Dashboard!M$48:AS$48,0)),"Di luar zona 92h") -> Di luar zona 92h | L48: =IF(Dashboard!L29>=0,0,1) -> 0 | M48: =IF(Dashboard!M29>=0,0,1) -> 0 | N48: =IF(Dashboard!N29>=0,0,1) -> 0 | O48: =IF(Dashboard!O29>=0,0,1) -> 0 | P48: =IF(Dashboard!P29>=0,0,1) -> 0 | Q48: =IF(Dashboard!Q29>=0,0,1) -> 0 | R48: =IF(Dashboard!R29>=0,0,1) -> 0 | S48: =IF(Dashboard!S29>=0,0,1) -> 0 | ... BA48: =IF(Dashboard!BA29>=0,0,1) -> 0
H49: Survival period | K49: =IF(K48="Di luar zona 92h",">92 days",K48-Dashboard!K$12-1 &" hari") -> >92 days
H50: Posisi likuiditas netto pada saat kegagalan likuiditas | K50: =IF(SUM(Dashboard!M$48:AS$48)>0,INDEX(Dashboard!M$29:AS$29,1,MATCH(1,Dashboard!M$48:AS$48,0)),"N/A") -> N/A
K52: 0 | M52: 0 | N52: 0 | O52: 0 | P52: 0 | AL52: 0 | AM52: 0 | AN52: 0 | AO52: 0
H53: Skenario Bank
H54: HQLA (posisi awal) | K54: ='SPM Skenario Bank'!K86+'SPM Skenario Bank'!K87+'SPM Skenario Bank'!K88+'SPM Skenario Bank'!K92+'SPM Skenario Bank'!K95 -> 0 | L54: =$K54 -> 0 | M54: =$K54 -> 0 | N54: =$K54 -> 0 | O54: =$K54 -> 0 | P54: =$K54 -> 0 | Q54: =$K54 -> 0 | R54: =$K54 -> 0 | S54: =$K54 -> 0 | ... BA54: =$K54 -> 0
H56: Arus masuk bruto | L56: ='SPM Skenario Bank'!L82 -> 0 | M56: ='SPM Skenario Bank'!M82 -> 0 | N56: ='SPM Skenario Bank'!N82 -> 0 | O56: ='SPM Skenario Bank'!O82 -> 0 | P56: ='SPM Skenario Bank'!P82 -> 0 | Q56: ='SPM Skenario Bank'!Q82 -> 0 | R56: ='SPM Skenario Bank'!R82 -> 0 | S56: ='SPM Skenario Bank'!S82 -> 0 | ... BA56: ='SPM Skenario Bank'!BA82 -> 0
H57: Arus keluar bruto | L57: =SUM('SPM Skenario Bank'!L51,'SPM Skenario Bank'!L108,'SPM Skenario Bank'!L115,'SPM Skenario Bank'!L118,'SPM Skenario Bank'!L123,'SPM Skenario Bank'!L128,'SPM Skenario Bank'!L132) -> 0 | M57: =SUM('SPM Skenario Bank'!M51,'SPM Skenario Bank'!M108,'SPM Skenario Bank'!M115,'SPM Skenario Bank'!M118,'SPM Skenario Bank'!M123,'SPM Skenario Bank'!M128,'SPM Skenario Bank'!M132) -> 0 | N57: =SUM('SPM Skenario Bank'!N51,'SPM Skenario Bank'!N108,'SPM Skenario Bank'!N115,'SPM Skenario Bank'!N118,'SPM Skenario Bank'!N123,'SPM Skenario Bank'!N128,'SPM Skenario Bank'!N132) -> 0 | O57: =SUM('SPM Skenario Bank'!O51,'SPM Skenario Bank'!O108,'SPM Skenario Bank'!O115,'SPM Skenario Bank'!O118,'SPM Skenario Bank'!O123,'SPM Skenario Bank'!O128,'SPM Skenario Bank'!O132) -> 0 | P57: =SUM('SPM Skenario Bank'!P51,'SPM Skenario Bank'!P108,'SPM Skenario Bank'!P115,'SPM Skenario Bank'!P118,'SPM Skenario Bank'!P123,'SPM Skenario Bank'!P128,'SPM Skenario Bank'!P132) -> 0 | Q57: =SUM('SPM Skenario Bank'!Q51,'SPM Skenario Bank'!Q108,'SPM Skenario Bank'!Q115,'SPM Skenario Bank'!Q118,'SPM Skenario Bank'!Q123,'SPM Skenario Bank'!Q128,'SPM Skenario Bank'!Q132) -> 0 | R57: =SUM('SPM Skenario Bank'!R51,'SPM Skenario Bank'!R108,'SPM Skenario Bank'!R115,'SPM Skenario Bank'!R118,'SPM Skenario Bank'!R123,'SPM Skenario Bank'!R128,'SPM Skenario Bank'!R132) -> 0 | S57: =SUM('SPM Skenario Bank'!S51,'SPM Skenario Bank'!S108,'SPM Skenario Bank'!S115,'SPM Skenario Bank'!S118,'SPM Skenario Bank'!S123,'SPM Skenario Bank'!S128,'SPM Skenario Bank'!S132) -> 0 | ... BA57: =SUM('SPM Skenario Bank'!BA51,'SPM Skenario Bank'!BA108,'SPM Skenario Bank'!BA115,'SPM Skenario Bank'!BA118,'SPM Skenario Bank'!BA123,'SPM Skenario Bank'!BA128,'SPM Skenario Bank'!BA132) -> 0
H58: Kumulatif arus masuk bruto | L58: =L56 -> 0 | M58: =M56+L58 -> 0 | N58: =N56+M58 -> 0 | O58: =O56+N58 -> 0 | P58: =P56+O58 -> 0 | Q58: =Q56+P58 -> 0 | R58: =R56+Q58 -> 0 | S58: =S56+R58 -> 0 | T58: =T56+S58 -> 0 | ... BA58: =BA56+AZ58 -> 0
H59: Kumulatif arus keluar bruto | L59: =L57 -> 0 | M59: =M57+L59 -> 0 | N59: =N57+M59 -> 0 | O59: =O57+N59 -> 0 | P59: =P57+O59 -> 0 | Q59: =Q57+P59 -> 0 | R59: =R57+Q59 -> 0 | S59: =S57+R59 -> 0 | T59: =T57+S59 -> 0 | ... BA59: =BA57+AZ59 -> 0
H60: FX swap arus masuk (memo) | L60: ='SPM Skenario Bank'!L76 -> 0 | M60: ='SPM Skenario Bank'!M76 -> 0 | N60: ='SPM Skenario Bank'!N76 -> 0 | O60: ='SPM Skenario Bank'!O76 -> 0 | P60: ='SPM Skenario Bank'!P76 -> 0 | Q60: ='SPM Skenario Bank'!Q76 -> 0 | R60: ='SPM Skenario Bank'!R76 -> 0 | S60: ='SPM Skenario Bank'!S76 -> 0 | ... BA60: ='SPM Skenario Bank'!BA76 -> 0
H61: FX swap arus keluar (memo) | L61: ='SPM Skenario Bank'!L48 -> 0 | M61: ='SPM Skenario Bank'!M48 -> 0 | N61: ='SPM Skenario Bank'!N48 -> 0 | O61: ='SPM Skenario Bank'!O48 -> 0 | P61: ='SPM Skenario Bank'!P48 -> 0 | Q61: ='SPM Skenario Bank'!Q48 -> 0 | R61: ='SPM Skenario Bank'!R48 -> 0 | S61: ='SPM Skenario Bank'!S48 -> 0 | ... BA61: ='SPM Skenario Bank'!BA48 -> 0
H62: Add-on Pillar 2 | L62: =('SPM Skenario Bank'!L180) -> 0 | M62: =('SPM Skenario Bank'!M180) -> 0 | N62: =('SPM Skenario Bank'!N180) -> 0 | O62: =('SPM Skenario Bank'!O180) -> 0 | P62: =('SPM Skenario Bank'!P180) -> 0 | Q62: =('SPM Skenario Bank'!Q180) -> 0 | R62: =('SPM Skenario Bank'!R180) -> 0 | S62: =('SPM Skenario Bank'!S180) -> 0 | ... BA62: =('SPM Skenario Bank'!BA180) -> 0
H63: Kumulatif arus keluar bruto (incl. Pillar 2) | L63: =L59+L62 -> 0 | M63: =M59+SUM($L62:M62) -> 0 | N63: =N59+SUM($L62:N62) -> 0 | O63: =O59+SUM($L62:O62) -> 0 | P63: =P59+SUM($L62:P62) -> 0 | Q63: =Q59+SUM($L62:Q62) -> 0 | R63: =R59+SUM($L62:R62) -> 0 | S63: =S59+SUM($L62:S62) -> 0 | T63: =T59+SUM($L62:T62) -> 0 | ... BA63: =BA59+SUM($L62:BA62) -> 0
H64: Kumulatif arus netto (incl. Pillar 2) | L64: =L58+L63 -> 0 | M64: =M58+M63 -> 0 | N64: =N58+N63 -> 0 | O64: =O58+O63 -> 0 | P64: =P58+P63 -> 0 | Q64: =Q58+Q63 -> 0 | R64: =R58+R63 -> 0 | S64: =S58+S63 -> 0 | ... BA64: =BA58+BA63 -> 0
H65: Kumulatif arus netto (excl. Pillar 2) | L65: =L59+L58 -> 0 | M65: =M59+M58 -> 0 | N65: =N59+N58 -> 0 | O65: =O59+O58 -> 0 | P65: =P59+P58 -> 0 | Q65: =Q59+Q58 -> 0 | R65: =R59+R58 -> 0 | S65: =S59+S58 -> 0 | ... BA65: =BA59+BA58 -> 0
H66: Posisi likuiditas kumulatif (HQLA + arus masuk - [arus keluar + P2]) | L66: =L54+L64 -> 0 | M66: =M54+M64 -> 0 | N66: =N54+N64 -> 0 | O66: =O54+O64 -> 0 | P66: =P54+P64 -> 0 | Q66: =Q54+Q64 -> 0 | R66: =R54+R64 -> 0 | S66: =S54+S64 -> 0 | ... BA66: =BA54+BA64 -> 0
H67: LCR (own weighting) | L67: =K54/(ABS(AP59)-MIN(AP58,ABS(AP59)*75%)) -> #DIV/0!
H71: Skenario Bank (30d)
H72: Posisi likuiditas netto terkecil (dalam 1 bln ke depan) | K72: =MIN(Dashboard!M$66:AP$66) -> 0
H73: Hari atau bucket waktu di mana posisi likuiditas netto terkecil (dalam 1 bln ke depan) | K73: =INDEX(Dashboard!$M$13:$AP$13,1,MATCH(K72,Dashboard!M66:AP66,0)) -> O/N
H74: Kumulatif arus kas keluar tertinggi (arus kas dalam 1 bln tanpa HQLA) | K74: =MIN(M$63:AP$63) -> 0
H75: Posisi likuiditas netto terkecil (arus kas + HQLA, dalam 15 hari) | K75: =MIN(M$66:AA$66) -> 0
H76: Tanggal kegagalan likuiditas | K76: =IF(SUM(M$76:AP$76)>0,INDEX(Dashboard!M$12:AP$12,1,MATCH(1,M$76:AP$76,0)),"Di luar zona 30h") -> Di luar zona 30h | L76: =IF(Dashboard!L66>=0,0,1) -> 0 | M76: =IF(Dashboard!M66>=0,0,1) -> 0 | N76: =IF(Dashboard!N66>=0,0,1) -> 0 | O76: =IF(Dashboard!O66>=0,0,1) -> 0 | P76: =IF(Dashboard!P66>=0,0,1) -> 0 | Q76: =IF(Dashboard!Q66>=0,0,1) -> 0 | R76: =IF(Dashboard!R66>=0,0,1) -> 0 | S76: =IF(Dashboard!S66>=0,0,1) -> 0 | ... BA76: =IF(Dashboard!BA66>=0,0,1) -> 0
H77: Survival period | K77: =IF(K76="Di luar zona 30h",">30 hari",K76-Dashboard!K$12-1 & " hari") -> >30 hari
H78: Posisi likuiditas netto pada saat kegagalan likuiditas | K78: =IF(SUM(M$76:AP$76)>0,INDEX(M$66:AP$66,1,MATCH(1,M$76:AP$76,0)),"N/A") -> N/A
H80: Skenario Bank (90d)
H81: Posisi likuiditas netto terkecil (dalam 3 bln ke depan) | K81: =MIN(Dashboard!M$66:AS$66) -> 0
H82: Hari atau bucket waktu di mana posisi likuiditas netto terkecil (dalam 3 bln ke depan) | K82: =INDEX(Dashboard!$M$13:$AS$13,1,MATCH(K81,Dashboard!M66:AS66,0)) -> O/N
H83: Kumulatif arus kas keluar tertinggi (arus kas dalam 3 bln tanpa HQLA) | K83: =MIN(M$63:AS$63) -> 0
H84: Posisi likuiditas netto terkecil (arus kas + HQLA, dalam 2 bln ke depan) | K84: =MIN(M$66:AR$66) -> 0
H85: Tanggal kegagalan likuiditas | K85: =IF(SUM(M$85:AS$85)>0,INDEX(Dashboard!M$12:AS$12,1,MATCH(1,M$85:AS$85,0)),"Di luar zona 92h") -> Di luar zona 92h | L85: =IF(Dashboard!L66>=0,0,1) -> 0 | M85: =IF(Dashboard!M66>=0,0,1) -> 0 | N85: =IF(Dashboard!N66>=0,0,1) -> 0 | O85: =IF(Dashboard!O66>=0,0,1) -> 0 | P85: =IF(Dashboard!P66>=0,0,1) -> 0 | Q85: =IF(Dashboard!Q66>=0,0,1) -> 0 | R85: =IF(Dashboard!R66>=0,0,1) -> 0 | S85: =IF(Dashboard!S66>=0,0,1) -> 0 | ... BA85: =IF(Dashboard!BA66>=0,0,1) -> 0
H86: Survival period | K86: =IF(K85="Di luar zona 92h",">92 days",K85-Dashboard!K$12-1 &" hari") -> >92 days
H87: Posisi likuiditas netto pada saat kegagalan likuiditas | K87: =IF(SUM(M$85:AS$85)>0,INDEX(M$66:AS$66,1,MATCH(1,M$85:AS$85,0)),"N/A") -> N/A

Sheet Input Bank
BA10: (Dalam Jutaan Rupiah)
N12: =M12+1 -> 1 | O12: =N12+1 -> 2 | P12: =O12+1 -> 3 | Q12: =P12+1 -> 4 | R12: =Q12+1 -> 5 | S12: =R12+1 -> 6 | AQ12: =#REF!+7 -> #REF! | AR12: =AQ12+ROUNDDOWN(21/2,0) -> #REF! | AS12: =AR12+30/2 -> #REF! | AT12: =AS12+30/2 -> #REF! | AU12: =AT12+30/2 -> #REF! | AV12: =AU12+30/2 -> #REF! | AW12: =AV12+92/2 -> #REF! | AX12: =AW12+92/2 -> #REF! | AY12: =AX12+ROUNDDOWN(365/2,0) -> #REF! | AZ12: =AY12+ROUNDDOWN(3*365/2,) -> #REF! | BA12: =AZ12+3650/2 -> #REF!
G13: Kode | H13: Baris | I13: Item | J13: Bobot LCR | K13: Stok Awal | L13: Tanpa Maturitas (Open) | M13: Overnight (selain Open) | N13: Hari-2 | O13: Hari-3 | P13: ... | Q13: Hari-5 | R13: Hari-6 | S13: Hari-7 | T13: Hari-8 | U13: Hari-9 | V13: Hari-10 | W13: Hari-11 | X13: Hari-12 | Y13: Hari-13 | Z13: Hari-14 | AA13: Hari-15 | AB13: Hari-16 | AC13: Hari-17 | AD13: Hari-18 | AE13: Hari-19 | AF13: Hari-20 | AG13: Hari-21 | AH13: Hari-22 | AI13: Hari-23 | AJ13: Hari-24 | AK13: Hari-25 | AL13: Hari-26 | AM13: Hari-27 | AN13: Hari-28 | AO13: Hari-29 | AP13: Hari-30 | AQ13: > Minggu 4 s.d. Minggu 5 | AR13: > Minggu 5 s.d. 2 Bulan | AS13: > 2 Bulan s.d 3 Bulan | AT13: > 3 Bulan s.d 4 Bulan | AU13: > 4 Bulan s.d 5 Bulan | AV13: > 5 Bulan s.d 6 Bulan | AW13: > 6 Bulan s.d. 9 Bulan | AX13: > 9 Bulan s.d. 12 Bulan | AY13: > 12 Bulan s.d. 2 Bulan | AZ13: > 2 Tahun s.d. 5 Tahun | BA13: > 5 Tahun
G14: 001 | H14: 1 | I14: ARUS KAS KELUAR
G15: 002 | H15: 1.1 | I15: Kewajiban yang berasal dari simpanan yang diterima | L15: =SUM(L16:L30) -> 0 | M15: =SUM(M16:M30) -> 0 | N15: =SUM(N16:N30) -> 0 | O15: =SUM(O16:O30) -> 0 | P15: =SUM(P16:P30) -> 0 | Q15: =SUM(Q16:Q30) -> 0 | R15: =SUM(R16:R30) -> 0 | S15: =SUM(S16:S30) -> 0 | ... BA15: =SUM(BA16:BA30) -> 0
G16: 003 | H16: 1.1.1 | I16: Simpanan stabil dari Nasabah Perorangan | J16: 0.05
G17: 004 | H17: 1.1.2 | I17: Simpanan kurang stabil dari Nasabah Perorangan yang dijamin LPS | J17: 0.1
G18: 005 | H18: 1.1.3 | I18: Simpanan kurang stabil Nasabah Perorangan yang tidak dijamin LPS | J18: 0.1
G19: 006 | H19: 1.1.4 | I19: Pendanaan Stabil dari Nasabah Usaha Mikro dan Usaha Kecil | J19: 0.05
G20: 007 | H20: 1.1.5 | I20: Pendanaan kurang Stabil dari Nasabah Usaha Mikro dan Usaha Kecil yang dijamin LPS | J20: 0.1
G21: 008 | H21: 1.1.6 | I21: Pendanaan kurang Stabil dari Nasabah Usaha Mikro dan Usaha Kecil yang tidak dijamin LPS | J21: 0.1
G22: 009 | H22: 1.1.7 | I22: Simpanan operasional nasabah korporasi yang dijamin LPS | J22: 0.05
G23: 010 | H23: 1.1.8 | I23: Simpanan operasional nasabah korporasi yang tidak dijamin LPS | J23: 0.25
G24: 011 | H24: 1.1.9 | I24: Penarikan Simpanan Non-Operasional dan/atau kewajiban lainnya yang bersifat non-operasional dari:
G25: 012 | H25: 1.1.10 | I25: Bank | J25: 1
G26: 013 | H26: 1.1.11 | I26: LJK lainnya | J26: 1
G27: 014 | H27: 1.1.12 | I27: Korporasi non-finansial yang dijamin LPS | J27: 0.2
G28: 015 | H28: 1.1.13 | I28: Korporasi non-finansial yang tidak dijamin LPS | J28: 0.4
G29: 016 | H29: 1.1.14 | I29: Pemerintah pusat, Bank Indonesia, multilateral, dan entitas publik yang dijamin LPS | J29: 0.2
G30: 017 | H30: 1.1.15 | I30: Pemerintah pusat, Bank Indonesia, multilateral, dan entitas publik yang tidak dijamin LPS | J30: 0.4
G31: 018 | H31: 1.2 | I31: Kewajiban terkait efek yang diterbitkan | L31: =SUM(L32:L33) -> 0 | M31: =SUM(M32:M33) -> 0 | N31: =SUM(N32:N33) -> 0 | O31: =SUM(O32:O33) -> 0 | P31: =SUM(P32:P33) -> 0 | Q31: =SUM(Q32:Q33) -> 0 | R31: =SUM(R32:R33) -> 0 | S31: =SUM(S32:S33) -> 0 | ... BA31: =SUM(BA32:BA33) -> 0
G32: 019 | H32: 1.2.1 | I32: Surat berharga berupa surat utang yang diterbitkan Bank tanpa agunan | J32: 1
G33: 020 | H33: 1.2.2 | I33: Lainnya | J33: 1
G34: 021 | H34: 1.3 | I34: Pendanaan dengan agunan (secured funding) | L34: =SUM(L35,L42) -> 0 | M34: =SUM(M35,M42) -> 0 | N34: =SUM(N35,N42) -> 0 | O34: =SUM(O35,O42) -> 0 | P34: =SUM(P35,P42) -> 0 | Q34: =SUM(Q35,Q42) -> 0 | R34: =SUM(R35,R42) -> 0 | S34: =SUM(S35,S42) -> 0 | ... BA34: =SUM(BA35,BA42) -> 0
G35: 022 | H35: 1.3.1 | I35: Kewajiban timbul dari secured funding atau transaksi pasar modal dengan pihak lawan selain Bank Indonesia: | L35: =SUM(L36:L41) -> 0 | M35: =SUM(M36:M41) -> 0 | N35: =SUM(N36:N41) -> 0 | O35: =SUM(O36:O41) -> 0 | P35: =SUM(P36:P41) -> 0 | Q35: =SUM(Q36:Q41) -> 0 | R35: =SUM(R36:R41) -> 0 | S35: =SUM(S36:S41) -> 0 | ... BA35: =SUM(BA36:BA41) -> 0
G36: 023 | H36: 1.3.2 | I36: Transaksi dilakukan dengan agunan HQLA Level 1 | J36: 0
G37: 024 | H37: 1.3.3 | I37: Transaksi dilakukan dengan agunan HQLA Level 2A | J37: 0.15
G38: 025 | H38: 1.3.4 | I38: Transaksi dilakukan dengan Pemerintah Pusat atau entitas sektor publik yang memiliki bobot risiko paling tinggi 20% atau bank pembangunan multilateral, dengan agunan selain HQLA Level 1 atau HQLA Level 2A | J38: 0.25
G39: 026 | H39: 1.3.5 | I39: Transaksi dilakukan dengan agunan HQLA Level 2B berupa EBA | J39: 0.25
G40: 027 | H40: 1.3.6 | I40: Transaksi dilakukan dengan agunan HQLA Level 2B berupa selain EBA | J40: 0.5
G41: 028 | H41: 1.3.7 | I41: Transaksi dilakukan dengan agunan selain HQLA | J41: 1
G42: 029 | H42: 1.3.8 | I42: Kewajiban timbul dari secured funding atau transaksi pasar modal dengan Bank Indonesia sebagai pihak lawan: | L42: =SUM(L43:L47) -> 0 | M42: =SUM(M43:M47) -> 0 | N42: =SUM(N43:N47) -> 0 | O42: =SUM(O43:O47) -> 0 | P42: =SUM(P43:P47) -> 0 | Q42: =SUM(Q43:Q47) -> 0 | R42: =SUM(R43:R47) -> 0 | S42: =SUM(S43:S47) -> 0 | ... BA42: =SUM(BA43:BA47) -> 0
G43: 030 | H43: 1.3.9 | I43: Transaksi dilakukan dengan agunan HQLA Level 1 | J43: 0
G44: 031 | H44: 1.3.10 | I44: Transaksi dilakukan dengan agunan HQLA Level 2A | J44: 0
G45: 032 | H45: 1.3.11 | I45: Transaksi dilakukan dengan agunan HQLA Level 2B berupa EBA | J45: 0
G46: 033 | H46: 1.3.12 | I46: Transaksi dilakukan dengan agunan HQLA Level 2B berupa selain EBA | J46: 0
G47: 034 | H47: 1.3.13 | I47: Transaksi dilakukan dengan agunan selain HQLA | J47: 0
G48: 035 | H48: 1.4 | I48: FX-swaps jatuh tempo | J48: 1
G49: 036 | H49: 1.5 | I49: Arus kas keluar lainnya terkait transaksi derivatif selain 1.4 | J49: 1
G50: 037 | H50: 1.6 | I50: Arus kas keluar lainnya | J50: 1
G51: 038 | H51: 1.7 | I51: Total arus kas keluar | L51: =SUM(L15,L34,L48,L49,L50) -> 0 | M51: =SUM(M15,M31,M34,M48,M49,M50) -> 0 | N51: =SUM(N15,N31,N34,N48,N49,N50) -> 0 | O51: =SUM(O15,O31,O34,O48,O49,O50) -> 0 | P51: =SUM(P15,P31,P34,P48,P49,P50) -> 0 | Q51: =SUM(Q15,Q31,Q34,Q48,Q49,Q50) -> 0 | R51: =SUM(R15,R31,R34,R48,R49,R50) -> 0 | S51: =SUM(S15,S31,S34,S48,S49,S50) -> 0 | T51: =SUM(T15,T31,T34,T48,T49,T50) -> 0 | ... BA51: =SUM(BA15,BA31,BA34,BA48,BA49,BA50) -> 0
G52: 039 | H52: 2 | I52: ARUS KAS MASUK
G53: 040 | H53: 2.1 | I53: Pinjaman dengan Agunan (Secured Lending) | L53: =SUM(L54,L61) -> 0 | M53: =SUM(M54,M61) -> 0 | N53: =SUM(N54,N61) -> 0 | O53: =SUM(O54,O61) -> 0 | P53: =SUM(P54,P61) -> 0 | Q53: =SUM(Q54,Q61) -> 0 | R53: =SUM(R54,R61) -> 0 | S53: =SUM(S54,S61) -> 0 | ... BA53: =SUM(BA54,BA61) -> 0
G54: 041 | H54: 2.1.1 | I54: Agunan tidak digunakan kembali untuk menutupi posisi short nasabah | L54: =SUM(L55:L60) -> 0 | M54: =SUM(M55:M60) -> 0 | N54: =SUM(N55:N60) -> 0 | O54: =SUM(O55:O60) -> 0 | P54: =SUM(P55:P60) -> 0 | Q54: =SUM(Q55:Q60) -> 0 | R54: =SUM(R55:R60) -> 0 | S54: =SUM(S55:S60) -> 0 | ... BA54: =SUM(BA55:BA60) -> 0
G55: 042 | H55: 2.1.2 | I55: Agunan berupa HQLA Level 1 | J55: 0
G56: 043 | H56: 2.1.3 | I56: Agunan berupa HQLA Level 2A | J56: 0.15
G57: 044 | H57: 2.1.4 | I57: Agunan HQLA Level 2B berupa EBA | J57: 0.25
G58: 045 | H58: 2.1.5 | I58: Agunan HQLA Level 2B selain EBA | J58: 0.5
G59: 046 | H59: 2.1.6 | I59: Transaksi berupa margin lending namun agunan berupa selain HQLA | J59: 0.5
G60: 047 | H60: 2.1.7 | I60: Agunan tidak memenuhi persyaratan sebagaimana tersebut di atas | J60: 1
G61: 048 | H61: 2.1.8 | I61: Agunan digunakan kembali untuk menutupi posisi short nasabah | L61: =SUM(L62:L67) -> 0 | M61: =SUM(M62:M67) -> 0 | N61: =SUM(N62:N67) -> 0 | O61: =SUM(O62:O67) -> 0 | P61: =SUM(P62:P67) -> 0 | Q61: =SUM(Q62:Q67) -> 0 | R61: =SUM(R62:R67) -> 0 | S61: =SUM(S62:S67) -> 0 | ... BA61: =SUM(BA62:BA67) -> 0
G62: 049 | H62: 2.1.9 | I62: Agunan berupa HQLA Level 1 | J62: 0
G63: 050 | H63: 2.1.10 | I63: Agunan berupa HQLA Level 2A | J63: 0
G64: 051 | H64: 2.1.11 | I64: Agunan HQLA Level 2B berupa EBA | J64: 0
G65: 052 | H65: 2.1.12 | I65: Agunan HQLA Level 2B selain EBA | J65: 0
G66: 053 | H66: 2.1.13 | I66: Transaksi berupa margin lending namun agunan berupa selain HQLA | J66: 0
G67: 054 | H67: 2.1.14 | I67: Agunan tidak memenuhi persyaratan sebagaimana tersebut di atas | J67: 0
G68: 055 | H68: 2.2 | I68: Tagihan berdasarkan pihak lawan | L68: =SUM(L69:L75) -> 0 | M68: =SUM(M69:M75) -> 0 | N68: =SUM(N69:N75) -> 0 | O68: =SUM(O69:O75) -> 0 | P68: =SUM(P69:P75) -> 0 | Q68: =SUM(Q69:Q75) -> 0 | R68: =SUM(R69:R75) -> 0 | S68: =SUM(S69:S75) -> 0 | ... BA68: =SUM(BA69:BA75) -> 0
G69: 056 | H69: 2.2.1 | I69: Nasabah perorangan | J69: 0.5
G70: 057 | H70: 2.2.2 | I70: Nasabah UMK | J70: 0.5
G71: 058 | H71: 2.2.3 | I71: Korporasi non-finansial | J71: 0.5
G72: 059 | H72: 2.2.4 | I72: Lembaga jasa keuangan | J72: 1
G73: 060 | H73: 2.2.5 | I73: Bank Indonesia | J73: 1
G74: 061 | H74: 2.2.6 | I74: Entitas sektor publik | J74: 0.5
G75: 062 | H75: 2.2.7 | I75: Lainnya (Pemerintah Pusat, pemerintah negara lain, dan bank pembangunan multilateral) | J75: 0.5
G76: 063 | H76: 2.3 | I76: FX Swaps jatuh tempo | J76: 1
G77: 064 | H77: 2.4 | I77: Arus kas masuk dari Derivatif selain yang dilaporkan pada 2.3 | J77: 1
G78: 065 | H78: 2.5 | I78: Surat berharga yang jatuh tempo | L78: =SUM(L79:L80) -> 0 | M78: =SUM(M79:M80) -> 0 | N78: =SUM(N79:N80) -> 0 | O78: =SUM(O79:O80) -> 0 | P78: =SUM(P79:P80) -> 0 | Q78: =SUM(Q79:Q80) -> 0 | R78: =SUM(R79:R80) -> 0 | S78: =SUM(S79:S80) -> 0 | ... BA78: =SUM(BA79:BA80) -> 0
G79: 066 | H79: 2.5.1 | I79: Surat berharga non-HQLA yang jatuh tempo | J79: 1
G80: 067 | H80: 2.5.2 | I80: Surat berharga HQLA yang jatuh tempo | J80: 0
G81: 068 | H81: 2.6 | I81: Arus Kas Masuk dari tagihan kontraktual Lainnya | J81: 0.5
G82: 069 | H82: 2.7 | I82: Total Arus Kas Masuk | L82: =SUM(L53,L68,L76,L77,L78,L81) -> 0 | M82: =SUM(M53,M68,M76,M77,M78,M81) -> 0 | N82: =SUM(N53,N68,N76,N77,N78,N81) -> 0 | O82: =SUM(O53,O68,O76,O77,O78,O81) -> 0 | P82: =SUM(P53,P68,P76,P77,P78,P81) -> 0 | Q82: =SUM(Q53,Q68,Q76,Q77,Q78,Q81) -> 0 | R82: =SUM(R53,R68,R76,R77,R78,R81) -> 0 | S82: =SUM(S53,S68,S76,S77,S78,S81) -> 0 | ... BA82: =SUM(BA53,BA68,BA76,BA77,BA78,BA81) -> 0
G83: 070 | H83: 2.8 | I83: Net contractual gap | L83: =L51+L82 -> 0 | M83: =M51+M82 -> 0 | N83: =N51+N82 -> 0 | O83: =O51+O82 -> 0 | P83: =P51+P82 -> 0 | Q83: =Q51+Q82 -> 0 | R83: =R51+R82 -> 0 | S83: =S51+S82 -> 0 | ... BA83: =BA51+BA82 -> 0
G84: 071 | H84: 2.9 | I84: Gap arus kas keluar kumulatif netto | L84: =L83 -> 0 | M84: =L84+M83 -> 0 | N84: =M84+N83 -> 0 | O84: =N84+O83 -> 0 | P84: =O84+P83 -> 0 | Q84: =P84+Q83 -> 0 | R84: =Q84+R83 -> 0 | S84: =R84+S83 -> 0 | T84: =S84+T83 -> 0 | ... BA84: =AZ84+BA83 -> 0
G85: 072 | H85: 3 | I85: COUNTERBALANCING CAPACITY
G86: 073 | H86: 3.1 | I86: Kas dan setara kas | J86: 1
G87: 074 | H87: 3.2 | I87: Penempatan di Bank Indonesia yang dapat ditarik tanpa hambatan atau penalti | J87: 1
G88: 075 | H88: 3.3 | I88: HQLA Level 1 berupa surat berharga | J88: 1 | K88: =SUM(K89:K91) -> 0 | L88: =SUM(L89:L91) -> 0 | M88: =SUM(M89:M91) -> 0 | N88: =SUM(N89:N91) -> 0 | O88: =SUM(O89:O91) -> 0 | P88: =SUM(P89:P91) -> 0 | Q88: =SUM(Q89:Q91) -> 0 | R88: =SUM(R89:R91) -> 0 | ... BA88: =SUM(BA89:BA91) -> 0
G89: 076 | H89: 3.3.1 | I89: Diterbitkan atau dijamin pemerintah negara lain, bank sentral negara lain, entitas sektor publik, bank pembangunan multilateral, lembaga internasional yang memenuhi kriteria Pasal 10 ayat (1) huruf c POJK LCR | J89: 1
G90: 077 | H90: 3.3.2 | I90: Surat berharga yang diterbitkan Pemerintah Pusat dan Bank Indonesia dalam rupiah dan valuta asing yang memenuhi kriteria Pasal 10 ayat (1) huruf d dan e POJK LCR | J90: 1
G91: 078 | H91: 3.3.3 | I91: Surat berharga yang diterbitkan oleh pemerintah dan bank sentral negara lain dalam valuta asing dengan bobot risiko lebih dari 0% yang memenuhi kriteria Pasal 10 ayat (1) huruf f POJK LCR | J91: 1
G92: 079 | H92: 3.4 | I92: HQLA Level 2A | J92: 0.85 | K92: =SUM(K93:K94) -> 0 | L92: =SUM(L93:L94) -> 0 | M92: =SUM(M93:M94) -> 0 | N92: =SUM(N93:N94) -> 0 | O92: =SUM(O93:O94) -> 0 | P92: =SUM(P93:P94) -> 0 | Q92: =SUM(Q93:Q94) -> 0 | R92: =SUM(R93:R94) -> 0 | ... BA92: =SUM(BA93:BA94) -> 0
G93: 080 | H93: 3.4.1 | I93: Surat Berharga diterbitkan atau dijamin pemerintah negara lain, bank sentral negara lain, entitas sektor publik, bank pembangunan multilateral, lembaga internasional yang memenuhi kriteria Pasal 11 ayat (1) huruf a POJK LCR | J93: 0.85
G94: 081 | H94: 3.4.2 | I94: Surat Berharga berupa surat utang yang diterbitkan oleh korporasi termasuk commercial paper dan covered bonds yang memenuhi kriteria Pasal 11 ayat (1) huruf b POJK LCR | J94: 0.85
G95: 082 | H95: 3.5 | I95: HQLA Level 2B | J95: 0.75 | K95: =SUM(K96:K99) -> 0 | L95: =SUM(L96:L99) -> 0 | M95: =SUM(M96:M99) -> 0 | N95: =SUM(N96:N99) -> 0 | O95: =SUM(O96:O99) -> 0 | P95: =SUM(P96:P99) -> 0 | Q95: =SUM(Q96:Q99) -> 0 | R95: =SUM(R96:R99) -> 0 | ... BA95: =SUM(BA96:BA99) -> 0
G96: 083 | H96: 3.5.1 | I96: Efek beragun aset (EBA) berupa rumah tinggal yang memenuhi kriteria Pasal 12 ayat (1) huruf a POJK LCR | J96: 0.75
G97: 084 | H97: 3.5.2 | I97: Surat berharga yang diterbitkan atau dijamin oleh pemerintah negara lain, bank sentral negara lain, dan/atau entitas sektor publik yang memenuhi kriteria Pasal 12 ayat (1) huruf b POJK LCR | J97: 0.5
G98: 085 | H98: 3.5.3 | I98: Surat berharga berupa surat utang yang diterbitkan oleh korporasi yang memenuhi kriteria Pasal 12 ayat (1) huruf c POJK LCR | J98: 0.5
G99: 086 | H99: 3.5.4 | I99: Saham biasa yang dimiliki perusahaan anak bukan Bank yang memenuhi kriteria Pasal 12 ayat (1) huruf d POJK LCR | J99: 0.5
G100: 087 | H100: 3.6 | I100: Non-tradable asset eligible for BI facilities | J100: 0
G101: 088 | H101: 3.7 | I101: Aset tradable lainnya | J101: 0
G102: 089 | H102: 3.8 | I102: Komitmen fasilitas yang diterima namun belum ditarik | J102: 0 | K102: =SUM(K103:K104) -> 0 | L102: =SUM(L103:L104) -> 0 | M102: =SUM(M103:M104) -> 0 | N102: =SUM(N103:N104) -> 0 | O102: =SUM(O103:O104) -> 0 | P102: =SUM(P103:P104) -> 0 | Q102: =SUM(Q103:Q104) -> 0 | R102: =SUM(R103:R104) -> 0 | ... BA102: =SUM(BA103:BA104) -> 0
G103: 090 | H103: 3.8.1 | I103: Dari PSP, PSPT, dan Perusahaan Anak | J103: 0
G104: 091 | H104: 3.8.2 | I104: Dari entitas lainnya | J104: 0
G105: 092 | H105: 3.9 | I105: Perubahan netto Counterbalancing Capacity | L105: =L86+L87+L88+L92+L95+L100+L101+L102 -> 0 | M105: =M86+M87+M88+M92+M95+M100+M101+M102 -> 0 | N105: =N86+N87+N88+N92+N95+N100+N101+N102 -> 0 | O105: =O86+O87+O88+O92+O95+O100+O101+O102 -> 0 | P105: =P86+P87+P88+P92+P95+P100+P101+P102 -> 0 | Q105: =Q86+Q87+Q88+Q92+Q95+Q100+Q101+Q102 -> 0 | R105: =R86+R87+R88+R92+R95+R100+R101+R102 -> 0 | S105: =S86+S87+S88+S92+S95+S100+S101+S102 -> 0 | ... BA105: =BA86+BA87+BA88+BA92+BA95+BA100+BA101+BA102 -> 0
G106: 093 | H106: 3.10 | I106: Kumulatif Counterbalancing Capacity | K106: =K86+K87+K88+K92+K95+K100+K101+K102 -> 0 | L106: =K106+L105 -> 0 | M106: =L106+M105 -> 0 | N106: =M106+N105 -> 0 | O106: =N106+O105 -> 0 | P106: =O106+P105 -> 0 | Q106: =P106+Q105 -> 0 | R106: =Q106+R105 -> 0 | S106: =R106+S105 -> 0 | ... BA106: =AZ106+BA105 -> 0
G107: 094 | H107: 4 | I107: KONTINGENSI
G108: 095 | H108: 4.1 | I108: Arus kas keluar terkait peningkatan kebutuhan likuiditas | L108: =SUM(L109:L114) -> 0 | M108: =SUM(M109,M111:M114) -> 0 | N108: =SUM(N109,N111:N114) -> 0 | O108: =SUM(O109,O111:O114) -> 0 | P108: =SUM(P109,P111:P114) -> 0 | Q108: =SUM(Q109,Q111:Q114) -> 0 | R108: =SUM(R109,R111:R114) -> 0 | S108: =SUM(S109,S111:S114) -> 0 | T108: =SUM(T109,T111:T114) -> 0 | ... BA108: =SUM(BA109,BA111:BA114) -> 0
G109: 096 | H109: 4.1.1 | I109: Terkait dengan penurunan peringkat (rating) Bank dalam transaksi Pendanaan, derivatif, dan perjanjian lainnya | J109: 1
G110: 097 | H110: 4.1.2 | I110: Terkait dengan perubahan mark to market atas transaksi derivatif atau transaksi lainnya | J110: 1
...

Sheet Bobot
T9: Scenario 1 | W9: Scenario 1 | Z9: Scenario 1
F11: Kode | G11: Baris | H11: Item | I11: LCR weight | O11: Skenario Dasar | P11: Tenorisasi | T11: Skenario Bank 1 | W11: Skenario Bank 2 | Z11: Skenario Bank 3
I12: Input dari Bank | J12: Input dari Bank atau standar LCR bila input Bank kosong | K12: Supervisory range | M12: Bobot bila Input Pengawas diterapkan
K13: Standar minimum | L13: Standar maksimum | O13: EXPECTED WEIGHT / Standard weight | P13: 1 = Tenorised across 30 days | T13: open | U13: term | W13: open | X13: term | Z13: open | AA13: term
F14: 001 | G14: 1 | H14: ARUS KAS KELUAR
F15: 002 | G15: 1.1 | H15: Kewajiban yang berasal dari simpanan yang diterima
F16: 003 | G16: 1.1.1 | H16: Simpanan stabil dari Nasabah Perorangan | I16: ='Input Bank'!$J16 -> 0.05 | J16: =IF(I16="", K16, I16) -> 0.05 | K16: 0.05 | L16: 0.05 | M16: =MAX(MIN(L16, J16), K16) -> 0.05 | O16: =IF(Dashboard!$M$7="Input LCR bank",J16,M16) -> 0.05 | P16: 1
F17: 004 | G17: 1.1.2 | H17: Simpanan kurang stabil dari Nasabah Perorangan yang dijamin LPS | I17: ='Input Bank'!$J17 -> 0.1 | J17: =IF(I17="", K17, I17) -> 0.1 | K17: 0.1 | L17: 0.1 | M17: =MAX(MIN(L17, J17), K17) -> 0.1 | O17: =IF(Dashboard!$M$7="Input LCR bank",J17,M17) -> 0.1 | P17: 1
F18: 005 | G18: 1.1.3 | H18: Simpanan kurang stabil Nasabah Perorangan yang tidak dijamin LPS | I18: ='Input Bank'!$J18 -> 0.1 | J18: =IF(I18="", K18, I18) -> 0.1 | K18: 0.1 | L18: 0.1 | M18: =MAX(MIN(L18, J18), K18) -> 0.1 | O18: =IF(Dashboard!$M$7="Input LCR bank",J18,M18) -> 0.1 | P18: 1
F19: 006 | G19: 1.1.4 | H19: Pendanaan Stabil dari Nasabah Usaha Mikro dan Usaha Kecil | I19: ='Input Bank'!$J19 -> 0.05 | J19: =IF(I19="", K19, I19) -> 0.05 | K19: 0.05 | L19: 0.05 | M19: =MAX(MIN(L19, J19), K19) -> 0.05 | O19: =IF(Dashboard!$M$7="Input LCR bank",J19,M19) -> 0.05 | P19: 1
F20: 007 | G20: 1.1.5 | H20: Pendanaan kurang Stabil dari Nasabah Usaha Mikro dan Usaha Kecil yang dijamin LPS | I20: ='Input Bank'!$J20 -> 0.1 | J20: =IF(I20="", K20, I20) -> 0.1 | K20: 0.1 | L20: 0.1 | M20: =MAX(MIN(L20, J20), K20) -> 0.1 | O20: =IF(Dashboard!$M$7="Input LCR bank",J20,M20) -> 0.1 | P20: 1
F21: 008 | G21: 1.1.6 | H21: Pendanaan kurang Stabil dari Nasabah Usaha Mikro dan Usaha Kecil yang tidak dijamin LPS | I21: ='Input Bank'!$J21 -> 0.1 | J21: =IF(I21="", K21, I21) -> 0.1 | K21: 0.1 | L21: 0.1 | M21: =MAX(MIN(L21, J21), K21) -> 0.1 | O21: =IF(Dashboard!$M$7="Input LCR bank",J21,M21) -> 0.1 | P21: 1
F22: 009 | G22: 1.1.7 | H22: Simpanan operasional nasabah korporasi yang dijamin LPS | I22: ='Input Bank'!$J22 -> 0.05 | J22: =IF(I22="", K22, I22) -> 0.05 | K22: 0.05 | L22: 0.05 | M22: =MAX(MIN(L22, J22), K22) -> 0.05 | O22: =IF(Dashboard!$M$7="Input LCR bank",J22,M22) -> 0.05 | P22: 1
F23: 010 | G23: 1.1.8 | H23: Simpanan operasional nasabah korporasi yang tidak dijamin LPS | I23: ='Input Bank'!$J23 -> 0.25 | J23: =IF(I23="", K23, I23) -> 0.25 | K23: 0.25 | L23: 0.25 | M23: =MAX(MIN(L23, J23), K23) -> 0.25 | O23: =IF(Dashboard!$M$7="Input LCR bank",J23,M23) -> 0.25 | P23: 1
F24: 011 | G24: 1.1.9 | H24: Penarikan Simpanan Non-Operasional dan/atau kewajiban lainnya yang bersifat non-operasional dari:
F25: 012 | G25: 1.1.10 | H25: Bank | I25: ='Input Bank'!$J25 -> 1 | J25: =IF(I25="", K25, I25) -> 1 | K25: 1 | L25: 1 | M25: 1 | O25: =IF(Dashboard!$M$7="Input LCR bank",J25,M25) -> 1 | P25: 1
F26: 013 | G26: 1.1.11 | H26: LJK lainnya | I26: ='Input Bank'!$J26 -> 1 | J26: =IF(I26="", K26, I26) -> 1 | K26: 1 | L26: 1 | M26: =MAX(MIN(L26, J26), K26) -> 1 | O26: =IF(Dashboard!$M$7="Input LCR bank",J26,M26) -> 1 | P26: 1
F27: 014 | G27: 1.1.12 | H27: Korporasi non-finansial yang dijamin LPS | I27: ='Input Bank'!$J27 -> 0.2 | J27: =IF(I27="", K27, I27) -> 0.2 | K27: 0.2 | L27: 0.2 | M27: =MAX(MIN(L27, J27), K27) -> 0.2 | O27: =IF(Dashboard!$M$7="Input LCR bank",J27,M27) -> 0.2 | P27: 1
F28: 015 | G28: 1.1.13 | H28: Korporasi non-finansial yang tidak dijamin LPS | I28: ='Input Bank'!$J28 -> 0.4 | J28: =IF(I28="", K28, I28) -> 0.4 | K28: 0.4 | L28: 0.4 | M28: =MAX(MIN(L28, J28), K28) -> 0.4 | O28: =IF(Dashboard!$M$7="Input LCR bank",J28,M28) -> 0.4 | P28: 1
F29: 016 | G29: 1.1.14 | H29: Pemerintah pusat, Bank Indonesia, multilateral, dan entitas publik yang dijamin LPS | I29: ='Input Bank'!$J29 -> 0.2 | J29: =IF(I29="", L29, I29) -> 0.2 | K29: 0.2 | L29: 0.2 | M29: =MAX(MIN(L29, J29), K29) -> 0.2 | O29: =IF(Dashboard!$M$7="Input LCR bank",J29,M29) -> 0.2 | P29: 1
F30: 017 | G30: 1.1.15 | H30: Pemerintah pusat, Bank Indonesia, multilateral, dan entitas publik yang tidak dijamin LPS | I30: ='Input Bank'!$J30 -> 0.4 | J30: =IF(I30="", K30, I30) -> 0.4 | K30: 0.4 | L30: 0.4 | M30: =MAX(MIN(L30, J30), K30) -> 0.4 | O30: =IF(Dashboard!$M$7="Input LCR bank",J30,M30) -> 0.4 | P30: 1
F31: 018 | G31: 1.2 | H31: Kewajiban terkait efek yang diterbitkan
F32: 019 | G32: 1.2.1 | H32: Surat berharga berupa surat utang yang diterbitkan Bank tanpa agunan | I32: ='Input Bank'!$J32 -> 1 | J32: =IF(I32="", K32, I32) -> 1 | K32: 1 | L32: 1 | M32: =MAX(MIN(L32, J32), K32) -> 1 | O32: =IF(Dashboard!$M$7="Input LCR bank",J32,M32) -> 1
F33: 020 | G33: 1.2.2 | H33: Lainnya | I33: ='Input Bank'!$J33 -> 1 | J33: =IF(I33="", K33, I33) -> 1 | K33: 1 | L33: 1 | M33: =MAX(MIN(L33, J33), K33) -> 1 | O33: =IF(Dashboard!$M$7="Input LCR bank",J33,M33) -> 1
F34: 021 | G34: 1.3 | H34: Pendanaan dengan agunan (secured funding)
F35: 022 | G35: 1.3.1 | H35: Kewajiban timbul dari secured funding atau transaksi pasar modal dengan pihak lawan selain Bank Indonesia:
F36: 023 | G36: 1.3.2 | H36: Transaksi dilakukan dengan agunan HQLA Level 1 | I36: ='Input Bank'!$J36 -> 0 | J36: 0 | K36: 0 | L36: 1 | M36: =MAX(MIN(L36, J36), K36) -> 0 | O36: =IF(Dashboard!$M$7="Input LCR bank",J36,M36) -> 0
F37: 024 | G37: 1.3.3 | H37: Transaksi dilakukan dengan agunan HQLA Level 2A | I37: ='Input Bank'!$J37 -> 0.15 | J37: 0.15 | K37: 0.15 | L37: 1 | M37: =MAX(MIN(L37, J37), K37) -> 0.15 | O37: =IF(Dashboard!$M$7="Input LCR bank",J37,M37) -> 0.15
F38: 025 | G38: 1.3.4 | H38: Transaksi dilakukan dengan Pemerintah Pusat atau entitas sektor publik yang memiliki bobot risiko paling tinggi 20% atau bank pembangunan multilateral, dengan agunan selain HQLA Level 1 atau HQLA Level 2A | I38: ='Input Bank'!$J38 -> 0.25 | J38: 0.25 | K38: 0.25 | L38: 1 | M38: =MAX(MIN(L38, J38), K38) -> 0.25 | O38: =IF(Dashboard!$M$7="Input LCR bank",J38,M38) -> 0.25
F39: 026 | G39: 1.3.5 | H39: Transaksi dilakukan dengan agunan HQLA Level 2B berupa EBA | I39: ='Input Bank'!$J39 -> 0.25 | J39: 0.25 | K39: 0.25 | L39: 1 | M39: =MAX(MIN(L39, J39), K39) -> 0.25 | O39: =IF(Dashboard!$M$7="Input LCR bank",J39,M39) -> 0.25
F40: 027 | G40: 1.3.6 | H40: Transaksi dilakukan dengan agunan HQLA Level 2B berupa selain EBA | I40: ='Input Bank'!$J40 -> 0.5 | J40: 0.5 | K40: 0.3 | L40: 1 | M40: =MAX(MIN(L40, J40), K40) -> 0.5 | O40: =IF(Dashboard!$M$7="Input LCR bank",J40,M40) -> 0.5
F41: 028 | G41: 1.3.7 | H41: Transaksi dilakukan dengan agunan selain HQLA | I41: ='Input Bank'!$J41 -> 1 | J41: 1 | K41: 1 | L41: 1 | M41: =MAX(MIN(L41, J41), K41) -> 1 | O41: =IF(Dashboard!$M$7="Input LCR bank",J41,M41) -> 1
F42: 029 | G42: 1.3.8 | H42: Kewajiban timbul dari secured funding atau transaksi pasar modal dengan Bank Indonesia sebagai pihak lawan:
F43: 030 | G43: 1.3.9 | H43: Transaksi dilakukan dengan agunan HQLA Level 1 | I43: ='Input Bank'!$J43 -> 0 | J43: 0 | K43: 0 | L43: 0 | M43: 0 | O43: =IF(Dashboard!$M$7="Input LCR bank",J43,M43) -> 0
F44: 031 | G44: 1.3.10 | H44: Transaksi dilakukan dengan agunan HQLA Level 2A | I44: ='Input Bank'!$J44 -> 0 | J44: 0 | K44: 0 | L44: 0 | M44: 0 | O44: =IF(Dashboard!$M$7="Input LCR bank",J44,M44) -> 0
F45: 032 | G45: 1.3.11 | H45: Transaksi dilakukan dengan agunan HQLA Level 2B berupa EBA | I45: ='Input Bank'!$J45 -> 0 | J45: 0 | K45: 0 | L45: 0 | M45: 0 | O45: =IF(Dashboard!$M$7="Input LCR bank",J45,M45) -> 0
F46: 033 | G46: 1.3.12 | H46: Transaksi dilakukan dengan agunan HQLA Level 2B berupa selain EBA | I46: ='Input Bank'!$J46 -> 0 | J46: 0 | K46: 0 | L46: 0 | M46: 0 | O46: =IF(Dashboard!$M$7="Input LCR bank",J46,M46) -> 0
F47: 034 | G47: 1.3.13 | H47: Transaksi dilakukan dengan agunan selain HQLA | I47: ='Input Bank'!$J47 -> 0 | J47: 0 | K47: 0 | L47: 0 | M47: 0 | O47: =IF(Dashboard!$M$7="Input LCR bank",J47,M47) -> 0
F48: 035 | G48: 1.4 | H48: FX-swaps jatuh tempo | I48: ='Input Bank'!$J48 -> 1 | J48: =IF(I48="", K48, I48) -> 1 | K48: 1 | L48: 1 | M48: =MAX(MIN(L48, J48), K48) -> 1 | O48: =IF(Dashboard!$M$7="Input LCR bank",J48,M48) -> 1 | P48: 1
F49: 036 | G49: 1.5 | H49: Arus kas keluar lainnya terkait transaksi derivatif selain 1.4 | I49: ='Input Bank'!$J49 -> 1 | J49: =IF(I49="", L49, I49) -> 1 | K49: 0 | L49: 1 | M49: =MAX(MIN(L49, J49), K49) -> 1 | O49: =IF(Dashboard!$M$7="Input LCR bank",J49,M49) -> 1 | P49: 1
F50: 037 | G50: 1.6 | H50: Arus kas keluar lainnya | I50: ='Input Bank'!$J50 -> 1 | J50: =IF(I50="", L50, I50) -> 1 | K50: 0 | L50: 1 | M50: =MAX(MIN(L50, J50), K50) -> 1 | O50: =IF(Dashboard!$M$7="Input LCR bank",J50,M50) -> 1 | P50: 1
F51: 038 | G51: 1.7 | H51: Total arus kas keluar
F52: 039 | G52: 2 | H52: ARUS KAS MASUK
F53: 040 | G53: 2.1 | H53: Pinjaman dengan Agunan (Secured Lending)
F54: 041 | G54: 2.1.1 | H54: Agunan tidak digunakan kembali untuk menutupi posisi short nasabah
F55: 042 | G55: 2.1.2 | H55: Agunan berupa HQLA Level 1 | I55: ='Input Bank'!$J55 -> 0 | J55: =IF(I55="", L55, I55) -> 0 | K55: 0 | L55: 0 | M55: =MAX(MIN(L55, J55), K55) -> 0 | O55: =IF(Dashboard!$M$7="Input LCR bank",J55,M55) -> 0
F56: 043 | G56: 2.1.3 | H56: Agunan berupa HQLA Level 2A | I56: ='Input Bank'!$J56 -> 0.15 | J56: =IF(I56="", L56, I56) -> 0.15 | K56: 0.15 | L56: 0.15 | M56: =MAX(MIN(L56, J56), K56) -> 0.15 | O56: =IF(Dashboard!$M$7="Input LCR bank",J56,M56) -> 0.15
F57: 044 | G57: 2.1.4 | H57: Agunan HQLA Level 2B berupa EBA | I57: ='Input Bank'!$J57 -> 0.25 | J57: =IF(I57="", 0.3, I57) -> 0.25 | K57: 0.25 | L57: 0.25 | M57: =MAX(MIN(L57, J57), K57) -> 0.25 | O57: =IF(Dashboard!$M$7="Input LCR bank",J57,M57) -> 0.25
F58: 045 | G58: 2.1.5 | H58: Agunan HQLA Level 2B selain EBA | I58: ='Input Bank'!$J58 -> 0.5 | J58: =IF(I58="", L58, I58) -> 0.5 | K58: 0.5 | L58: 0.5 | M58: =MAX(MIN(L58, J58), K58) -> 0.5 | O58: =IF(Dashboard!$M$7="Input LCR bank",J58,M58) -> 0.5
F59: 046 | G59: 2.1.6 | H59: Transaksi berupa margin lending namun agunan berupa selain HQLA | I59: ='Input Bank'!$J59 -> 0.5 | J59: =IF(I59="", L59, I59) -> 0.5 | K59: 1 | L59: 1 | M59: =MAX(MIN(L59, J59), K59) -> 1 | O59: =IF(Dashboard!$M$7="Input LCR bank",J59,M59) -> 1
F60: 047 | G60: 2.1.7 | H60: Agunan tidak memenuhi persyaratan sebagaimana tersebut di atas | I60: ='Input Bank'!$J60 -> 1 | J60: =IF(I60="", L60, I60) -> 1 | K60: 0.5 | L60: 0.5 | M60: =MAX(MIN(L60, J60), K60) -> 0.5 | O60: =IF(Dashboard!$M$7="Input LCR bank",J60,M60) -> 0.5
F61: 048 | G61: 2.1.8 | H61: Agunan digunakan kembali untuk menutupi posisi short nasabah
F62: 049 | G62: 2.1.9 | H62: Agunan berupa HQLA Level 1 | I62: ='Input Bank'!$J62 -> 0 | J62: =IF(I62="", L62, I62) -> 0 | K62: 0 | L62: 0 | M62: =MAX(MIN(L62, J62), K62) -> 0 | O62: =IF(Dashboard!$M$7="Input LCR bank",J62,M62) -> 0
F63: 050 | G63: 2.1.10 | H63: Agunan berupa HQLA Level 2A | I63: ='Input Bank'!$J63 -> 0 | J63: =IF(I63="", L63, I63) -> 0 | K63: 0 | L63: 0 | M63: =MAX(MIN(L63, J63), K63) -> 0 | O63: =IF(Dashboard!$M$7="Input LCR bank",J63,M63) -> 0
F64: 051 | G64: 2.1.11 | H64: Agunan HQLA Level 2B berupa EBA | I64: ='Input Bank'!$J64 -> 0 | J64: =IF(I64="", L64, I64) -> 0 | K64: 0 | L64: 0 | M64: =MAX(MIN(L64, J64), K64) -> 0 | O64: =IF(Dashboard!$M$7="Input LCR bank",J64,M64) -> 0
F65: 052 | G65: 2.1.12 | H65: Agunan HQLA Level 2B selain EBA | I65: ='Input Bank'!$J65 -> 0 | J65: =IF(I65="", L65, I65) -> 0 | K65: 0 | L65: 0 | M65: =MAX(MIN(L65, J65), K65) -> 0 | O65: =IF(Dashboard!$M$7="Input LCR bank",J65,M65) -> 0
F66: 053 | G66: 2.1.13 | H66: Transaksi berupa margin lending namun agunan berupa selain HQLA | I66: ='Input Bank'!$J66 -> 0 | J66: =IF(I66="", L66, I66) -> 0 | K66: 0 | L66: 0 | M66: =MAX(MIN(L66, J66), K66) -> 0 | O66: =IF(Dashboard!$M$7="Input LCR bank",J66,M66) -> 0
F67: 054 | G67: 2.1.14 | H67: Agunan tidak memenuhi persyaratan sebagaimana tersebut di atas | I67: ='Input Bank'!$J67 -> 0 | J67: =IF(I67="", L67, I67) -> 0 | K67: 0 | L67: 0 | M67: =MAX(MIN(L67, J67), K67) -> 0 | O67: =IF(Dashboard!$M$7="Input LCR bank",J67,M67) -> 0
F68: 055 | G68: 2.2 | H68: Tagihan berdasarkan pihak lawan
F69: 056 | G69: 2.2.1 | H69: Nasabah perorangan | I69: ='Input Bank'!$J69 -> 0.5 | J69: =IF(I69="", L69, I69) -> 0.5 | K69: 0.5 | L69: 0.5 | M69: =MAX(MIN(L69, J69), K69) -> 0.5 | O69: =IF(Dashboard!$M$7="Input LCR bank",J69,M69) -> 0.5 | P69: 1
F70: 057 | G70: 2.2.2 | H70: Nasabah UMK | I70: ='Input Bank'!$J70 -> 0.5 | J70: =IF(I70="", L70, I70) -> 0.5 | K70: 0.5 | L70: 0.5 | M70: =MAX(MIN(L70, J70), K70) -> 0.5 | O70: =IF(Dashboard!$M$7="Input LCR bank",J70,M70) -> 0.5 | P70: 1
F71: 058 | G71: 2.2.3 | H71: Korporasi non-finansial | I71: ='Input Bank'!$J71 -> 0.5 | J71: =IF(I71="", L71, I71) -> 0.5 | K71: 0.5 | L71: 0.5 | M71: =MAX(MIN(L71, J71), K71) -> 0.5 | O71: =IF(Dashboard!$M$7="Input LCR bank",J71,M71) -> 0.5 | P71: 1
F72: 059 | G72: 2.2.4 | H72: Lembaga jasa keuangan | I72: ='Input Bank'!$J72 -> 1 | J72: =IF(I72="", L72, I72) -> 1 | K72: 1 | L72: 1 | M72: =MAX(MIN(L72, J72), K72) -> 1 | O72: =IF(Dashboard!$M$7="Input LCR bank",J72,M72) -> 1 | P72: 1
F73: 060 | G73: 2.2.5 | H73: Bank Indonesia | I73: ='Input Bank'!$J73 -> 1 | J73: =IF(I73="", L73, I73) -> 1 | K73: 1 | L73: 1 | M73: =MAX(MIN(L73, J73), K73) -> 1 | O73: =IF(Dashboard!$M$7="Input LCR bank",J73,M73) -> 1 | P73: 1
F74: 061 | G74: 2.2.6 | H74: Entitas sektor publik | I74: ='Input Bank'!$J74 -> 0.5 | J74: =IF(I74="", 0.5, I74) -> 0.5 | K74: 0.5 | L74: 0.5 | M74: =MAX(MIN(L74, J74), K74) -> 0.5 | O74: =IF(Dashboard!$M$7="Input LCR bank",J74,M74) -> 0.5 | P74: 1
F75: 062 | G75: 2.2.7 | H75: Lainnya (Pemerintah Pusat, pemerintah negara lain, dan bank pembangunan multilateral) | I75: ='Input Bank'!$J75 -> 0.5 | J75: =IF(I75="", 0.5, I75) -> 0.5 | K75: 0.5 | L75: 0.5 | M75: =MAX(MIN(L75, J75), K75) -> 0.5 | O75: =IF(Dashboard!$M$7="Input LCR bank",J75,M75) -> 0.5 | P75: 1
F76: 063 | G76: 2.3 | H76: FX Swaps jatuh tempo | I76: ='Input Bank'!$J76 -> 1 | J76: =IF(I76="", L76, I76) -> 1 | K76: 1 | L76: 1 | M76: =MAX(MIN(L76, J76), K76) -> 1 | O76: =IF(Dashboard!$M$7="Input LCR bank",J76,M76) -> 1 | P76: 1
F77: 064 | G77: 2.4 | H77: Arus kas masuk dari Derivatif selain yang dilaporkan pada 2.3 | I77: ='Input Bank'!$J77 -> 1 | J77: =IF(I77="", L77, I77) -> 1 | K77: 1 | L77: 1 | M77: =MAX(MIN(L77, J77), K77) -> 1 | O77: =IF(Dashboard!$M$7="Input LCR bank",J77,M77) -> 1 | P77: 1
F78: 065 | G78: 2.5 | H78: Surat berharga yang jatuh tempo
F79: 066 | G79: 2.5.1 | H79: Surat berharga non-HQLA yang jatuh tempo | I79: ='Input Bank'!$J79 -> 1 | J79: =IF(I79="", L79, I79) -> 1 | K79: 1 | L79: 1 | M79: =MAX(MIN(L79, J79), K79) -> 1 | O79: =IF(Dashboard!$M$7="Input LCR bank",J79,M79) -> 1
F80: 067 | G80: 2.5.2 | H80: Surat berharga HQLA yang jatuh tempo | I80: ='Input Bank'!$J80 -> 0 | J80: =IF(I80="", L80, I80) -> 0 | K80: 0 | L80: 0 | M80: =MAX(MIN(L80, J80), K80) -> 0 | O80: =IF(Dashboard!$M$7="Input LCR bank",J80,M80) -> 0
F81: 068 | G81: 2.6 | H81: Arus Kas Masuk dari tagihan kontraktual Lainnya | I81: ='Input Bank'!$J81 -> 0.5 | J81: =IF(I81="", L81, I81) -> 0.5 | K81: 0 | L81: 1 | M81: =MAX(MIN(L81, J81), K81) -> 0.5 | O81: =IF(Dashboard!$M$7="Input LCR bank",J81,M81) -> 0.5 | P81: 1
F82: 069 | G82: 2.7 | H82: Total Arus Kas Masuk
F83: 070 | G83: 2.8 | H83: Net contractual gap
F84: 071 | G84: 2.9 | H84: Gap arus kas keluar kumulatif netto
F85: 072 | G85: 3 | H85: COUNTERBALANCING CAPACITY
F86: 073 | G86: 3.1 | H86: Kas dan setara kas | I86: ='Input Bank'!$J86 -> 1 | J86: =IF(I86="", L86, I86) -> 1 | K86: 1 | L86: 1 | M86: =MAX(MIN(L86, J86), K86) -> 1 | O86: =IF(Dashboard!$M$7="Input LCR bank",J86,M86) -> 1
F87: 074 | G87: 3.2 | H87: Penempatan di Bank Indonesia yang dapat ditarik tanpa hambatan atau penalti | I87: ='Input Bank'!$J87 -> 1 | J87: =IF(I87="", L87, I87) -> 1 | K87: 1 | L87: 1 | M87: =MAX(MIN(L87, J87), K87) -> 1 | O87: =IF(Dashboard!$M$7="Input LCR bank",J87,M87) -> 1
F88: 075 | G88: 3.3 | H88: HQLA Level 1 berupa surat berharga | I88: ='Input Bank'!$J88 -> 1
F89: 076 | G89: 3.3.1 | H89: Diterbitkan atau dijamin pemerintah negara lain, bank sentral negara lain, entitas sektor publik, bank pembangunan multilateral, lembaga internasional yang memenuhi kriteria Pasal 10 ayat (1) huruf c POJK LCR | I89: ='Input Bank'!$J89 -> 1 | J89: =IF(I89="", L89, I89) -> 1 | K89: 1 | L89: 1 | M89: =MAX(MIN(L89, J89), K89) -> 1 | O89: =IF(Dashboard!$M$7="Input LCR bank",J89,M89) -> 1
F90: 077 | G90: 3.3.2 | H90: Surat berharga yang diterbitkan Pemerintah Pusat dan Bank Indonesia dalam rupiah dan valuta asing yang memenuhi kriteria Pasal 10 ayat (1) huruf d dan e POJK LCR | I90: ='Input Bank'!$J90 -> 1 | J90: =IF(I90="", L90, I90) -> 1 | K90: 1 | L90: 1 | M90: =MAX(MIN(L90, J90), K90) -> 1 | O90: =IF(Dashboard!$M$7="Input LCR bank",J90,M90) -> 1
F91: 078 | G91: 3.3.3 | H91: Surat berharga yang diterbitkan oleh pemerintah dan bank sentral negara lain dalam valuta asing dengan bobot risiko lebih dari 0% yang memenuhi kriteria Pasal 10 ayat (1) huruf f POJK LCR | I91: ='Input Bank'!$J91 -> 1 | J91: =IF(I91="", L91, I91) -> 1 | K91: 1 | L91: 1 | M91: =MAX(MIN(L91, J91), K91) -> 1 | O91: =IF(Dashboard!$M$7="Input LCR bank",J91,M91) -> 1
F92: 079 | G92: 3.4 | H92: HQLA Level 2A | I92: ='Input Bank'!$J92 -> 0.85
F93: 080 | G93: 3.4.1 | H93: Surat Berharga diterbitkan atau dijamin pemerintah negara lain, bank sentral negara lain, entitas sektor publik, bank pembangunan multilateral, lembaga internasional yang memenuhi kriteria Pasal 11 ayat (1) huruf a POJK LCR | I93: ='Input Bank'!$J93 -> 0.85 | J93: =IF(I93="", L93, I93) -> 0.85 | K93: 0.85 | L93: 0.85 | M93: =MAX(MIN(L93, J93), K93) -> 0.85 | O93: =IF(Dashboard!$M$7="Input LCR bank",J93,M93) -> 0.85
F94: 081 | G94: 3.4.2 | H94: Surat Berharga berupa surat utang yang diterbitkan oleh korporasi termasuk commercial paper dan covered bonds yang memenuhi kriteria Pasal 11 ayat (1) huruf b POJK LCR | I94: ='Input Bank'!$J94 -> 0.85 | J94: =IF(I94="", L94, I94) -> 0.85 | K94: 0.85 | L94: 0.85 | M94: =MAX(MIN(L94, J94), K94) -> 0.85 | O94: =IF(Dashboard!$M$7="Input LCR bank",J94,M94) -> 0.85
F95: 082 | G95: 3.5 | H95: HQLA Level 2B | I95: ='Input Bank'!$J95 -> 0.75
F96: 083 | G96: 3.5.1 | H96: Efek beragun aset (EBA) berupa rumah tinggal yang memenuhi kriteria Pasal 12 ayat (1) huruf a POJK LCR | I96: ='Input Bank'!$J96 -> 0.75 | J96: =IF(I96="", L96, I96) -> 0.75 | K96: 0.85 | L96: 0.85 | M96: =MAX(MIN(L96, J96), K96) -> 0.85 | O96: =IF(Dashboard!$M$7="Input LCR bank",J96,M96) -> 0.85
F97: 084 | G97: 3.5.2 | H97: Surat berharga yang diterbitkan atau dijamin oleh pemerintah negara lain, bank sentral negara lain, dan/atau entitas sektor publik yang memenuhi kriteria Pasal 12 ayat (1) huruf b POJK LCR | I97: ='Input Bank'!$J97 -> 0.5 | J97: =IF(I97="", L97, I97) -> 0.5 | K97: 0.85 | L97: 0.85 | M97: =MAX(MIN(L97, J97), K97) -> 0.85 | O97: =IF(Dashboard!$M$7="Input LCR bank",J97,M97) -> 0.85
F98: 085 | G98: 3.5.3 | H98: Surat berharga berupa surat utang yang diterbitkan oleh korporasi yang memenuhi kriteria Pasal 12 ayat (1) huruf c POJK LCR | I98: ='Input Bank'!$J98 -> 0.5 | J98: =IF(I98="", L98, I98) -> 0.5 | K98: 0.85 | L98: 0.85 | M98: =MAX(MIN(L98, J98), K98) -> 0.85 | O98: =IF(Dashboard!$M$7="Input LCR bank",J98,M98) -> 0.85
F99: 086 | G99: 3.5.4 | H99: Saham biasa yang dimiliki perusahaan anak bukan Bank yang memenuhi kriteria Pasal 12 ayat (1) huruf d POJK LCR | I99: ='Input Bank'!$J99 -> 0.5 | J99: =IF(I99="", L99, I99) -> 0.5 | K99: 0.85 | L99: 0.85 | M99: =MAX(MIN(L99, J99), K99) -> 0.85 | O99: =IF(Dashboard!$M$7="Input LCR bank",J99,M99) -> 0.85
F100: 087 | G100: 3.6 | H100: Non-tradable asset eligible for BI facilities | I100: ='Input Bank'!$J100 -> 0 | J100: =IF(I100="", L100, I100) -> 0 | K100: 0 | L100: 0 | M100: =MAX(MIN(L100, J100), K100) -> 0 | O100: =IF(Dashboard!$M$7="Input LCR bank",J100,M100) -> 0
F101: 088 | G101: 3.7 | H101: Aset tradable lainnya | I101: ='Input Bank'!$J101 -> 0 | J101: =IF(I101="", L101, I101) -> 0 | K101: 0 | L101: 0 | M101: =MAX(MIN(L101, J101), K101) -> 0 | O101: =IF(Dashboard!$M$7="Input LCR bank",J101,M101) -> 0
F102: 089 | G102: 3.8 | H102: Komitmen fasilitas yang diterima namun belum ditarik | I102: ='Input Bank'!$J102 -> 0
F103: 090 | G103: 3.8.1 | H103: Dari PSP, PSPT, dan Perusahaan Anak | I103: ='Input Bank'!$J103 -> 0 | J103: =IF(I103="", L103, I103) -> 0 | K103: 0 | L103: 0 | M103: =MAX(MIN(L103, J103), K103) -> 0 | O103: =IF(Dashboard!$M$7="Input LCR bank",J103,M103) -> 0
F104: 091 | G104: 3.8.2 | H104: Dari entitas lainnya | I104: ='Input Bank'!$J104 -> 0 | J104: =IF(I104="", L104, I104) -> 0 | K104: 0 | L104: 0 | M104: =MAX(MIN(L104, J104), K104) -> 0 | O104: =IF(Dashboard!$M$7="Input LCR bank",J104,M104) -> 0
F105: 092 | G105: 3.9 | H105: Perubahan netto Counterbalancing Capacity
F106: 093 | G106: 3.10 | H106: Kumulatif Counterbalancing Capacity
F107: 094 | G107: 4 | H107: KONTINGENSI
F108: 095 | G108: 4.1 | H108: Arus kas keluar terkait peningkatan kebutuhan likuiditas
F109: 096 | G109: 4.1.1 | H109: Terkait dengan penurunan peringkat (rating) Bank dalam transaksi Pendanaan, derivatif, dan perjanjian lainnya | I109: ='Input Bank'!$J109 -> 1 | J109: =IF(I109="", L109, I109) -> 1 | K109: 0 | L109: 1 | M109: =MAX(MIN(L109, J109), K109) -> 1 | O109: =IF(Dashboard!$M$7="Input LCR bank",J109,M109) -> 1 | P109: 1
...

Sheet SPM Skenario Dasar
H9: LCR (30 hari) & Benchmark (90 hari)
K11: =TEXT(K12,"ddd") -> MM/DD/YYYY
K12: ='Header & Notes'!J10 -> MM/DD/YYYY | AQ12: =#REF!+7 -> #REF! | AR12: =AQ12+ROUNDDOWN(21/2,0) -> #REF! | AS12: =AR12+30/2 -> #REF! | AT12: =AS12+30/2 -> #REF! | AU12: =AT12+30/2 -> #REF! | AV12: =AU12+30/2 -> #REF! | AW12: =AV12+92/2 -> #REF! | AX12: =AW12+92/2 -> #REF! | AY12: =AX12+ROUNDDOWN(365/2,0) -> #REF! | AZ12: =AY12+ROUNDDOWN(3*365/2,) -> #REF! | BA12: =AZ12+3650/2 -> #REF!
F13: Kode | G13: Baris | H13: Item | I13: Weight - open | J13: Weight - term | K13: Stok awal | L13: Tanpa Maturitas (Open) | M13: O/N (selain Open) | N13: Hari-2 | O13: Hari-3 | P13: Hari-4 | Q13: Hari-5 | R13: Hari-6 | S13: Hari-7 | T13: Hari-8 | U13: Hari-9 | V13: Hari-10 | W13: Hari-11 | X13: Hari-12 | Y13: Hari-13 | Z13: Hari-14 | AA13: Hari-15 | AB13: Hari-16 | AC13: Hari-17 | AD13: Hari-18 | AE13: Hari-19 | AF13: Hari-20 | AG13: Hari-21 | AH13: Hari-22 | AI13: Hari-23 | AJ13: Hari-24 | AK13: Hari-25 | AL13: Hari-26 | AM13: Hari-27 | AN13: Hari-28 | AO13: Hari-29 | AP13: Hari-30 | AQ13: > mg 4 s.d. mg 5 | AR13: > mg 5 s.d. 2 bln | AS13: > 2 bln s.d 3 bln | AT13: > 3 bln s.d 4 bln | AU13: > 4 bln s.d 5 bln | AV13: > 5 bln s.d 6 bln | AW13: > 6 bln s.d. 9 bln | AX13: > 9 bln s.d. 12 bln | AY13: > 12 bln s.d. 2 thn | AZ13: > 2 thn s.d. 5 thn | BA13: > 5 thn
F14: 001 | G14: 1 | H14: ARUS KAS KELUAR
A15: =Bobot!#REF! -> #REF! | F15: 002 | G15: 1.1 | H15: Kewajiban yang berasal dari simpanan yang diterima | L15: =SUM(L16:L30) -> 0 | M15: =SUM(M16:M30) -> 0 | N15: =SUM(N16:N30) -> 0 | O15: =SUM(O16:O30) -> 0 | P15: =SUM(P16:P30) -> 0 | Q15: =SUM(Q16:Q30) -> 0 | R15: =SUM(R16:R30) -> 0 | S15: =SUM(S16:S30) -> 0 | ... BA15: =SUM(BA16:BA30) -> 0
A16: =Bobot!#REF! -> #REF! | F16: 003 | G16: 1.1.1 | H16: Simpanan stabil dari Nasabah Perorangan | I16: =Bobot!O16 -> 0.05 | J16: =Bobot!O16 -> 0.05 | L16: =IF(Bobot!$P16=0,1,0)*('Input Bank'!L16+'Input Bank'!K16)*I16 -> 0 | M16: =Bobot!$P16*($I16*('Input Bank'!$K16+'Input Bank'!$L16)/30)+($J16*'Input Bank'!M16) -> 0 | N16: =Bobot!$P16*($I16*('Input Bank'!$K16+'Input Bank'!$L16)/30)+($J16*'Input Bank'!N16) -> 0 | O16: =Bobot!$P16*($I16*('Input Bank'!$K16+'Input Bank'!$L16)/30)+($J16*'Input Bank'!O16) -> 0 | P16: =Bobot!$P16*($I16*('Input Bank'!$K16+'Input Bank'!$L16)/30)+($J16*'Input Bank'!P16) -> 0 | Q16: =Bobot!$P16*($I16*('Input Bank'!$K16+'Input Bank'!$L16)/30)+($J16*'Input Bank'!Q16) -> 0 | R16: =Bobot!$P16*($I16*('Input Bank'!$K16+'Input Bank'!$L16)/30)+($J16*'Input Bank'!R16) -> 0 | S16: =Bobot!$P16*($I16*('Input Bank'!$K16+'Input Bank'!$L16)/30)+($J16*'Input Bank'!S16) -> 0 | T16: =Bobot!$P16*($I16*('Input Bank'!$K16+'Input Bank'!$L16)/30)+($J16*'Input Bank'!T16) -> 0 | ... AP16: =Bobot!$P16*($I16*('Input Bank'!$K16+'Input Bank'!$L16)/30)+($J16*'Input Bank'!AP16) -> 0 | AQ16: =$J16*'Input Bank'!AQ16 -> 0 | AR16: =$J16*'Input Bank'!AR16 -> 0 | AS16: =$J16*'Input Bank'!AS16 -> 0 | AT16: =$J16*'Input Bank'!AT16 -> 0 | AU16: =$J16*'Input Bank'!AU16 -> 0 | AV16: =$J16*'Input Bank'!AV16 -> 0 | AW16: =$J16*'Input Bank'!AW16 -> 0 | AX16: =$J16*'Input Bank'!AX16 -> 0 | ... BA16: =$J16*'Input Bank'!BA16 -> 0
A17: =Bobot!#REF! -> #REF! | F17: 004 | G17: 1.1.2 | H17: Simpanan kurang stabil dari Nasabah Perorangan yang dijamin LPS | I17: =Bobot!O17 -> 0.1 | J17: =Bobot!O17 -> 0.1 | L17: =IF(Bobot!$P17=0,1,0)*('Input Bank'!L17+'Input Bank'!K17)*I17 -> 0 | M17: =Bobot!$P17*($I17*('Input Bank'!$K17+'Input Bank'!$L17)/30)+($J17*'Input Bank'!M17) -> 0 | N17: =Bobot!$P17*($I17*('Input Bank'!$K17+'Input Bank'!$L17)/30)+($J17*'Input Bank'!N17) -> 0 | O17: =Bobot!$P17*($I17*('Input Bank'!$K17+'Input Bank'!$L17)/30)+($J17*'Input Bank'!O17) -> 0 | P17: =Bobot!$P17*($I17*('Input Bank'!$K17+'Input Bank'!$L17)/30)+($J17*'Input Bank'!P17) -> 0 | Q17: =Bobot!$P17*($I17*('Input Bank'!$K17+'Input Bank'!$L17)/30)+($J17*'Input Bank'!Q17) -> 0 | R17: =Bobot!$P17*($I17*('Input Bank'!$K17+'Input Bank'!$L17)/30)+($J17*'Input Bank'!R17) -> 0 | S17: =Bobot!$P17*($I17*('Input Bank'!$K17+'Input Bank'!$L17)/30)+($J17*'Input Bank'!S17) -> 0 | T17: =Bobot!$P17*($I17*('Input Bank'!$K17+'Input Bank'!$L17)/30)+($J17*'Input Bank'!T17) -> 0 | ... AP17: =Bobot!$P17*($I17*('Input Bank'!$K17+'Input Bank'!$L17)/30)+($J17*'Input Bank'!AP17) -> 0 | AQ17: =$J17*'Input Bank'!AQ17 -> 0 | AR17: =$J17*'Input Bank'!AR17 -> 0 | AS17: =$J17*'Input Bank'!AS17 -> 0 | AT17: =$J17*'Input Bank'!AT17 -> 0 | AU17: =$J17*'Input Bank'!AU17 -> 0 | AV17: =$J17*'Input Bank'!AV17 -> 0 | AW17: =$J17*'Input Bank'!AW17 -> 0 | AX17: =$J17*'Input Bank'!AX17 -> 0 | ... BA17: =$J17*'Input Bank'!BA17 -> 0
A18: =Bobot!#REF! -> #REF! | F18: 005 | G18: 1.1.3 | H18: Simpanan kurang stabil Nasabah Perorangan yang tidak dijamin LPS | I18: =Bobot!O18 -> 0.1 | J18: =Bobot!O18 -> 0.1 | L18: =IF(Bobot!$P18=0,1,0)*('Input Bank'!L18+'Input Bank'!K18)*I18 -> 0 | M18: =Bobot!$P18*($I18*('Input Bank'!$K18+'Input Bank'!$L18)/30)+($J18*'Input Bank'!M18) -> 0 | N18: =Bobot!$P18*($I18*('Input Bank'!$K18+'Input Bank'!$L18)/30)+($J18*'Input Bank'!N18) -> 0 | O18: =Bobot!$P18*($I18*('Input Bank'!$K18+'Input Bank'!$L18)/30)+($J18*'Input Bank'!O18) -> 0 | P18: =Bobot!$P18*($I18*('Input Bank'!$K18+'Input Bank'!$L18)/30)+($J18*'Input Bank'!P18) -> 0 | Q18: =Bobot!$P18*($I18*('Input Bank'!$K18+'Input Bank'!$L18)/30)+($J18*'Input Bank'!Q18) -> 0 | R18: =Bobot!$P18*($I18*('Input Bank'!$K18+'Input Bank'!$L18)/30)+($J18*'Input Bank'!R18) -> 0 | S18: =Bobot!$P18*($I18*('Input Bank'!$K18+'Input Bank'!$L18)/30)+($J18*'Input Bank'!S18) -> 0 | T18: =Bobot!$P18*($I18*('Input Bank'!$K18+'Input Bank'!$L18)/30)+($J18*'Input Bank'!T18) -> 0 | ... AP18: =Bobot!$P18*($I18*('Input Bank'!$K18+'Input Bank'!$L18)/30)+($J18*'Input Bank'!AP18) -> 0 | AQ18: =$J18*'Input Bank'!AQ18 -> 0 | AR18: =$J18*'Input Bank'!AR18 -> 0 | AS18: =$J18*'Input Bank'!AS18 -> 0 | AT18: =$J18*'Input Bank'!AT18 -> 0 | AU18: =$J18*'Input Bank'!AU18 -> 0 | AV18: =$J18*'Input Bank'!AV18 -> 0 | AW18: =$J18*'Input Bank'!AW18 -> 0 | AX18: =$J18*'Input Bank'!AX18 -> 0 | ... BA18: =$J18*'Input Bank'!BA18 -> 0
F19: 006 | G19: 1.1.4 | H19: Pendanaan Stabil dari Nasabah Usaha Mikro dan Usaha Kecil | I19: =Bobot!O19 -> 0.05 | J19: =Bobot!O19 -> 0.05 | L19: =IF(Bobot!$P19=0,1,0)*('Input Bank'!L19+'Input Bank'!K19)*I19 -> 0 | M19: =Bobot!$P19*($I19*('Input Bank'!$K19+'Input Bank'!$L19)/30)+($J19*'Input Bank'!M19) -> 0 | N19: =Bobot!$P19*($I19*('Input Bank'!$K19+'Input Bank'!$L19)/30)+($J19*'Input Bank'!N19) -> 0 | O19: =Bobot!$P19*($I19*('Input Bank'!$K19+'Input Bank'!$L19)/30)+($J19*'Input Bank'!O19) -> 0 | P19: =Bobot!$P19*($I19*('Input Bank'!$K19+'Input Bank'!$L19)/30)+($J19*'Input Bank'!P19) -> 0 | Q19: =Bobot!$P19*($I19*('Input Bank'!$K19+'Input Bank'!$L19)/30)+($J19*'Input Bank'!Q19) -> 0 | R19: =Bobot!$P19*($I19*('Input Bank'!$K19+'Input Bank'!$L19)/30)+($J19*'Input Bank'!R19) -> 0 | S19: =Bobot!$P19*($I19*('Input Bank'!$K19+'Input Bank'!$L19)/30)+($J19*'Input Bank'!S19) -> 0 | T19: =Bobot!$P19*($I19*('Input Bank'!$K19+'Input Bank'!$L19)/30)+($J19*'Input Bank'!T19) -> 0 | ... AP19: =Bobot!$P19*($I19*('Input Bank'!$K19+'Input Bank'!$L19)/30)+($J19*'Input Bank'!AP19) -> 0 | AQ19: =$J19*'Input Bank'!AQ19 -> 0 | AR19: =$J19*'Input Bank'!AR19 -> 0 | AS19: =$J19*'Input Bank'!AS19 -> 0 | AT19: =$J19*'Input Bank'!AT19 -> 0 | AU19: =$J19*'Input Bank'!AU19 -> 0 | AV19: =$J19*'Input Bank'!AV19 -> 0 | AW19: =$J19*'Input Bank'!AW19 -> 0 | AX19: =$J19*'Input Bank'!AX19 -> 0 | ... BA19: =$J19*'Input Bank'!BA19 -> 0
A20: =Bobot!P37 -> 0 | F20: 007 | G20: 1.1.5 | H20: Pendanaan kurang Stabil dari Nasabah Usaha Mikro dan Usaha Kecil yang dijamin LPS | I20: =Bobot!O20 -> 0.1 | J20: =Bobot!O20 -> 0.1 | L20: =IF(Bobot!$P20=0,1,0)*('Input Bank'!L20+'Input Bank'!K20)*I20 -> 0 | M20: =Bobot!$P20*($I20*('Input Bank'!$K20+'Input Bank'!$L20)/30)+($J20*'Input Bank'!M20) -> 0 | N20: =Bobot!$P20*($I20*('Input Bank'!$K20+'Input Bank'!$L20)/30)+($J20*'Input Bank'!N20) -> 0 | O20: =Bobot!$P20*($I20*('Input Bank'!$K20+'Input Bank'!$L20)/30)+($J20*'Input Bank'!O20) -> 0 | P20: =Bobot!$P20*($I20*('Input Bank'!$K20+'Input Bank'!$L20)/30)+($J20*'Input Bank'!P20) -> 0 | Q20: =Bobot!$P20*($I20*('Input Bank'!$K20+'Input Bank'!$L20)/30)+($J20*'Input Bank'!Q20) -> 0 | R20: =Bobot!$P20*($I20*('Input Bank'!$K20+'Input Bank'!$L20)/30)+($J20*'Input Bank'!R20) -> 0 | S20: =Bobot!$P20*($I20*('Input Bank'!$K20+'Input Bank'!$L20)/30)+($J20*'Input Bank'!S20) -> 0 | T20: =Bobot!$P20*($I20*('Input Bank'!$K20+'Input Bank'!$L20)/30)+($J20*'Input Bank'!T20) -> 0 | ... AP20: =Bobot!$P20*($I20*('Input Bank'!$K20+'Input Bank'!$L20)/30)+($J20*'Input Bank'!AP20) -> 0 | AQ20: =$J20*'Input Bank'!AQ20 -> 0 | AR20: =$J20*'Input Bank'!AR20 -> 0 | AS20: =$J20*'Input Bank'!AS20 -> 0 | AT20: =$J20*'Input Bank'!AT20 -> 0 | AU20: =$J20*'Input Bank'!AU20 -> 0 | AV20: =$J20*'Input Bank'!AV20 -> 0 | AW20: =$J20*'Input Bank'!AW20 -> 0 | AX20: =$J20*'Input Bank'!AX20 -> 0 | ... BA20: =$J20*'Input Bank'!BA20 -> 0
A21: =Bobot!#REF! -> #REF! | F21: 008 | G21: 1.1.6 | H21: Pendanaan kurang Stabil dari Nasabah Usaha Mikro dan Usaha Kecil yang tidak dijamin LPS | I21: =Bobot!O21 -> 0.1 | J21: =Bobot!O21 -> 0.1 | L21: =IF(Bobot!$P21=0,1,0)*('Input Bank'!L21+'Input Bank'!K21)*I21 -> 0 | M21: =Bobot!$P21*($I21*('Input Bank'!$K21+'Input Bank'!$L21)/30)+($J21*'Input Bank'!M21) -> 0 | N21: =Bobot!$P21*($I21*('Input Bank'!$K21+'Input Bank'!$L21)/30)+($J21*'Input Bank'!N21) -> 0 | O21: =Bobot!$P21*($I21*('Input Bank'!$K21+'Input Bank'!$L21)/30)+($J21*'Input Bank'!O21) -> 0 | P21: =Bobot!$P21*($I21*('Input Bank'!$K21+'Input Bank'!$L21)/30)+($J21*'Input Bank'!P21) -> 0 | Q21: =Bobot!$P21*($I21*('Input Bank'!$K21+'Input Bank'!$L21)/30)+($J21*'Input Bank'!Q21) -> 0 | R21: =Bobot!$P21*($I21*('Input Bank'!$K21+'Input Bank'!$L21)/30)+($J21*'Input Bank'!R21) -> 0 | S21: =Bobot!$P21*($I21*('Input Bank'!$K21+'Input Bank'!$L21)/30)+($J21*'Input Bank'!S21) -> 0 | T21: =Bobot!$P21*($I21*('Input Bank'!$K21+'Input Bank'!$L21)/30)+($J21*'Input Bank'!T21) -> 0 | ... AP21: =Bobot!$P21*($I21*('Input Bank'!$K21+'Input Bank'!$L21)/30)+($J21*'Input Bank'!AP21) -> 0 | AQ21: =$J21*'Input Bank'!AQ21 -> 0 | AR21: =$J21*'Input Bank'!AR21 -> 0 | AS21: =$J21*'Input Bank'!AS21 -> 0 | AT21: =$J21*'Input Bank'!AT21 -> 0 | AU21: =$J21*'Input Bank'!AU21 -> 0 | AV21: =$J21*'Input Bank'!AV21 -> 0 | AW21: =$J21*'Input Bank'!AW21 -> 0 | AX21: =$J21*'Input Bank'!AX21 -> 0 | ... BA21: =$J21*'Input Bank'!BA21 -> 0
A22: =Bobot!#REF! -> #REF! | F22: 009 | G22: 1.1.7 | H22: Simpanan operasional nasabah korporasi yang dijamin LPS | I22: =Bobot!O22 -> 0.05 | J22: =Bobot!O22 -> 0.05 | L22: =IF(Bobot!$P22=0,1,0)*('Input Bank'!L22+'Input Bank'!K22)*I22 -> 0 | M22: =Bobot!$P22*($I22*('Input Bank'!$K22+'Input Bank'!$L22)/30)+($J22*'Input Bank'!M22) -> 0 | N22: =Bobot!$P22*($I22*('Input Bank'!$K22+'Input Bank'!$L22)/30)+($J22*'Input Bank'!N22) -> 0 | O22: =Bobot!$P22*($I22*('Input Bank'!$K22+'Input Bank'!$L22)/30)+($J22*'Input Bank'!O22) -> 0 | P22: =Bobot!$P22*($I22*('Input Bank'!$K22+'Input Bank'!$L22)/30)+($J22*'Input Bank'!P22) -> 0 | Q22: =Bobot!$P22*($I22*('Input Bank'!$K22+'Input Bank'!$L22)/30)+($J22*'Input Bank'!Q22) -> 0 | R22: =Bobot!$P22*($I22*('Input Bank'!$K22+'Input Bank'!$L22)/30)+($J22*'Input Bank'!R22) -> 0 | S22: =Bobot!$P22*($I22*('Input Bank'!$K22+'Input Bank'!$L22)/30)+($J22*'Input Bank'!S22) -> 0 | T22: =Bobot!$P22*($I22*('Input Bank'!$K22+'Input Bank'!$L22)/30)+($J22*'Input Bank'!T22) -> 0 | ... AP22: =Bobot!$P22*($I22*('Input Bank'!$K22+'Input Bank'!$L22)/30)+($J22*'Input Bank'!AP22) -> 0 | AQ22: =$J22*'Input Bank'!AQ22 -> 0 | AR22: =$J22*'Input Bank'!AR22 -> 0 | AS22: =$J22*'Input Bank'!AS22 -> 0 | AT22: =$J22*'Input Bank'!AT22 -> 0 | AU22: =$J22*'Input Bank'!AU22 -> 0 | AV22: =$J22*'Input Bank'!AV22 -> 0 | AW22: =$J22*'Input Bank'!AW22 -> 0 | AX22: =$J22*'Input Bank'!AX22 -> 0 | ... BA22: =$J22*'Input Bank'!BA22 -> 0
A23: =Bobot!P39 -> 0 | F23: 010 | G23: 1.1.8 | H23: Simpanan operasional nasabah korporasi yang tidak dijamin LPS | I23: =Bobot!O23 -> 0.25 | J23: =Bobot!O23 -> 0.25 | L23: =IF(Bobot!$P23=0,1,0)*('Input Bank'!L23+'Input Bank'!K23)*I23 -> 0 | M23: =Bobot!$P23*($I23*('Input Bank'!$K23+'Input Bank'!$L23)/30)+($J23*'Input Bank'!M23) -> 0 | N23: =Bobot!$P23*($I23*('Input Bank'!$K23+'Input Bank'!$L23)/30)+($J23*'Input Bank'!N23) -> 0 | O23: =Bobot!$P23*($I23*('Input Bank'!$K23+'Input Bank'!$L23)/30)+($J23*'Input Bank'!O23) -> 0 | P23: =Bobot!$P23*($I23*('Input Bank'!$K23+'Input Bank'!$L23)/30)+($J23*'Input Bank'!P23) -> 0 | Q23: =Bobot!$P23*($I23*('Input Bank'!$K23+'Input Bank'!$L23)/30)+($J23*'Input Bank'!Q23) -> 0 | R23: =Bobot!$P23*($I23*('Input Bank'!$K23+'Input Bank'!$L23)/30)+($J23*'Input Bank'!R23) -> 0 | S23: =Bobot!$P23*($I23*('Input Bank'!$K23+'Input Bank'!$L23)/30)+($J23*'Input Bank'!S23) -> 0 | T23: =Bobot!$P23*($I23*('Input Bank'!$K23+'Input Bank'!$L23)/30)+($J23*'Input Bank'!T23) -> 0 | ... AP23: =Bobot!$P23*($I23*('Input Bank'!$K23+'Input Bank'!$L23)/30)+($J23*'Input Bank'!AP23) -> 0 | AQ23: =$J23*'Input Bank'!AQ23 -> 0 | AR23: =$J23*'Input Bank'!AR23 -> 0 | AS23: =$J23*'Input Bank'!AS23 -> 0 | AT23: =$J23*'Input Bank'!AT23 -> 0 | AU23: =$J23*'Input Bank'!AU23 -> 0 | AV23: =$J23*'Input Bank'!AV23 -> 0 | AW23: =$J23*'Input Bank'!AW23 -> 0 | AX23: =$J23*'Input Bank'!AX23 -> 0 | ... BA23: =$J23*'Input Bank'!BA23 -> 0
A24: =Bobot!#REF! -> #REF! | F24: 011 | G24: 1.1.9 | H24: Penarikan Simpanan Non-Operasional dan/atau kewajiban lainnya yang bersifat non-operasional dari: | I24: =Bobot!O24 -> 0 | J24: =Bobot!O24 -> 0
A25: =Bobot!#REF! -> #REF! | F25: 012 | G25: 1.1.10 | H25: Bank | I25: =Bobot!O25 -> 1 | J25: =Bobot!O25 -> 1 | L25: =IF(Bobot!$P25=0,1,0)*('Input Bank'!L26+'Input Bank'!K25)*I25 -> 0 | M25: =Bobot!$P25*($I25*('Input Bank'!$K25+'Input Bank'!$L25)/30)+($J25*'Input Bank'!M25) -> 0 | N25: =Bobot!$P25*($I25*('Input Bank'!$K25+'Input Bank'!$L25)/30)+($J25*'Input Bank'!N25) -> 0 | O25: =Bobot!$P25*($I25*('Input Bank'!$K25+'Input Bank'!$L25)/30)+($J25*'Input Bank'!O25) -> 0 | P25: =Bobot!$P25*($I25*('Input Bank'!$K25+'Input Bank'!$L25)/30)+($J25*'Input Bank'!P25) -> 0 | Q25: =Bobot!$P25*($I25*('Input Bank'!$K25+'Input Bank'!$L25)/30)+($J25*'Input Bank'!Q25) -> 0 | R25: =Bobot!$P25*($I25*('Input Bank'!$K25+'Input Bank'!$L25)/30)+($J25*'Input Bank'!R25) -> 0 | S25: =Bobot!$P25*($I25*('Input Bank'!$K25+'Input Bank'!$L25)/30)+($J25*'Input Bank'!S25) -> 0 | T25: =Bobot!$P25*($I25*('Input Bank'!$K25+'Input Bank'!$L25)/30)+($J25*'Input Bank'!T25) -> 0 | ... AP25: =Bobot!$P25*($I25*('Input Bank'!$K25+'Input Bank'!$L25)/30)+($J25*'Input Bank'!AP25) -> 0 | AQ25: =$J25*'Input Bank'!AQ25 -> 0 | AR25: =$J25*'Input Bank'!AR25 -> 0 | AS25: =$J25*'Input Bank'!AS25 -> 0 | AT25: =$J25*'Input Bank'!AT25 -> 0 | AU25: =$J25*'Input Bank'!AU25 -> 0 | AV25: =$J25*'Input Bank'!AV25 -> 0 | AW25: =$J25*'Input Bank'!AW25 -> 0 | AX25: =$J25*'Input Bank'!AX25 -> 0 | ... BA25: =$J25*'Input Bank'!BA25 -> 0
A26: =Bobot!#REF! -> #REF! | F26: 013 | G26: 1.1.11 | H26: LJK lainnya | I26: =Bobot!O26 -> 1 | J26: =Bobot!O26 -> 1 | L26: =IF(Bobot!$P26=0,1,0)*('Input Bank'!L26+'Input Bank'!K26)*I26 -> 0 | M26: =Bobot!$P26*($I26*('Input Bank'!$K26+'Input Bank'!$L26)/30)+($J26*'Input Bank'!M26) -> 0 | N26: =Bobot!$P26*($I26*('Input Bank'!$K26+'Input Bank'!$L26)/30)+($J26*'Input Bank'!N26) -> 0 | O26: =Bobot!$P26*($I26*('Input Bank'!$K26+'Input Bank'!$L26)/30)+($J26*'Input Bank'!O26) -> 0 | P26: =Bobot!$P26*($I26*('Input Bank'!$K26+'Input Bank'!$L26)/30)+($J26*'Input Bank'!P26) -> 0 | Q26: =Bobot!$P26*($I26*('Input Bank'!$K26+'Input Bank'!$L26)/30)+($J26*'Input Bank'!Q26) -> 0 | R26: =Bobot!$P26*($I26*('Input Bank'!$K26+'Input Bank'!$L26)/30)+($J26*'Input Bank'!R26) -> 0 | S26: =Bobot!$P26*($I26*('Input Bank'!$K26+'Input Bank'!$L26)/30)+($J26*'Input Bank'!S26) -> 0 | T26: =Bobot!$P26*($I26*('Input Bank'!$K26+'Input Bank'!$L26)/30)+($J26*'Input Bank'!T26) -> 0 | ... AP26: =Bobot!$P26*($I26*('Input Bank'!$K26+'Input Bank'!$L26)/30)+($J26*'Input Bank'!AP26) -> 0 | AQ26: =$J26*'Input Bank'!AQ26 -> 0 | AR26: =$J26*'Input Bank'!AR26 -> 0 | AS26: =$J26*'Input Bank'!AS26 -> 0 | AT26: =$J26*'Input Bank'!AT26 -> 0 | AU26: =$J26*'Input Bank'!AU26 -> 0 | AV26: =$J26*'Input Bank'!AV26 -> 0 | AW26: =$J26*'Input Bank'!AW26 -> 0 | AX26: =$J26*'Input Bank'!AX26 -> 0 | ... BA26: =$J26*'Input Bank'!BA26 -> 0
A27: =Bobot!#REF! -> #REF! | F27: 014 | G27: 1.1.12 | H27: Korporasi non-finansial yang dijamin LPS | I27: =Bobot!O27 -> 0.2 | J27: =Bobot!O27 -> 0.2 | L27: =IF(Bobot!$P27=0,1,0)*('Input Bank'!L27+'Input Bank'!K27)*I27 -> 0 | M27: =Bobot!$P27*($I27*('Input Bank'!$K27+'Input Bank'!$L27)/30)+($J27*'Input Bank'!M27) -> 0 | N27: =Bobot!$P27*($I27*('Input Bank'!$K27+'Input Bank'!$L27)/30)+($J27*'Input Bank'!N27) -> 0 | O27: =Bobot!$P27*($I27*('Input Bank'!$K27+'Input Bank'!$L27)/30)+($J27*'Input Bank'!O27) -> 0 | P27: =Bobot!$P27*($I27*('Input Bank'!$K27+'Input Bank'!$L27)/30)+($J27*'Input Bank'!P27) -> 0 | Q27: =Bobot!$P27*($I27*('Input Bank'!$K27+'Input Bank'!$L27)/30)+($J27*'Input Bank'!Q27) -> 0 | R27: =Bobot!$P27*($I27*('Input Bank'!$K27+'Input Bank'!$L27)/30)+($J27*'Input Bank'!R27) -> 0 | S27: =Bobot!$P27*($I27*('Input Bank'!$K27+'Input Bank'!$L27)/30)+($J27*'Input Bank'!S27) -> 0 | T27: =Bobot!$P27*($I27*('Input Bank'!$K27+'Input Bank'!$L27)/30)+($J27*'Input Bank'!T27) -> 0 | ... AP27: =Bobot!$P27*($I27*('Input Bank'!$K27+'Input Bank'!$L27)/30)+($J27*'Input Bank'!AP27) -> 0 | AQ27: =$J27*'Input Bank'!AQ27 -> 0 | AR27: =$J27*'Input Bank'!AR27 -> 0 | AS27: =$J27*'Input Bank'!AS27 -> 0 | AT27: =$J27*'Input Bank'!AT27 -> 0 | AU27: =$J27*'Input Bank'!AU27 -> 0 | AV27: =$J27*'Input Bank'!AV27 -> 0 | AW27: =$J27*'Input Bank'!AW27 -> 0 | AX27: =$J27*'Input Bank'!AX27 -> 0 | ... BA27: =$J27*'Input Bank'!BA27 -> 0
A28: =Bobot!#REF! -> #REF! | F28: 015 | G28: 1.1.13 | H28: Korporasi non-finansial yang tidak dijamin LPS | I28: =Bobot!O28 -> 0.4 | J28: =Bobot!O28 -> 0.4 | L28: =IF(Bobot!$P28=0,1,0)*('Input Bank'!L28+'Input Bank'!K28)*I28 -> 0 | M28: =Bobot!$P28*($I28*('Input Bank'!$K28+'Input Bank'!$L28)/30)+($J28*'Input Bank'!M28) -> 0 | N28: =Bobot!$P28*($I28*('Input Bank'!$K28+'Input Bank'!$L28)/30)+($J28*'Input Bank'!N28) -> 0 | O28: =Bobot!$P28*($I28*('Input Bank'!$K28+'Input Bank'!$L28)/30)+($J28*'Input Bank'!O28) -> 0 | P28: =Bobot!$P28*($I28*('Input Bank'!$K28+'Input Bank'!$L28)/30)+($J28*'Input Bank'!P28) -> 0 | Q28: =Bobot!$P28*($I28*('Input Bank'!$K28+'Input Bank'!$L28)/30)+($J28*'Input Bank'!Q28) -> 0 | R28: =Bobot!$P28*($I28*('Input Bank'!$K28+'Input Bank'!$L28)/30)+($J28*'Input Bank'!R28) -> 0 | S28: =Bobot!$P28*($I28*('Input Bank'!$K28+'Input Bank'!$L28)/30)+($J28*'Input Bank'!S28) -> 0 | T28: =Bobot!$P28*($I28*('Input Bank'!$K28+'Input Bank'!$L28)/30)+($J28*'Input Bank'!T28) -> 0 | ... AP28: =Bobot!$P28*($I28*('Input Bank'!$K28+'Input Bank'!$L28)/30)+($J28*'Input Bank'!AP28) -> 0 | AQ28: =$J28*'Input Bank'!AQ28 -> 0 | AR28: =$J28*'Input Bank'!AR28 -> 0 | AS28: =$J28*'Input Bank'!AS28 -> 0 | AT28: =$J28*'Input Bank'!AT28 -> 0 | AU28: =$J28*'Input Bank'!AU28 -> 0 | AV28: =$J28*'Input Bank'!AV28 -> 0 | AW28: =$J28*'Input Bank'!AW28 -> 0 | AX28: =$J28*'Input Bank'!AX28 -> 0 | ... BA28: =$J28*'Input Bank'!BA28 -> 0
A29: =Bobot!#REF! -> #REF! | F29: 016 | G29: 1.1.14 | H29: Pemerintah pusat, Bank Indonesia, multilateral dan entitas publik yang dijamin LPS | I29: =Bobot!O29 -> 0.2 | J29: =Bobot!O29 -> 0.2 | L29: =IF(Bobot!$P29=0,1,0)*('Input Bank'!L29+'Input Bank'!K29)*I29 -> 0 | M29: =Bobot!$P29*($I29*('Input Bank'!$K29+'Input Bank'!$L29)/30)+($J29*'Input Bank'!M29) -> 0 | N29: =Bobot!$P29*($I29*('Input Bank'!$K29+'Input Bank'!$L29)/30)+($J29*'Input Bank'!N29) -> 0 | O29: =Bobot!$P29*($I29*('Input Bank'!$K29+'Input Bank'!$L29)/30)+($J29*'Input Bank'!O29) -> 0 | P29: =Bobot!$P29*($I29*('Input Bank'!$K29+'Input Bank'!$L29)/30)+($J29*'Input Bank'!P29) -> 0 | Q29: =Bobot!$P29*($I29*('Input Bank'!$K29+'Input Bank'!$L29)/30)+($J29*'Input Bank'!Q29) -> 0 | R29: =Bobot!$P29*($I29*('Input Bank'!$K29+'Input Bank'!$L29)/30)+($J29*'Input Bank'!R29) -> 0 | S29: =Bobot!$P29*($I29*('Input Bank'!$K29+'Input Bank'!$L29)/30)+($J29*'Input Bank'!S29) -> 0 | T29: =Bobot!$P29*($I29*('Input Bank'!$K29+'Input Bank'!$L29)/30)+($J29*'Input Bank'!T29) -> 0 | ... AP29: =Bobot!$P29*($I29*('Input Bank'!$K29+'Input Bank'!$L29)/30)+($J29*'Input Bank'!AP29) -> 0 | AQ29: =$J29*'Input Bank'!AQ29 -> 0 | AR29: =$J29*'Input Bank'!AR29 -> 0 | AS29: =$J29*'Input Bank'!AS29 -> 0 | AT29: =$J29*'Input Bank'!AT29 -> 0 | AU29: =$J29*'Input Bank'!AU29 -> 0 | AV29: =$J29*'Input Bank'!AV29 -> 0 | AW29: =$J29*'Input Bank'!AW29 -> 0 | AX29: =$J29*'Input Bank'!AX29 -> 0 | ... BA29: =$J29*'Input Bank'!BA29 -> 0
A30: =Bobot!#REF! -> #REF! | F30: 017 | G30: 1.1.15 | H30: Pemerintah pusat, Bank Indonesia, multilateral dan entitas publik yang tidak dijamin LPS | I30: =Bobot!O30 -> 0.4 | J30: =Bobot!O30 -> 0.4 | L30: =IF(Bobot!$P30=0,1,0)*('Input Bank'!L30+'Input Bank'!K30)*I30 -> 0 | M30: =Bobot!$P30*($I30*('Input Bank'!$K30+'Input Bank'!$L30)/30)+($J30*'Input Bank'!M30) -> 0 | N30: =Bobot!$P30*($I30*('Input Bank'!$K30+'Input Bank'!$L30)/30)+($J30*'Input Bank'!N30) -> 0 | O30: =Bobot!$P30*($I30*('Input Bank'!$K30+'Input Bank'!$L30)/30)+($J30*'Input Bank'!O30) -> 0 | P30: =Bobot!$P30*($I30*('Input Bank'!$K30+'Input Bank'!$L30)/30)+($J30*'Input Bank'!P30) -> 0 | Q30: =Bobot!$P30*($I30*('Input Bank'!$K30+'Input Bank'!$L30)/30)+($J30*'Input Bank'!Q30) -> 0 | R30: =Bobot!$P30*($I30*('Input Bank'!$K30+'Input Bank'!$L30)/30)+($J30*'Input Bank'!R30) -> 0 | S30: =Bobot!$P30*($I30*('Input Bank'!$K30+'Input Bank'!$L30)/30)+($J30*'Input Bank'!S30) -> 0 | T30: =Bobot!$P30*($I30*('Input Bank'!$K30+'Input Bank'!$L30)/30)+($J30*'Input Bank'!T30) -> 0 | ... AP30: =Bobot!$P30*($I30*('Input Bank'!$K30+'Input Bank'!$L30)/30)+($J30*'Input Bank'!AP30) -> 0 | AQ30: =$J30*'Input Bank'!AQ30 -> 0 | AR30: =$J30*'Input Bank'!AR30 -> 0 | AS30: =$J30*'Input Bank'!AS30 -> 0 | AT30: =$J30*'Input Bank'!AT30 -> 0 | AU30: =$J30*'Input Bank'!AU30 -> 0 | AV30: =$J30*'Input Bank'!AV30 -> 0 | AW30: =$J30*'Input Bank'!AW30 -> 0 | AX30: =$J30*'Input Bank'!AX30 -> 0 | ... BA30: =$J30*'Input Bank'!BA30 -> 0
A31: =Bobot!P31 -> 0 | F31: 018 | G31: 1.2 | H31: Kewajiban terkait efek yang diterbitkan | L31: =SUM(L32:L33) -> 0 | M31: =SUM(M32:M33) -> 0 | N31: =SUM(N32:N33) -> 0 | O31: =SUM(O32:O33) -> 0 | P31: =SUM(P32:P33) -> 0 | Q31: =SUM(Q32:Q33) -> 0 | R31: =SUM(R32:R33) -> 0 | S31: =SUM(S32:S33) -> 0 | ... BA31: =SUM(BA32:BA33) -> 0
A32: =Bobot!P32 -> 0 | F32: 019 | G32: 1.2.1 | H32: Surat berharga berupa surat utang yang diterbitkan Bank tanpa agunan | I32: =Bobot!O32 -> 1 | J32: =Bobot!O32 -> 1 | M32: =$J32*'Input Bank'!M32 -> 0 | N32: =$J32*'Input Bank'!N32 -> 0 | O32: =$J32*'Input Bank'!O32 -> 0 | P32: =$J32*'Input Bank'!P32 -> 0 | Q32: =$J32*'Input Bank'!Q32 -> 0 | R32: =$J32*'Input Bank'!R32 -> 0 | S32: =$J32*'Input Bank'!S32 -> 0 | T32: =$J32*'Input Bank'!T32 -> 0 | ... BA32: =$J32*'Input Bank'!BA32 -> 0
A33: =Bobot!#REF! -> #REF! | F33: 020 | G33: 1.2.2 | H33: Lainnya | I33: =Bobot!O33 -> 1 | J33: =Bobot!O33 -> 1 | M33: =$J33*'Input Bank'!M33 -> 0 | N33: =$J33*'Input Bank'!N33 -> 0 | O33: =$J33*'Input Bank'!O33 -> 0 | P33: =$J33*'Input Bank'!P33 -> 0 | Q33: =$J33*'Input Bank'!Q33 -> 0 | R33: =$J33*'Input Bank'!R33 -> 0 | S33: =$J33*'Input Bank'!S33 -> 0 | T33: =$J33*'Input Bank'!T33 -> 0 | ... BA33: =$J33*'Input Bank'!BA33 -> 0
F34: 021 | G34: 1.3 | H34: Pendanaan dengan agunan (secured funding) | L34: =SUM(L35,L42) -> 0 | M34: =SUM(M35,M42) -> 0 | N34: =SUM(N35,N42) -> 0 | O34: =SUM(O35,O42) -> 0 | P34: =SUM(P35,P42) -> 0 | Q34: =SUM(Q35,Q42) -> 0 | R34: =SUM(R35,R42) -> 0 | S34: =SUM(S35,S42) -> 0 | ... BA34: =SUM(BA35,BA42) -> 0
A35: =Bobot!#REF! -> #REF! | F35: 022 | G35: 1.3.1 | H35: Kewajiban timbul dari secured funding atau transaksi pasar modal dengan pihak lawan selain Bank Indonesia: | L35: =SUM(L36:L41) -> 0 | M35: =SUM(M36:M41) -> 0 | N35: =SUM(N36:N41) -> 0 | O35: =SUM(O36:O41) -> 0 | P35: =SUM(P36:P41) -> 0 | Q35: =SUM(Q36:Q41) -> 0 | R35: =SUM(R36:R41) -> 0 | S35: =SUM(S36:S41) -> 0 | ... BA35: =SUM(BA36:BA41) -> 0
A36: =Bobot!P33 -> 0 | F36: 023 | G36: 1.3.2 | H36: Transaksi dilakukan dengan agunan HQLA Level 1 | I36: =Bobot!O36 -> 0 | J36: =Bobot!O36 -> 0 | L36: =IF(Bobot!$P36=0,1,0)*('Input Bank'!L36+'Input Bank'!K36)*I36 -> 0 | M36: =Bobot!$P36*($I36*('Input Bank'!$K36+'Input Bank'!$L36)/30)+($J36*'Input Bank'!M36) -> 0 | N36: =Bobot!$P36*($I36*('Input Bank'!$K36+'Input Bank'!$L36)/30)+($J36*'Input Bank'!N36) -> 0 | O36: =Bobot!$P36*($I36*('Input Bank'!$K36+'Input Bank'!$L36)/30)+($J36*'Input Bank'!O36) -> 0 | P36: =Bobot!$P36*($I36*('Input Bank'!$K36+'Input Bank'!$L36)/30)+($J36*'Input Bank'!P36) -> 0 | Q36: =Bobot!$P36*($I36*('Input Bank'!$K36+'Input Bank'!$L36)/30)+($J36*'Input Bank'!Q36) -> 0 | R36: =Bobot!$P36*($I36*('Input Bank'!$K36+'Input Bank'!$L36)/30)+($J36*'Input Bank'!R36) -> 0 | S36: =Bobot!$P36*($I36*('Input Bank'!$K36+'Input Bank'!$L36)/30)+($J36*'Input Bank'!S36) -> 0 | T36: =Bobot!$P36*($I36*('Input Bank'!$K36+'Input Bank'!$L36)/30)+($J36*'Input Bank'!T36) -> 0 | ... AP36: =Bobot!$P36*($I36*('Input Bank'!$K36+'Input Bank'!$L36)/30)+($J36*'Input Bank'!AP36) -> 0 | AQ36: =$J36*'Input Bank'!AQ36 -> 0 | AR36: =$J36*'Input Bank'!AR36 -> 0 | AS36: =$J36*'Input Bank'!AS36 -> 0 | AT36: =$J36*'Input Bank'!AT36 -> 0 | AU36: =$J36*'Input Bank'!AU36 -> 0 | AV36: =$J36*'Input Bank'!AV36 -> 0 | AW36: =$J36*'Input Bank'!AW36 -> 0 | AX36: =$J36*'Input Bank'!AX36 -> 0 | ... BA36: =$J36*'Input Bank'!BA36 -> 0
A37: =Bobot!P34 -> 0 | F37: 024 | G37: 1.3.3 | H37: Transaksi dilakukan dengan agunan HQLA Level 2A | I37: =Bobot!O37 -> 0.15 | J37: =Bobot!O37 -> 0.15 | L37: =IF(Bobot!$P37=0,1,0)*('Input Bank'!L37+'Input Bank'!K37)*I37 -> 0 | M37: =Bobot!$P37*($I37*('Input Bank'!$K37+'Input Bank'!$L37)/30)+($J37*'Input Bank'!M37) -> 0 | N37: =Bobot!$P37*($I37*('Input Bank'!$K37+'Input Bank'!$L37)/30)+($J37*'Input Bank'!N37) -> 0 | O37: =Bobot!$P37*($I37*('Input Bank'!$K37+'Input Bank'!$L37)/30)+($J37*'Input Bank'!O37) -> 0 | P37: =Bobot!$P37*($I37*('Input Bank'!$K37+'Input Bank'!$L37)/30)+($J37*'Input Bank'!P37) -> 0 | Q37: =Bobot!$P37*($I37*('Input Bank'!$K37+'Input Bank'!$L37)/30)+($J37*'Input Bank'!Q37) -> 0 | R37: =Bobot!$P37*($I37*('Input Bank'!$K37+'Input Bank'!$L37)/30)+($J37*'Input Bank'!R37) -> 0 | S37: =Bobot!$P37*($I37*('Input Bank'!$K37+'Input Bank'!$L37)/30)+($J37*'Input Bank'!S37) -> 0 | T37: =Bobot!$P37*($I37*('Input Bank'!$K37+'Input Bank'!$L37)/30)+($J37*'Input Bank'!T37) -> 0 | ... AP37: =Bobot!$P37*($I37*('Input Bank'!$K37+'Input Bank'!$L37)/30)+($J37*'Input Bank'!AP37) -> 0 | AQ37: =$J37*'Input Bank'!AQ37 -> 0 | AR37: =$J37*'Input Bank'!AR37 -> 0 | AS37: =$J37*'Input Bank'!AS37 -> 0 | AT37: =$J37*'Input Bank'!AT37 -> 0 | AU37: =$J37*'Input Bank'!AU37 -> 0 | AV37: =$J37*'Input Bank'!AV37 -> 0 | AW37: =$J37*'Input Bank'!AW37 -> 0 | AX37: =$J37*'Input Bank'!AX37 -> 0 | ... BA37: =$J37*'Input Bank'!BA37 -> 0
F38: 025 | G38: 1.3.4 | H38: Transaksi dilakukan dengan Pemerintah Pusat atau entitas sektor publik yang memiliki bobot risiko paling tinggi 20% atau bank pembangunan multilateral, dengan agunan selain HQLA Level 1 atau HQLA Level 2A | I38: =Bobot!O38 -> 0.25 | J38: =Bobot!O38 -> 0.25 | L38: =IF(Bobot!$P38=0,1,0)*('Input Bank'!L38+'Input Bank'!K38)*I38 -> 0 | M38: =Bobot!$P38*($I38*('Input Bank'!$K38+'Input Bank'!$L38)/30)+($J38*'Input Bank'!M38) -> 0 | N38: =Bobot!$P38*($I38*('Input Bank'!$K38+'Input Bank'!$L38)/30)+($J38*'Input Bank'!N38) -> 0 | O38: =Bobot!$P38*($I38*('Input Bank'!$K38+'Input Bank'!$L38)/30)+($J38*'Input Bank'!O38) -> 0 | P38: =Bobot!$P38*($I38*('Input Bank'!$K38+'Input Bank'!$L38)/30)+($J38*'Input Bank'!P38) -> 0 | Q38: =Bobot!$P38*($I38*('Input Bank'!$K38+'Input Bank'!$L38)/30)+($J38*'Input Bank'!Q38) -> 0 | R38: =Bobot!$P38*($I38*('Input Bank'!$K38+'Input Bank'!$L38)/30)+($J38*'Input Bank'!R38) -> 0 | S38: =Bobot!$P38*($I38*('Input Bank'!$K38+'Input Bank'!$L38)/30)+($J38*'Input Bank'!S38) -> 0 | T38: =Bobot!$P38*($I38*('Input Bank'!$K38+'Input Bank'!$L38)/30)+($J38*'Input Bank'!T38) -> 0 | ... AP38: =Bobot!$P38*($I38*('Input Bank'!$K38+'Input Bank'!$L38)/30)+($J38*'Input Bank'!AP38) -> 0 | AQ38: =$J38*'Input Bank'!AQ38 -> 0 | AR38: =$J38*'Input Bank'!AR38 -> 0 | AS38: =$J38*'Input Bank'!AS38 -> 0 | AT38: =$J38*'Input Bank'!AT38 -> 0 | AU38: =$J38*'Input Bank'!AU38 -> 0 | AV38: =$J38*'Input Bank'!AV38 -> 0 | AW38: =$J38*'Input Bank'!AW38 -> 0 | AX38: =$J38*'Input Bank'!AX38 -> 0 | ... BA38: =$J38*'Input Bank'!BA38 -> 0
A39: =Bobot!P36 -> 0 | F39: 026 | G39: 1.3.5 | H39: Transaksi dilakukan dengan agunan HQLA Level 2B berupa EBA | I39: =Bobot!O39 -> 0.25 | J39: =Bobot!O39 -> 0.25 | L39: =IF(Bobot!$P39=0,1,0)*('Input Bank'!L39+'Input Bank'!K39)*I39 -> 0 | M39: =Bobot!$P39*($I39*('Input Bank'!$K39+'Input Bank'!$L39)/30)+($J39*'Input Bank'!M39) -> 0 | N39: =Bobot!$P39*($I39*('Input Bank'!$K39+'Input Bank'!$L39)/30)+($J39*'Input Bank'!N39) -> 0 | O39: =Bobot!$P39*($I39*('Input Bank'!$K39+'Input Bank'!$L39)/30)+($J39*'Input Bank'!O39) -> 0 | P39: =Bobot!$P39*($I39*('Input Bank'!$K39+'Input Bank'!$L39)/30)+($J39*'Input Bank'!P39) -> 0 | Q39: =Bobot!$P39*($I39*('Input Bank'!$K39+'Input Bank'!$L39)/30)+($J39*'Input Bank'!Q39) -> 0 | R39: =Bobot!$P39*($I39*('Input Bank'!$K39+'Input Bank'!$L39)/30)+($J39*'Input Bank'!R39) -> 0 | S39: =Bobot!$P39*($I39*('Input Bank'!$K39+'Input Bank'!$L39)/30)+($J39*'Input Bank'!S39) -> 0 | T39: =Bobot!$P39*($I39*('Input Bank'!$K39+'Input Bank'!$L39)/30)+($J39*'Input Bank'!T39) -> 0 | ... AP39: =Bobot!$P39*($I39*('Input Bank'!$K39+'Input Bank'!$L39)/30)+($J39*'Input Bank'!AP39) -> 0 | AQ39: =$J39*'Input Bank'!AQ39 -> 0 | AR39: =$J39*'Input Bank'!AR39 -> 0 | AS39: =$J39*'Input Bank'!AS39 -> 0 | AT39: =$J39*'Input Bank'!AT39 -> 0 | AU39: =$J39*'Input Bank'!AU39 -> 0 | AV39: =$J39*'Input Bank'!AV39 -> 0 | AW39: =$J39*'Input Bank'!AW39 -> 0 | AX39: =$J39*'Input Bank'!AX39 -> 0 | ... BA39: =$J39*'Input Bank'!BA39 -> 0
A40: =Bobot!#REF! -> #REF! | F40: 027 | G40: 1.3.6 | H40: Transaksi dilakukan dengan agunan HQLA Level 2B berupa selain EBA | I40: =Bobot!O40 -> 0.5 | J40: =Bobot!O40 -> 0.5 | L40: =IF(Bobot!$P40=0,1,0)*('Input Bank'!L40+'Input Bank'!K40)*I40 -> 0 | M40: =Bobot!$P40*($I40*('Input Bank'!$K40+'Input Bank'!$L40)/30)+($J40*'Input Bank'!M40) -> 0 | N40: =Bobot!$P40*($I40*('Input Bank'!$K40+'Input Bank'!$L40)/30)+($J40*'Input Bank'!N40) -> 0 | O40: =Bobot!$P40*($I40*('Input Bank'!$K40+'Input Bank'!$L40)/30)+($J40*'Input Bank'!O40) -> 0 | P40: =Bobot!$P40*($I40*('Input Bank'!$K40+'Input Bank'!$L40)/30)+($J40*'Input Bank'!P40) -> 0 | Q40: =Bobot!$P40*($I40*('Input Bank'!$K40+'Input Bank'!$L40)/30)+($J40*'Input Bank'!Q40) -> 0 | R40: =Bobot!$P40*($I40*('Input Bank'!$K40+'Input Bank'!$L40)/30)+($J40*'Input Bank'!R40) -> 0 | S40: =Bobot!$P40*($I40*('Input Bank'!$K40+'Input Bank'!$L40)/30)+($J40*'Input Bank'!S40) -> 0 | T40: =Bobot!$P40*($I40*('Input Bank'!$K40+'Input Bank'!$L40)/30)+($J40*'Input Bank'!T40) -> 0 | ... AP40: =Bobot!$P40*($I40*('Input Bank'!$K40+'Input Bank'!$L40)/30)+($J40*'Input Bank'!AP40) -> 0 | AQ40: =$J40*'Input Bank'!AQ40 -> 0 | AR40: =$J40*'Input Bank'!AR40 -> 0 | AS40: =$J40*'Input Bank'!AS40 -> 0 | AT40: =$J40*'Input Bank'!AT40 -> 0 | AU40: =$J40*'Input Bank'!AU40 -> 0 | AV40: =$J40*'Input Bank'!AV40 -> 0 | AW40: =$J40*'Input Bank'!AW40 -> 0 | AX40: =$J40*'Input Bank'!AX40 -> 0 | ... BA40: =$J40*'Input Bank'!BA40 -> 0
A41: =Bobot!#REF! -> #REF! | F41: 028 | G41: 1.3.7 | H41: Transaksi dilakukan dengan agunan selain HQLA | I41: =Bobot!O41 -> 1 | J41: =Bobot!O41 -> 1 | L41: =IF(Bobot!$P41=0,1,0)*('Input Bank'!L41+'Input Bank'!K41)*I41 -> 0 | M41: =Bobot!$P41*($I41*('Input Bank'!$K41+'Input Bank'!$L41)/30)+($J41*'Input Bank'!M41) -> 0 | N41: =Bobot!$P41*($I41*('Input Bank'!$K41+'Input Bank'!$L41)/30)+($J41*'Input Bank'!N41) -> 0 | O41: =Bobot!$P41*($I41*('Input Bank'!$K41+'Input Bank'!$L41)/30)+($J41*'Input Bank'!O41) -> 0 | P41: =Bobot!$P41*($I41*('Input Bank'!$K41+'Input Bank'!$L41)/30)+($J41*'Input Bank'!P41) -> 0 | Q41: =Bobot!$P41*($I41*('Input Bank'!$K41+'Input Bank'!$L41)/30)+($J41*'Input Bank'!Q41) -> 0 | R41: =Bobot!$P41*($I41*('Input Bank'!$K41+'Input Bank'!$L41)/30)+($J41*'Input Bank'!R41) -> 0 | S41: =Bobot!$P41*($I41*('Input Bank'!$K41+'Input Bank'!$L41)/30)+($J41*'Input Bank'!S41) -> 0 | T41: =Bobot!$P41*($I41*('Input Bank'!$K41+'Input Bank'!$L41)/30)+($J41*'Input Bank'!T41) -> 0 | ... AP41: =Bobot!$P41*($I41*('Input Bank'!$K41+'Input Bank'!$L41)/30)+($J41*'Input Bank'!AP41) -> 0 | AQ41: =$J41*'Input Bank'!AQ41 -> 0 | AR41: =$J41*'Input Bank'!AR41 -> 0 | AS41: =$J41*'Input Bank'!AS41 -> 0 | AT41: =$J41*'Input Bank'!AT41 -> 0 | AU41: =$J41*'Input Bank'!AU41 -> 0 | AV41: =$J41*'Input Bank'!AV41 -> 0 | AW41: =$J41*'Input Bank'!AW41 -> 0 | AX41: =$J41*'Input Bank'!AX41 -> 0 | ... BA41: =$J41*'Input Bank'!BA41 -> 0
F42: 029 | G42: 1.3.8 | H42: Kewajiban timbul dari secured funding atau transaksi pasar modal dengan Bank Indonesia sebagai pihak lawan: | L42: =SUM(L43:L47) -> 0 | M42: =SUM(M43:M47) -> 0 | N42: =SUM(N43:N47) -> 0 | O42: =SUM(O43:O47) -> 0 | P42: =SUM(P43:P47) -> 0 | Q42: =SUM(Q43:Q47) -> 0 | R42: =SUM(R43:R47) -> 0 | S42: =SUM(S43:S47) -> 0 | ... BA42: =SUM(BA43:BA47) -> 0
F43: 030 | G43: 1.3.9 | H43: Transaksi dilakukan dengan agunan HQLA Level 1 | I43: =Bobot!O43 -> 0 | J43: =Bobot!O43 -> 0 | L43: =IF(Bobot!$P43=0,1,0)*('Input Bank'!L43+'Input Bank'!K43)*I43 -> 0 | M43: =Bobot!$P43*($I43*('Input Bank'!$K43+'Input Bank'!$L43)/30)+($J43*'Input Bank'!M43) -> 0 | N43: =Bobot!$P43*($I43*('Input Bank'!$K43+'Input Bank'!$L43)/30)+($J43*'Input Bank'!N43) -> 0 | O43: =Bobot!$P43*($I43*('Input Bank'!$K43+'Input Bank'!$L43)/30)+($J43*'Input Bank'!O43) -> 0 | P43: =Bobot!$P43*($I43*('Input Bank'!$K43+'Input Bank'!$L43)/30)+($J43*'Input Bank'!P43) -> 0 | Q43: =Bobot!$P43*($I43*('Input Bank'!$K43+'Input Bank'!$L43)/30)+($J43*'Input Bank'!Q43) -> 0 | R43: =Bobot!$P43*($I43*('Input Bank'!$K43+'Input Bank'!$L43)/30)+($J43*'Input Bank'!R43) -> 0 | S43: =Bobot!$P43*($I43*('Input Bank'!$K43+'Input Bank'!$L43)/30)+($J43*'Input Bank'!S43) -> 0 | T43: =Bobot!$P43*($I43*('Input Bank'!$K43+'Input Bank'!$L43)/30)+($J43*'Input Bank'!T43) -> 0 | ... AP43: =Bobot!$P43*($I43*('Input Bank'!$K43+'Input Bank'!$L43)/30)+($J43*'Input Bank'!AP43) -> 0 | AQ43: =$J43*'Input Bank'!AQ43 -> 0 | AR43: =$J43*'Input Bank'!AR43 -> 0 | AS43: =$J43*'Input Bank'!AS43 -> 0 | AT43: =$J43*'Input Bank'!AT43 -> 0 | AU43: =$J43*'Input Bank'!AU43 -> 0 | AV43: =$J43*'Input Bank'!AV43 -> 0 | AW43: =$J43*'Input Bank'!AW43 -> 0 | AX43: =$J43*'Input Bank'!AX43 -> 0 | ... BA43: =$J43*'Input Bank'!BA43 -> 0
F44: 031 | G44: 1.3.10 | H44: Transaksi dilakukan dengan agunan HQLA Level 2A | I44: =Bobot!O44 -> 0 | J44: =Bobot!O44 -> 0 | L44: =IF(Bobot!$P44=0,1,0)*('Input Bank'!L44+'Input Bank'!K44)*I44 -> 0 | M44: =Bobot!$P44*($I44*('Input Bank'!$K44+'Input Bank'!$L44)/30)+($J44*'Input Bank'!M44) -> 0 | N44: =Bobot!$P44*($I44*('Input Bank'!$K44+'Input Bank'!$L44)/30)+($J44*'Input Bank'!N44) -> 0 | O44: =Bobot!$P44*($I44*('Input Bank'!$K44+'Input Bank'!$L44)/30)+($J44*'Input Bank'!O44) -> 0 | P44: =Bobot!$P44*($I44*('Input Bank'!$K44+'Input Bank'!$L44)/30)+($J44*'Input Bank'!P44) -> 0 | Q44: =Bobot!$P44*($I44*('Input Bank'!$K44+'Input Bank'!$L44)/30)+($J44*'Input Bank'!Q44) -> 0 | R44: =Bobot!$P44*($I44*('Input Bank'!$K44+'Input Bank'!$L44)/30)+($J44*'Input Bank'!R44) -> 0 | S44: =Bobot!$P44*($I44*('Input Bank'!$K44+'Input Bank'!$L44)/30)+($J44*'Input Bank'!S44) -> 0 | T44: =Bobot!$P44*($I44*('Input Bank'!$K44+'Input Bank'!$L44)/30)+($J44*'Input Bank'!T44) -> 0 | ... AP44: =Bobot!$P44*($I44*('Input Bank'!$K44+'Input Bank'!$L44)/30)+($J44*'Input Bank'!AP44) -> 0 | AQ44: =$J44*'Input Bank'!AQ44 -> 0 | AR44: =$J44*'Input Bank'!AR44 -> 0 | AS44: =$J44*'Input Bank'!AS44 -> 0 | AT44: =$J44*'Input Bank'!AT44 -> 0 | AU44: =$J44*'Input Bank'!AU44 -> 0 | AV44: =$J44*'Input Bank'!AV44 -> 0 | AW44: =$J44*'Input Bank'!AW44 -> 0 | AX44: =$J44*'Input Bank'!AX44 -> 0 | ... BA44: =$J44*'Input Bank'!BA44 -> 0
F45: 032 | G45: 1.3.11 | H45: Transaksi dilakukan dengan agunan HQLA Level 2B berupa EBA | I45: =Bobot!O45 -> 0 | J45: =Bobot!O45 -> 0 | L45: =IF(Bobot!$P45=0,1,0)*('Input Bank'!L45+'Input Bank'!K45)*I45 -> 0 | M45: =Bobot!$P45*($I45*('Input Bank'!$K45+'Input Bank'!$L45)/30)+($J45*'Input Bank'!M45) -> 0 | N45: =Bobot!$P45*($I45*('Input Bank'!$K45+'Input Bank'!$L45)/30)+($J45*'Input Bank'!N45) -> 0 | O45: =Bobot!$P45*($I45*('Input Bank'!$K45+'Input Bank'!$L45)/30)+($J45*'Input Bank'!O45) -> 0 | P45: =Bobot!$P45*($I45*('Input Bank'!$K45+'Input Bank'!$L45)/30)+($J45*'Input Bank'!P45) -> 0 | Q45: =Bobot!$P45*($I45*('Input Bank'!$K45+'Input Bank'!$L45)/30)+($J45*'Input Bank'!Q45) -> 0 | R45: =Bobot!$P45*($I45*('Input Bank'!$K45+'Input Bank'!$L45)/30)+($J45*'Input Bank'!R45) -> 0 | S45: =Bobot!$P45*($I45*('Input Bank'!$K45+'Input Bank'!$L45)/30)+($J45*'Input Bank'!S45) -> 0 | T45: =Bobot!$P45*($I45*('Input Bank'!$K45+'Input Bank'!$L45)/30)+($J45*'Input Bank'!T45) -> 0 | ... AP45: =Bobot!$P45*($I45*('Input Bank'!$K45+'Input Bank'!$L45)/30)+($J45*'Input Bank'!AP45) -> 0 | AQ45: =$J45*'Input Bank'!AQ45 -> 0 | AR45: =$J45*'Input Bank'!AR45 -> 0 | AS45: =$J45*'Input Bank'!AS45 -> 0 | AT45: =$J45*'Input Bank'!AT45 -> 0 | AU45: =$J45*'Input Bank'!AU45 -> 0 | AV45: =$J45*'Input Bank'!AV45 -> 0 | AW45: =$J45*'Input Bank'!AW45 -> 0 | AX45: =$J45*'Input Bank'!AX45 -> 0 | ... BA45: =$J45*'Input Bank'!BA45 -> 0
F46: 033 | G46: 1.3.12 | H46: Transaksi dilakukan dengan agunan HQLA Level 2B berupa selain EBA | I46: =Bobot!O46 -> 0 | J46: =Bobot!O46 -> 0 | L46: =IF(Bobot!$P46=0,1,0)*('Input Bank'!L46+'Input Bank'!K46)*I46 -> 0 | M46: =Bobot!$P46*($I46*('Input Bank'!$K46+'Input Bank'!$L46)/30)+($J46*'Input Bank'!M46) -> 0 | N46: =Bobot!$P46*($I46*('Input Bank'!$K46+'Input Bank'!$L46)/30)+($J46*'Input Bank'!N46) -> 0 | O46: =Bobot!$P46*($I46*('Input Bank'!$K46+'Input Bank'!$L46)/30)+($J46*'Input Bank'!O46) -> 0 | P46: =Bobot!$P46*($I46*('Input Bank'!$K46+'Input Bank'!$L46)/30)+($J46*'Input Bank'!P46) -> 0 | Q46: =Bobot!$P46*($I46*('Input Bank'!$K46+'Input Bank'!$L46)/30)+($J46*'Input Bank'!Q46) -> 0 | R46: =Bobot!$P46*($I46*('Input Bank'!$K46+'Input Bank'!$L46)/30)+($J46*'Input Bank'!R46) -> 0 | S46: =Bobot!$P46*($I46*('Input Bank'!$K46+'Input Bank'!$L46)/30)+($J46*'Input Bank'!S46) -> 0 | T46: =Bobot!$P46*($I46*('Input Bank'!$K46+'Input Bank'!$L46)/30)+($J46*'Input Bank'!T46) -> 0 | ... AP46: =Bobot!$P46*($I46*('Input Bank'!$K46+'Input Bank'!$L46)/30)+($J46*'Input Bank'!AP46) -> 0 | AQ46: =$J46*'Input Bank'!AQ46 -> 0 | AR46: =$J46*'Input Bank'!AR46 -> 0 | AS46: =$J46*'Input Bank'!AS46 -> 0 | AT46: =$J46*'Input Bank'!AT46 -> 0 | AU46: =$J46*'Input Bank'!AU46 -> 0 | AV46: =$J46*'Input Bank'!AV46 -> 0 | AW46: =$J46*'Input Bank'!AW46 -> 0 | AX46: =$J46*'Input Bank'!AX46 -> 0 | ... BA46: =$J46*'Input Bank'!BA46 -> 0
F47: 034 | G47: 1.3.13 | H47: Transaksi dilakukan dengan agunan selain HQLA | I47: =Bobot!O47 -> 0 | J47: =Bobot!O47 -> 0 | L47: =IF(Bobot!$P47=0,1,0)*('Input Bank'!L47+'Input Bank'!K47)*I47 -> 0 | M47: =Bobot!$P47*($I47*('Input Bank'!$K47+'Input Bank'!$L47)/30)+($J47*'Input Bank'!M47) -> 0 | N47: =Bobot!$P47*($I47*('Input Bank'!$K47+'Input Bank'!$L47)/30)+($J47*'Input Bank'!N47) -> 0 | O47: =Bobot!$P47*($I47*('Input Bank'!$K47+'Input Bank'!$L47)/30)+($J47*'Input Bank'!O47) -> 0 | P47: =Bobot!$P47*($I47*('Input Bank'!$K47+'Input Bank'!$L47)/30)+($J47*'Input Bank'!P47) -> 0 | Q47: =Bobot!$P47*($I47*('Input Bank'!$K47+'Input Bank'!$L47)/30)+($J47*'Input Bank'!Q47) -> 0 | R47: =Bobot!$P47*($I47*('Input Bank'!$K47+'Input Bank'!$L47)/30)+($J47*'Input Bank'!R47) -> 0 | S47: =Bobot!$P47*($I47*('Input Bank'!$K47+'Input Bank'!$L47)/30)+($J47*'Input Bank'!S47) -> 0 | T47: =Bobot!$P47*($I47*('Input Bank'!$K47+'Input Bank'!$L47)/30)+($J47*'Input Bank'!T47) -> 0 | ... AP47: =Bobot!$P47*($I47*('Input Bank'!$K47+'Input Bank'!$L47)/30)+($J47*'Input Bank'!AP47) -> 0 | AQ47: =$J47*'Input Bank'!AQ47 -> 0 | AR47: =$J47*'Input Bank'!AR47 -> 0 | AS47: =$J47*'Input Bank'!AS47 -> 0 | AT47: =$J47*'Input Bank'!AT47 -> 0 | AU47: =$J47*'Input Bank'!AU47 -> 0 | AV47: =$J47*'Input Bank'!AV47 -> 0 | AW47: =$J47*'Input Bank'!AW47 -> 0 | AX47: =$J47*'Input Bank'!AX47 -> 0 | ... BA47: =$J47*'Input Bank'!BA47 -> 0
A48: =Bobot!#REF! -> #REF! | F48: 035 | G48: 1.4 | H48: FX-swaps jatuh tempo | I48: =Bobot!O48 -> 1 | J48: =Bobot!O48 -> 1 | L48: =IF(Bobot!$P48=0,1,0)*('Input Bank'!L48+'Input Bank'!K48)*I48 -> 0 | M48: =Bobot!$P48*($I48*('Input Bank'!$K48+'Input Bank'!$L48)/30)+($J48*'Input Bank'!M48) -> 0 | N48: =Bobot!$P48*($I48*('Input Bank'!$K48+'Input Bank'!$L48)/30)+($J48*'Input Bank'!N48) -> 0 | O48: =Bobot!$P48*($I48*('Input Bank'!$K48+'Input Bank'!$L48)/30)+($J48*'Input Bank'!O48) -> 0 | P48: =Bobot!$P48*($I48*('Input Bank'!$K48+'Input Bank'!$L48)/30)+($J48*'Input Bank'!P48) -> 0 | Q48: =Bobot!$P48*($I48*('Input Bank'!$K48+'Input Bank'!$L48)/30)+($J48*'Input Bank'!Q48) -> 0 | R48: =Bobot!$P48*($I48*('Input Bank'!$K48+'Input Bank'!$L48)/30)+($J48*'Input Bank'!R48) -> 0 | S48: =Bobot!$P48*($I48*('Input Bank'!$K48+'Input Bank'!$L48)/30)+($J48*'Input Bank'!S48) -> 0 | T48: =Bobot!$P48*($I48*('Input Bank'!$K48+'Input Bank'!$L48)/30)+($J48*'Input Bank'!T48) -> 0 | ... AP48: =Bobot!$P48*($I48*('Input Bank'!$K48+'Input Bank'!$L48)/30)+($J48*'Input Bank'!AP48) -> 0 | AQ48: =$J48*'Input Bank'!AQ48 -> 0 | AR48: =$J48*'Input Bank'!AR48 -> 0 | AS48: =$J48*'Input Bank'!AS48 -> 0 | AT48: =$J48*'Input Bank'!AT48 -> 0 | AU48: =$J48*'Input Bank'!AU48 -> 0 | AV48: =$J48*'Input Bank'!AV48 -> 0 | AW48: =$J48*'Input Bank'!AW48 -> 0 | AX48: =$J48*'Input Bank'!AX48 -> 0 | ... BA48: =$J48*'Input Bank'!BA48 -> 0
A49: =Bobot!#REF! -> #REF! | F49: 036 | G49: 1.5 | H49: Arus kas keluar lainnya terkait transaksi derivatif selain 1.4 | I49: =Bobot!O49 -> 1 | J49: =Bobot!O49 -> 1 | L49: =IF(Bobot!$P49=0,1,0)*('Input Bank'!L49+'Input Bank'!K49)*I49 -> 0 | M49: =Bobot!$P49*($I49*('Input Bank'!$K49+'Input Bank'!$L49)/30)+($J49*'Input Bank'!M49) -> 0 | N49: =Bobot!$P49*($I49*('Input Bank'!$K49+'Input Bank'!$L49)/30)+($J49*'Input Bank'!N49) -> 0 | O49: =Bobot!$P49*($I49*('Input Bank'!$K49+'Input Bank'!$L49)/30)+($J49*'Input Bank'!O49) -> 0 | P49: =Bobot!$P49*($I49*('Input Bank'!$K49+'Input Bank'!$L49)/30)+($J49*'Input Bank'!P49) -> 0 | Q49: =Bobot!$P49*($I49*('Input Bank'!$K49+'Input Bank'!$L49)/30)+($J49*'Input Bank'!Q49) -> 0 | R49: =Bobot!$P49*($I49*('Input Bank'!$K49+'Input Bank'!$L49)/30)+($J49*'Input Bank'!R49) -> 0 | S49: =Bobot!$P49*($I49*('Input Bank'!$K49+'Input Bank'!$L49)/30)+($J49*'Input Bank'!S49) -> 0 | T49: =Bobot!$P49*($I49*('Input Bank'!$K49+'Input Bank'!$L49)/30)+($J49*'Input Bank'!T49) -> 0 | ... AP49: =Bobot!$P49*($I49*('Input Bank'!$K49+'Input Bank'!$L49)/30)+($J49*'Input Bank'!AP49) -> 0 | AQ49: =$J49*'Input Bank'!AQ49 -> 0 | AR49: =$J49*'Input Bank'!AR49 -> 0 | AS49: =$J49*'Input Bank'!AS49 -> 0 | AT49: =$J49*'Input Bank'!AT49 -> 0 | AU49: =$J49*'Input Bank'!AU49 -> 0 | AV49: =$J49*'Input Bank'!AV49 -> 0 | AW49: =$J49*'Input Bank'!AW49 -> 0 | AX49: =$J49*'Input Bank'!AX49 -> 0 | ... BA49: =$J49*'Input Bank'!BA49 -> 0
A50: =Bobot!#REF! -> #REF! | F50: 037 | G50: 1.6 | H50: Arus kas keluar lainnya | I50: =Bobot!O50 -> 1 | J50: =Bobot!O50 -> 1 | L50: =IF(Bobot!$P50=0,1,0)*('Input Bank'!L50+'Input Bank'!K50)*I50 -> 0 | M50: =Bobot!$P50*($I50*('Input Bank'!$K50+'Input Bank'!$L50)/30)+($J50*'Input Bank'!M50) -> 0 | N50: =Bobot!$P50*($I50*('Input Bank'!$K50+'Input Bank'!$L50)/30)+($J50*'Input Bank'!N50) -> 0 | O50: =Bobot!$P50*($I50*('Input Bank'!$K50+'Input Bank'!$L50)/30)+($J50*'Input Bank'!O50) -> 0 | P50: =Bobot!$P50*($I50*('Input Bank'!$K50+'Input Bank'!$L50)/30)+($J50*'Input Bank'!P50) -> 0 | Q50: =Bobot!$P50*($I50*('Input Bank'!$K50+'Input Bank'!$L50)/30)+($J50*'Input Bank'!Q50) -> 0 | R50: =Bobot!$P50*($I50*('Input Bank'!$K50+'Input Bank'!$L50)/30)+($J50*'Input Bank'!R50) -> 0 | S50: =Bobot!$P50*($I50*('Input Bank'!$K50+'Input Bank'!$L50)/30)+($J50*'Input Bank'!S50) -> 0 | T50: =Bobot!$P50*($I50*('Input Bank'!$K50+'Input Bank'!$L50)/30)+($J50*'Input Bank'!T50) -> 0 | ... AP50: =Bobot!$P50*($I50*('Input Bank'!$K50+'Input Bank'!$L50)/30)+($J50*'Input Bank'!AP50) -> 0 | AQ50: =$J50*'Input Bank'!AQ50 -> 0 | AR50: =$J50*'Input Bank'!AR50 -> 0 | AS50: =$J50*'Input Bank'!AS50 -> 0 | AT50: =$J50*'Input Bank'!AT50 -> 0 | AU50: =$J50*'Input Bank'!AU50 -> 0 | AV50: =$J50*'Input Bank'!AV50 -> 0 | AW50: =$J50*'Input Bank'!AW50 -> 0 | AX50: =$J50*'Input Bank'!AX50 -> 0 | ... BA50: =$J50*'Input Bank'!BA50 -> 0
A51: =Bobot!#REF! -> #REF! | F51: 038 | G51: 1.7 | H51: Total arus kas keluar | L51: =SUM(L15,L34,L48,L49,L50) -> 0 | M51: =SUM(M15,M34,M48,M49,M50,M31) -> 0 | N51: =SUM(N15,N34,N48,N49,N50,N31) -> 0 | O51: =SUM(O15,O34,O48,O49,O50,O31) -> 0 | P51: =SUM(P15,P34,P48,P49,P50,P31) -> 0 | Q51: =SUM(Q15,Q34,Q48,Q49,Q50,Q31) -> 0 | R51: =SUM(R15,R34,R48,R49,R50,R31) -> 0 | S51: =SUM(S15,S34,S48,S49,S50,S31) -> 0 | T51: =SUM(T15,T34,T48,T49,T50,T31) -> 0 | ... BA51: =SUM(BA15,BA34,BA48,BA49,BA50,BA31) -> 0
A52: =Bobot!#REF! -> #REF! | F52: 039 | G52: 2 | H52: ARUS KAS MASUK | I52: Weight - open | J52: Weight - term | K52: Stok awal | L52: Tanpa Maturitas (Open) | M52: O/N (selain Open) | N52: Hari-2 | O52: Hari-3 | P52: Hari-4 | Q52: Hari-5 | R52: Hari-6 | S52: Hari-7 | T52: Hari-8 | U52: Hari-9 | V52: Hari-10 | W52: Hari-11 | X52: Hari-12 | Y52: Hari-13 | Z52: Hari-14 | AA52: Hari-15 | AB52: Hari-16 | AC52: Hari-17 | AD52: Hari-18 | AE52: Hari-19 | AF52: Hari-20 | AG52: Hari-21 | AH52: Hari-22 | AI52: Hari-23 | AJ52: Hari-24 | AK52: Hari-25 | AL52: Hari-26 | AM52: Hari-27 | AN52: Hari-28 | AO52: Hari-29 | AP52: Hari-30 | AQ52: > mg 4 s.d. mg 5 | AR52: > mg 5 s.d. 2 bln | AS52: > 2 bln s.d 3 bln | AT52: > 3 bln s.d 4 bln | AU52: > 4 bln s.d 5 bln | AV52: > 5 bln s.d 6 bln | AW52: > 6 bln s.d. 9 bln | AX52: > 9 bln s.d. 12 bln | AY52: > 12 bln s.d. 2 thn | AZ52: > 2 thn s.d. 5 thn | BA52: > 5 thn
A53: =Bobot!#REF! -> #REF! | F53: 040 | G53: 2.1 | H53: Pinjaman dengan Agunan (Secured Lending) | L53: =SUM(L54,L61) -> 0 | M53: =SUM(M54,M61) -> 0 | N53: =SUM(N54,N61) -> 0 | O53: =SUM(O54,O61) -> 0 | P53: =SUM(P54,P61) -> 0 | Q53: =SUM(Q54,Q61) -> 0 | R53: =SUM(R54,R61) -> 0 | S53: =SUM(S54,S61) -> 0 | ... BA53: =SUM(BA54,BA61) -> 0
A54: =Bobot!#REF! -> #REF! | F54: 041 | G54: 2.1.1 | H54: Agunan tidak digunakan kembali untuk menutupi posisi short nasabah | L54: =SUM(L55:L60) -> 0 | M54: =SUM(M55:M60) -> 0 | N54: =SUM(N55:N60) -> 0 | O54: =SUM(O55:O60) -> 0 | P54: =SUM(P55:P60) -> 0 | Q54: =SUM(Q55:Q60) -> 0 | R54: =SUM(R55:R60) -> 0 | S54: =SUM(S55:S60) -> 0 | ... BA54: =SUM(BA55:BA60) -> 0
A55: =Bobot!#REF! -> #REF! | F55: 042 | G55: 2.1.2 | H55: Agunan berupa HQLA Level 1 | I55: =Bobot!O55 -> 0 | J55: =Bobot!O55 -> 0 | L55: =IF(Bobot!$P55=0,1,0)*('Input Bank'!L55+'Input Bank'!K55)*I55 -> 0 | M55: =Bobot!$P55*($I55*('Input Bank'!$K55+'Input Bank'!$L55)/30)+($J55*'Input Bank'!M55) -> 0 | N55: =Bobot!$P55*($I55*('Input Bank'!$K55+'Input Bank'!$L55)/30)+($J55*'Input Bank'!N55) -> 0 | O55: =Bobot!$P55*($I55*('Input Bank'!$K55+'Input Bank'!$L55)/30)+($J55*'Input Bank'!O55) -> 0 | P55: =Bobot!$P55*($I55*('Input Bank'!$K55+'Input Bank'!$L55)/30)+($J55*'Input Bank'!P55) -> 0 | Q55: =Bobot!$P55*($I55*('Input Bank'!$K55+'Input Bank'!$L55)/30)+($J55*'Input Bank'!Q55) -> 0 | R55: =Bobot!$P55*($I55*('Input Bank'!$K55+'Input Bank'!$L55)/30)+($J55*'Input Bank'!R55) -> 0 | S55: =Bobot!$P55*($I55*('Input Bank'!$K55+'Input Bank'!$L55)/30)+($J55*'Input Bank'!S55) -> 0 | T55: =Bobot!$P55*($I55*('Input Bank'!$K55+'Input Bank'!$L55)/30)+($J55*'Input Bank'!T55) -> 0 | ... AP55: =Bobot!$P55*($I55*('Input Bank'!$K55+'Input Bank'!$L55)/30)+($J55*'Input Bank'!AP55) -> 0 | AQ55: =$J55*'Input Bank'!AQ55 -> 0 | AR55: =$J55*'Input Bank'!AR55 -> 0 | AS55: =$J55*'Input Bank'!AS55 -> 0 | AT55: =$J55*'Input Bank'!AT55 -> 0 | AU55: =$J55*'Input Bank'!AU55 -> 0 | AV55: =$J55*'Input Bank'!AV55 -> 0 | AW55: =$J55*'Input Bank'!AW55 -> 0 | AX55: =$J55*'Input Bank'!AX55 -> 0 | ... BA55: =$J55*'Input Bank'!BA55 -> 0
A56: =Bobot!#REF! -> #REF! | F56: 043 | G56: 2.1.3 | H56: Agunan berupa HQLA Level 2A | I56: =Bobot!O56 -> 0.15 | J56: =Bobot!O56 -> 0.15 | L56: =IF(Bobot!$P56=0,1,0)*('Input Bank'!L56+'Input Bank'!K56)*I56 -> 0 | M56: =Bobot!$P56*($I56*('Input Bank'!$K56+'Input Bank'!$L56)/30)+($J56*'Input Bank'!M56) -> 0 | N56: =Bobot!$P56*($I56*('Input Bank'!$K56+'Input Bank'!$L56)/30)+($J56*'Input Bank'!N56) -> 0 | O56: =Bobot!$P56*($I56*('Input Bank'!$K56+'Input Bank'!$L56)/30)+($J56*'Input Bank'!O56) -> 0 | P56: =Bobot!$P56*($I56*('Input Bank'!$K56+'Input Bank'!$L56)/30)+($J56*'Input Bank'!P56) -> 0 | Q56: =Bobot!$P56*($I56*('Input Bank'!$K56+'Input Bank'!$L56)/30)+($J56*'Input Bank'!Q56) -> 0 | R56: =Bobot!$P56*($I56*('Input Bank'!$K56+'Input Bank'!$L56)/30)+($J56*'Input Bank'!R56) -> 0 | S56: =Bobot!$P56*($I56*('Input Bank'!$K56+'Input Bank'!$L56)/30)+($J56*'Input Bank'!S56) -> 0 | T56: =Bobot!$P56*($I56*('Input Bank'!$K56+'Input Bank'!$L56)/30)+($J56*'Input Bank'!T56) -> 0 | ... AP56: =Bobot!$P56*($I56*('Input Bank'!$K56+'Input Bank'!$L56)/30)+($J56*'Input Bank'!AP56) -> 0 | AQ56: =$J56*'Input Bank'!AQ56 -> 0 | AR56: =$J56*'Input Bank'!AR56 -> 0 | AS56: =$J56*'Input Bank'!AS56 -> 0 | AT56: =$J56*'Input Bank'!AT56 -> 0 | AU56: =$J56*'Input Bank'!AU56 -> 0 | AV56: =$J56*'Input Bank'!AV56 -> 0 | AW56: =$J56*'Input Bank'!AW56 -> 0 | AX56: =$J56*'Input Bank'!AX56 -> 0 | ... BA56: =$J56*'Input Bank'!BA56 -> 0
A57: =Bobot!#REF! -> #REF! | F57: 044 | G57: 2.1.4 | H57: Agunan HQLA Level 2B berupa EBA | I57: =Bobot!O57 -> 0.25 | J57: =Bobot!O57 -> 0.25 | L57: =IF(Bobot!$P57=0,1,0)*('Input Bank'!L57+'Input Bank'!K57)*I57 -> 0 | M57: =Bobot!$P57*($I57*('Input Bank'!$K57+'Input Bank'!$L57)/30)+($J57*'Input Bank'!M57) -> 0 | N57: =Bobot!$P57*($I57*('Input Bank'!$K57+'Input Bank'!$L57)/30)+($J57*'Input Bank'!N57) -> 0 | O57: =Bobot!$P57*($I57*('Input Bank'!$K57+'Input Bank'!$L57)/30)+($J57*'Input Bank'!O57) -> 0 | P57: =Bobot!$P57*($I57*('Input Bank'!$K57+'Input Bank'!$L57)/30)+($J57*'Input Bank'!P57) -> 0 | Q57: =Bobot!$P57*($I57*('Input Bank'!$K57+'Input Bank'!$L57)/30)+($J57*'Input Bank'!Q57) -> 0 | R57: =Bobot!$P57*($I57*('Input Bank'!$K57+'Input Bank'!$L57)/30)+($J57*'Input Bank'!R57) -> 0 | S57: =Bobot!$P57*($I57*('Input Bank'!$K57+'Input Bank'!$L57)/30)+($J57*'Input Bank'!S57) -> 0 | T57: =Bobot!$P57*($I57*('Input Bank'!$K57+'Input Bank'!$L57)/30)+($J57*'Input Bank'!T57) -> 0 | ... AP57: =Bobot!$P57*($I57*('Input Bank'!$K57+'Input Bank'!$L57)/30)+($J57*'Input Bank'!AP57) -> 0 | AQ57: =$J57*'Input Bank'!AQ57 -> 0 | AR57: =$J57*'Input Bank'!AR57 -> 0 | AS57: =$J57*'Input Bank'!AS57 -> 0 | AT57: =$J57*'Input Bank'!AT57 -> 0 | AU57: =$J57*'Input Bank'!AU57 -> 0 | AV57: =$J57*'Input Bank'!AV57 -> 0 | AW57: =$J57*'Input Bank'!AW57 -> 0 | AX57: =$J57*'Input Bank'!AX57 -> 0 | ... BA57: =$J57*'Input Bank'!BA57 -> 0
A58: =Bobot!#REF! -> #REF! | F58: 045 | G58: 2.1.5 | H58: Agunan HQLA Level 2B selain EBA | I58: =Bobot!O58 -> 0.5 | J58: =Bobot!O58 -> 0.5 | L58: =IF(Bobot!$P58=0,1,0)*('Input Bank'!L58+'Input Bank'!K58)*I58 -> 0 | M58: =Bobot!$P58*($I58*('Input Bank'!$K58+'Input Bank'!$L58)/30)+($J58*'Input Bank'!M58) -> 0 | N58: =Bobot!$P58*($I58*('Input Bank'!$K58+'Input Bank'!$L58)/30)+($J58*'Input Bank'!N58) -> 0 | O58: =Bobot!$P58*($I58*('Input Bank'!$K58+'Input Bank'!$L58)/30)+($J58*'Input Bank'!O58) -> 0 | P58: =Bobot!$P58*($I58*('Input Bank'!$K58+'Input Bank'!$L58)/30)+($J58*'Input Bank'!P58) -> 0 | Q58: =Bobot!$P58*($I58*('Input Bank'!$K58+'Input Bank'!$L58)/30)+($J58*'Input Bank'!Q58) -> 0 | R58: =Bobot!$P58*($I58*('Input Bank'!$K58+'Input Bank'!$L58)/30)+($J58*'Input Bank'!R58) -> 0 | S58: =Bobot!$P58*($I58*('Input Bank'!$K58+'Input Bank'!$L58)/30)+($J58*'Input Bank'!S58) -> 0 | T58: =Bobot!$P58*($I58*('Input Bank'!$K58+'Input Bank'!$L58)/30)+($J58*'Input Bank'!T58) -> 0 | ... AP58: =Bobot!$P58*($I58*('Input Bank'!$K58+'Input Bank'!$L58)/30)+($J58*'Input Bank'!AP58) -> 0 | AQ58: =$J58*'Input Bank'!AQ58 -> 0 | AR58: =$J58*'Input Bank'!AR58 -> 0 | AS58: =$J58*'Input Bank'!AS58 -> 0 | AT58: =$J58*'Input Bank'!AT58 -> 0 | AU58: =$J58*'Input Bank'!AU58 -> 0 | AV58: =$J58*'Input Bank'!AV58 -> 0 | AW58: =$J58*'Input Bank'!AW58 -> 0 | AX58: =$J58*'Input Bank'!AX58 -> 0 | ... BA58: =$J58*'Input Bank'!BA58 -> 0
A59: =Bobot!P41 -> 0 | F59: 046 | G59: 2.1.6 | H59: Transaksi berupa margin lending namun agunan berupa selain HQLA | I59: =Bobot!O59 -> 1 | J59: =Bobot!O59 -> 1 | L59: =IF(Bobot!$P59=0,1,0)*('Input Bank'!L59+'Input Bank'!K59)*I59 -> 0 | M59: =Bobot!$P59*($I59*('Input Bank'!$K59+'Input Bank'!$L59)/30)+($J59*'Input Bank'!M59) -> 0 | N59: =Bobot!$P59*($I59*('Input Bank'!$K59+'Input Bank'!$L59)/30)+($J59*'Input Bank'!N59) -> 0 | O59: =Bobot!$P59*($I59*('Input Bank'!$K59+'Input Bank'!$L59)/30)+($J59*'Input Bank'!O59) -> 0 | P59: =Bobot!$P59*($I59*('Input Bank'!$K59+'Input Bank'!$L59)/30)+($J59*'Input Bank'!P59) -> 0 | Q59: =Bobot!$P59*($I59*('Input Bank'!$K59+'Input Bank'!$L59)/30)+($J59*'Input Bank'!Q59) -> 0 | R59: =Bobot!$P59*($I59*('Input Bank'!$K59+'Input Bank'!$L59)/30)+($J59*'Input Bank'!R59) -> 0 | S59: =Bobot!$P59*($I59*('Input Bank'!$K59+'Input Bank'!$L59)/30)+($J59*'Input Bank'!S59) -> 0 | T59: =Bobot!$P59*($I59*('Input Bank'!$K59+'Input Bank'!$L59)/30)+($J59*'Input Bank'!T59) -> 0 | ... AP59: =Bobot!$P59*($I59*('Input Bank'!$K59+'Input Bank'!$L59)/30)+($J59*'Input Bank'!AP59) -> 0 | AQ59: =$J59*'Input Bank'!AQ59 -> 0 | AR59: =$J59*'Input Bank'!AR59 -> 0 | AS59: =$J59*'Input Bank'!AS59 -> 0 | AT59: =$J59*'Input Bank'!AT59 -> 0 | AU59: =$J59*'Input Bank'!AU59 -> 0 | AV59: =$J59*'Input Bank'!AV59 -> 0 | AW59: =$J59*'Input Bank'!AW59 -> 0 | AX59: =$J59*'Input Bank'!AX59 -> 0 | ... BA59: =$J59*'Input Bank'!BA59 -> 0
A60: =Bobot!P15 -> 0 | F60: 047 | G60: 2.1.7 | H60: Agunan tidak memenuhi persyaratan sebagaimana tersebut diatas | I60: =Bobot!O60 -> 0.5 | J60: =Bobot!O60 -> 0.5 | L60: =IF(Bobot!$P60=0,1,0)*('Input Bank'!L60+'Input Bank'!K60)*I60 -> 0 | M60: =Bobot!$P60*($I60*('Input Bank'!$K60+'Input Bank'!$L60)/30)+($J60*'Input Bank'!M60) -> 0 | N60: =Bobot!$P60*($I60*('Input Bank'!$K60+'Input Bank'!$L60)/30)+($J60*'Input Bank'!N60) -> 0 | O60: =Bobot!$P60*($I60*('Input Bank'!$K60+'Input Bank'!$L60)/30)+($J60*'Input Bank'!O60) -> 0 | P60: =Bobot!$P60*($I60*('Input Bank'!$K60+'Input Bank'!$L60)/30)+($J60*'Input Bank'!P60) -> 0 | Q60: =Bobot!$P60*($I60*('Input Bank'!$K60+'Input Bank'!$L60)/30)+($J60*'Input Bank'!Q60) -> 0 | R60: =Bobot!$P60*($I60*('Input Bank'!$K60+'Input Bank'!$L60)/30)+($J60*'Input Bank'!R60) -> 0 | S60: =Bobot!$P60*($I60*('Input Bank'!$K60+'Input Bank'!$L60)/30)+($J60*'Input Bank'!S60) -> 0 | T60: =Bobot!$P60*($I60*('Input Bank'!$K60+'Input Bank'!$L60)/30)+($J60*'Input Bank'!T60) -> 0 | ... AP60: =Bobot!$P60*($I60*('Input Bank'!$K60+'Input Bank'!$L60)/30)+($J60*'Input Bank'!AP60) -> 0 | AQ60: =$J60*'Input Bank'!AQ60 -> 0 | AR60: =$J60*'Input Bank'!AR60 -> 0 | AS60: =$J60*'Input Bank'!AS60 -> 0 | AT60: =$J60*'Input Bank'!AT60 -> 0 | AU60: =$J60*'Input Bank'!AU60 -> 0 | AV60: =$J60*'Input Bank'!AV60 -> 0 | AW60: =$J60*'Input Bank'!AW60 -> 0 | AX60: =$J60*'Input Bank'!AX60 -> 0 | ... BA60: =$J60*'Input Bank'!BA60 -> 0
A61: =Bobot!P16 -> 1 | F61: 048 | G61: 2.1.8 | H61: Agunan digunakan kembali untuk menutupi posisi short nasabah | L61: =SUM(L62:L67) -> 0 | M61: =SUM(M62:M67) -> 0 | N61: =SUM(N62:N67) -> 0 | O61: =SUM(O62:O67) -> 0 | P61: =SUM(P62:P67) -> 0 | Q61: =SUM(Q62:Q67) -> 0 | R61: =SUM(R62:R67) -> 0 | S61: =SUM(S62:S67) -> 0 | ... BA61: =SUM(BA62:BA67) -> 0
A62: =Bobot!#REF! -> #REF! | F62: 049 | G62: 2.1.9 | H62: Agunan berupa HQLA Level 1 | I62: =Bobot!O62 -> 0 | J62: =Bobot!O62 -> 0 | L62: =IF(Bobot!$P62=0,1,0)*('Input Bank'!L62+'Input Bank'!K62)*I62 -> 0 | M62: =Bobot!$P62*($I62*('Input Bank'!$K62+'Input Bank'!$L62)/30)+($J62*'Input Bank'!M62) -> 0 | N62: =Bobot!$P62*($I62*('Input Bank'!$K62+'Input Bank'!$L62)/30)+($J62*'Input Bank'!N62) -> 0 | O62: =Bobot!$P62*($I62*('Input Bank'!$K62+'Input Bank'!$L62)/30)+($J62*'Input Bank'!O62) -> 0 | P62: =Bobot!$P62*($I62*('Input Bank'!$K62+'Input Bank'!$L62)/30)+($J62*'Input Bank'!P62) -> 0 | Q62: =Bobot!$P62*($I62*('Input Bank'!$K62+'Input Bank'!$L62)/30)+($J62*'Input Bank'!Q62) -> 0 | R62: =Bobot!$P62*($I62*('Input Bank'!$K62+'Input Bank'!$L62)/30)+($J62*'Input Bank'!R62) -> 0 | S62: =Bobot!$P62*($I62*('Input Bank'!$K62+'Input Bank'!$L62)/30)+($J62*'Input Bank'!S62) -> 0 | T62: =Bobot!$P62*($I62*('Input Bank'!$K62+'Input Bank'!$L62)/30)+($J62*'Input Bank'!T62) -> 0 | ... AP62: =Bobot!$P62*($I62*('Input Bank'!$K62+'Input Bank'!$L62)/30)+($J62*'Input Bank'!AP62) -> 0 | AQ62: =$J62*'Input Bank'!AQ62 -> 0 | AR62: =$J62*'Input Bank'!AR62 -> 0 | AS62: =$J62*'Input Bank'!AS62 -> 0 | AT62: =$J62*'Input Bank'!AT62 -> 0 | AU62: =$J62*'Input Bank'!AU62 -> 0 | AV62: =$J62*'Input Bank'!AV62 -> 0 | AW62: =$J62*'Input Bank'!AW62 -> 0 | AX62: =$J62*'Input Bank'!AX62 -> 0 | ... BA62: =$J62*'Input Bank'!BA62 -> 0
A63: =Bobot!#REF! -> #REF! | F63: 050 | G63: 2.1.10 | H63: Agunan berupa HQLA Level 2A | I63: =Bobot!O63 -> 0 | J63: =Bobot!O63 -> 0 | L63: =IF(Bobot!$P63=0,1,0)*('Input Bank'!L63+'Input Bank'!K63)*I63 -> 0 | M63: =Bobot!$P63*($I63*('Input Bank'!$K63+'Input Bank'!$L63)/30)+($J63*'Input Bank'!M63) -> 0 | N63: =Bobot!$P63*($I63*('Input Bank'!$K63+'Input Bank'!$L63)/30)+($J63*'Input Bank'!N63) -> 0 | O63: =Bobot!$P63*($I63*('Input Bank'!$K63+'Input Bank'!$L63)/30)+($J63*'Input Bank'!O63) -> 0 | P63: =Bobot!$P63*($I63*('Input Bank'!$K63+'Input Bank'!$L63)/30)+($J63*'Input Bank'!P63) -> 0 | Q63: =Bobot!$P63*($I63*('Input Bank'!$K63+'Input Bank'!$L63)/30)+($J63*'Input Bank'!Q63) -> 0 | R63: =Bobot!$P63*($I63*('Input Bank'!$K63+'Input Bank'!$L63)/30)+($J63*'Input Bank'!R63) -> 0 | S63: =Bobot!$P63*($I63*('Input Bank'!$K63+'Input Bank'!$L63)/30)+($J63*'Input Bank'!S63) -> 0 | T63: =Bobot!$P63*($I63*('Input Bank'!$K63+'Input Bank'!$L63)/30)+($J63*'Input Bank'!T63) -> 0 | ... AP63: =Bobot!$P63*($I63*('Input Bank'!$K63+'Input Bank'!$L63)/30)+($J63*'Input Bank'!AP63) -> 0 | AQ63: =$J63*'Input Bank'!AQ63 -> 0 | AR63: =$J63*'Input Bank'!AR63 -> 0 | AS63: =$J63*'Input Bank'!AS63 -> 0 | AT63: =$J63*'Input Bank'!AT63 -> 0 | AU63: =$J63*'Input Bank'!AU63 -> 0 | AV63: =$J63*'Input Bank'!AV63 -> 0 | AW63: =$J63*'Input Bank'!AW63 -> 0 | AX63: =$J63*'Input Bank'!AX63 -> 0 | ... BA63: =$J63*'Input Bank'!BA63 -> 0
A64: =Bobot!P17 -> 1 | F64: 051 | G64: 2.1.11 | H64: Agunan HQLA Level 2B berupa EBA | I64: =Bobot!O64 -> 0 | J64: =Bobot!O64 -> 0 | L64: =IF(Bobot!$P64=0,1,0)*('Input Bank'!L64+'Input Bank'!K64)*I64 -> 0 | M64: =Bobot!$P64*($I64*('Input Bank'!$K64+'Input Bank'!$L64)/30)+($J64*'Input Bank'!M64) -> 0 | N64: =Bobot!$P64*($I64*('Input Bank'!$K64+'Input Bank'!$L64)/30)+($J64*'Input Bank'!N64) -> 0 | O64: =Bobot!$P64*($I64*('Input Bank'!$K64+'Input Bank'!$L64)/30)+($J64*'Input Bank'!O64) -> 0 | P64: =Bobot!$P64*($I64*('Input Bank'!$K64+'Input Bank'!$L64)/30)+($J64*'Input Bank'!P64) -> 0 | Q64: =Bobot!$P64*($I64*('Input Bank'!$K64+'Input Bank'!$L64)/30)+($J64*'Input Bank'!Q64) -> 0 | R64: =Bobot!$P64*($I64*('Input Bank'!$K64+'Input Bank'!$L64)/30)+($J64*'Input Bank'!R64) -> 0 | S64: =Bobot!$P64*($I64*('Input Bank'!$K64+'Input Bank'!$L64)/30)+($J64*'Input Bank'!S64) -> 0 | T64: =Bobot!$P64*($I64*('Input Bank'!$K64+'Input Bank'!$L64)/30)+($J64*'Input Bank'!T64) -> 0 | ... AP64: =Bobot!$P64*($I64*('Input Bank'!$K64+'Input Bank'!$L64)/30)+($J64*'Input Bank'!AP64) -> 0 | AQ64: =$J64*'Input Bank'!AQ64 -> 0 | AR64: =$J64*'Input Bank'!AR64 -> 0 | AS64: =$J64*'Input Bank'!AS64 -> 0 | AT64: =$J64*'Input Bank'!AT64 -> 0 | AU64: =$J64*'Input Bank'!AU64 -> 0 | AV64: =$J64*'Input Bank'!AV64 -> 0 | AW64: =$J64*'Input Bank'!AW64 -> 0 | AX64: =$J64*'Input Bank'!AX64 -> 0 | ... BA64: =$J64*'Input Bank'!BA64 -> 0
A65: =Bobot!P18 -> 1 | F65: 052 | G65: 2.1.12 | H65: Agunan HQLA Level 2B selain EBA | I65: =Bobot!O65 -> 0 | J65: =Bobot!O65 -> 0 | L65: =IF(Bobot!$P65=0,1,0)*('Input Bank'!L65+'Input Bank'!K65)*I65 -> 0 | M65: =Bobot!$P65*($I65*('Input Bank'!$K65+'Input Bank'!$L65)/30)+($J65*'Input Bank'!M65) -> 0 | N65: =Bobot!$P65*($I65*('Input Bank'!$K65+'Input Bank'!$L65)/30)+($J65*'Input Bank'!N65) -> 0 | O65: =Bobot!$P65*($I65*('Input Bank'!$K65+'Input Bank'!$L65)/30)+($J65*'Input Bank'!O65) -> 0 | P65: =Bobot!$P65*($I65*('Input Bank'!$K65+'Input Bank'!$L65)/30)+($J65*'Input Bank'!P65) -> 0 | Q65: =Bobot!$P65*($I65*('Input Bank'!$K65+'Input Bank'!$L65)/30)+($J65*'Input Bank'!Q65) -> 0 | R65: =Bobot!$P65*($I65*('Input Bank'!$K65+'Input Bank'!$L65)/30)+($J65*'Input Bank'!R65) -> 0 | S65: =Bobot!$P65*($I65*('Input Bank'!$K65+'Input Bank'!$L65)/30)+($J65*'Input Bank'!S65) -> 0 | T65: =Bobot!$P65*($I65*('Input Bank'!$K65+'Input Bank'!$L65)/30)+($J65*'Input Bank'!T65) -> 0 | ... AP65: =Bobot!$P65*($I65*('Input Bank'!$K65+'Input Bank'!$L65)/30)+($J65*'Input Bank'!AP65) -> 0 | AQ65: =$J65*'Input Bank'!AQ65 -> 0 | AR65: =$J65*'Input Bank'!AR65 -> 0 | AS65: =$J65*'Input Bank'!AS65 -> 0 | AT65: =$J65*'Input Bank'!AT65 -> 0 | AU65: =$J65*'Input Bank'!AU65 -> 0 | AV65: =$J65*'Input Bank'!AV65 -> 0 | AW65: =$J65*'Input Bank'!AW65 -> 0 | AX65: =$J65*'Input Bank'!AX65 -> 0 | ... BA65: =$J65*'Input Bank'!BA65 -> 0
A66: =Bobot!#REF! -> #REF! | F66: 053 | G66: 2.1.13 | H66: Transaksi berupa margin lending namun agunan berupa selain HQLA | I66: =Bobot!O66 -> 0 | J66: =Bobot!O66 -> 0 | L66: =IF(Bobot!$P66=0,1,0)*('Input Bank'!L66+'Input Bank'!K66)*I66 -> 0 | M66: =Bobot!$P66*($I66*('Input Bank'!$K66+'Input Bank'!$L66)/30)+($J66*'Input Bank'!M66) -> 0 | N66: =Bobot!$P66*($I66*('Input Bank'!$K66+'Input Bank'!$L66)/30)+($J66*'Input Bank'!N66) -> 0 | O66: =Bobot!$P66*($I66*('Input Bank'!$K66+'Input Bank'!$L66)/30)+($J66*'Input Bank'!O66) -> 0 | P66: =Bobot!$P66*($I66*('Input Bank'!$K66+'Input Bank'!$L66)/30)+($J66*'Input Bank'!P66) -> 0 | Q66: =Bobot!$P66*($I66*('Input Bank'!$K66+'Input Bank'!$L66)/30)+($J66*'Input Bank'!Q66) -> 0 | R66: =Bobot!$P66*($I66*('Input Bank'!$K66+'Input Bank'!$L66)/30)+($J66*'Input Bank'!R66) -> 0 | S66: =Bobot!$P66*($I66*('Input Bank'!$K66+'Input Bank'!$L66)/30)+($J66*'Input Bank'!S66) -> 0 | T66: =Bobot!$P66*($I66*('Input Bank'!$K66+'Input Bank'!$L66)/30)+($J66*'Input Bank'!T66) -> 0 | ... AP66: =Bobot!$P66*($I66*('Input Bank'!$K66+'Input Bank'!$L66)/30)+($J66*'Input Bank'!AP66) -> 0 | AQ66: =$J66*'Input Bank'!AQ66 -> 0 | AR66: =$J66*'Input Bank'!AR66 -> 0 | AS66: =$J66*'Input Bank'!AS66 -> 0 | AT66: =$J66*'Input Bank'!AT66 -> 0 | AU66: =$J66*'Input Bank'!AU66 -> 0 | AV66: =$J66*'Input Bank'!AV66 -> 0 | AW66: =$J66*'Input Bank'!AW66 -> 0 | AX66: =$J66*'Input Bank'!AX66 -> 0 | ... BA66: =$J66*'Input Bank'!BA66 -> 0
A67: =Bobot!P20 -> 1 | F67: 054 | G67: 2.1.14 | H67: Agunan tidak memenuhi persyaratan sebagaimana tersebut diatas | I67: =Bobot!O67 -> 0 | J67: =Bobot!O67 -> 0 | L67: =IF(Bobot!$P67=0,1,0)*('Input Bank'!L67+'Input Bank'!K67)*I67 -> 0 | M67: =Bobot!$P67*($I67*('Input Bank'!$K67+'Input Bank'!$L67)/30)+($J67*'Input Bank'!M67) -> 0 | N67: =Bobot!$P67*($I67*('Input Bank'!$K67+'Input Bank'!$L67)/30)+($J67*'Input Bank'!N67) -> 0 | O67: =Bobot!$P67*($I67*('Input Bank'!$K67+'Input Bank'!$L67)/30)+($J67*'Input Bank'!O67) -> 0 | P67: =Bobot!$P67*($I67*('Input Bank'!$K67+'Input Bank'!$L67)/30)+($J67*'Input Bank'!P67) -> 0 | Q67: =Bobot!$P67*($I67*('Input Bank'!$K67+'Input Bank'!$L67)/30)+($J67*'Input Bank'!Q67) -> 0 | R67: =Bobot!$P67*($I67*('Input Bank'!$K67+'Input Bank'!$L67)/30)+($J67*'Input Bank'!R67) -> 0 | S67: =Bobot!$P67*($I67*('Input Bank'!$K67+'Input Bank'!$L67)/30)+($J67*'Input Bank'!S67) -> 0 | T67: =Bobot!$P67*($I67*('Input Bank'!$K67+'Input Bank'!$L67)/30)+($J67*'Input Bank'!T67) -> 0 | ... AP67: =Bobot!$P67*($I67*('Input Bank'!$K67+'Input Bank'!$L67)/30)+($J67*'Input Bank'!AP67) -> 0 | AQ67: =$J67*'Input Bank'!AQ67 -> 0 | AR67: =$J67*'Input Bank'!AR67 -> 0 | AS67: =$J67*'Input Bank'!AS67 -> 0 | AT67: =$J67*'Input Bank'!AT67 -> 0 | AU67: =$J67*'Input Bank'!AU67 -> 0 | AV67: =$J67*'Input Bank'!AV67 -> 0 | AW67: =$J67*'Input Bank'!AW67 -> 0 | AX67: =$J67*'Input Bank'!AX67 -> 0 | ... BA67: =$J67*'Input Bank'!BA67 -> 0
A68: =Bobot!P21 -> 1 | F68: 055 | G68: 2.2 | H68: Tagihan berdasarkan pihak lawan | L68: =SUM(L69:L75) -> 0 | M68: =SUM(M69:M75) -> 0 | N68: =SUM(N69:N75) -> 0 | O68: =SUM(O69:O75) -> 0 | P68: =SUM(P69:P75) -> 0 | Q68: =SUM(Q69:Q75) -> 0 | R68: =SUM(R69:R75) -> 0 | S68: =SUM(S69:S75) -> 0 | ... BA68: =SUM(BA69:BA75) -> 0
A69: =Bobot!#REF! -> #REF! | F69: 056 | G69: 2.2.1 | H69: Nasabah perorangan | I69: =Bobot!O69 -> 0.5 | J69: =Bobot!O69 -> 0.5 | L69: =IF(Bobot!$P69=0,1,0)*('Input Bank'!L69+'Input Bank'!K69)*I69 -> 0 | M69: =Bobot!$P69*($I69*('Input Bank'!$K69+'Input Bank'!$L69)/30)+($J69*'Input Bank'!M69) -> 0 | N69: =Bobot!$P69*($I69*('Input Bank'!$K69+'Input Bank'!$L69)/30)+($J69*'Input Bank'!N69) -> 0 | O69: =Bobot!$P69*($I69*('Input Bank'!$K69+'Input Bank'!$L69)/30)+($J69*'Input Bank'!O69) -> 0 | P69: =Bobot!$P69*($I69*('Input Bank'!$K69+'Input Bank'!$L69)/30)+($J69*'Input Bank'!P69) -> 0 | Q69: =Bobot!$P69*($I69*('Input Bank'!$K69+'Input Bank'!$L69)/30)+($J69*'Input Bank'!Q69) -> 0 | R69: =Bobot!$P69*($I69*('Input Bank'!$K69+'Input Bank'!$L69)/30)+($J69*'Input Bank'!R69) -> 0 | S69: =Bobot!$P69*($I69*('Input Bank'!$K69+'Input Bank'!$L69)/30)+($J69*'Input Bank'!S69) -> 0 | T69: =Bobot!$P69*($I69*('Input Bank'!$K69+'Input Bank'!$L69)/30)+($J69*'Input Bank'!T69) -> 0 | ... AP69: =Bobot!$P69*($I69*('Input Bank'!$K69+'Input Bank'!$L69)/30)+($J69*'Input Bank'!AP69) -> 0 | AQ69: =$J69*'Input Bank'!AQ69 -> 0 | AR69: =$J69*'Input Bank'!AR69 -> 0 | AS69: =$J69*'Input Bank'!AS69 -> 0 | AT69: =$J69*'Input Bank'!AT69 -> 0 | AU69: =$J69*'Input Bank'!AU69 -> 0 | AV69: =$J69*'Input Bank'!AV69 -> 0 | AW69: =$J69*'Input Bank'!AW69 -> 0 | AX69: =$J69*'Input Bank'!AX69 -> 0 | ... BA69: =$J69*'Input Bank'!BA69 -> 0
A70: =Bobot!P22 -> 1 | F70: 057 | G70: 2.2.2 | H70: Nasabah UMK | I70: =Bobot!O70 -> 0.5 | J70: =Bobot!O70 -> 0.5 | L70: =IF(Bobot!$P70=0,1,0)*('Input Bank'!L70+'Input Bank'!K70)*I70 -> 0 | M70: =Bobot!$P70*($I70*('Input Bank'!$K70+'Input Bank'!$L70)/30)+($J70*'Input Bank'!M70) -> 0 | N70: =Bobot!$P70*($I70*('Input Bank'!$K70+'Input Bank'!$L70)/30)+($J70*'Input Bank'!N70) -> 0 | O70: =Bobot!$P70*($I70*('Input Bank'!$K70+'Input Bank'!$L70)/30)+($J70*'Input Bank'!O70) -> 0 | P70: =Bobot!$P70*($I70*('Input Bank'!$K70+'Input Bank'!$L70)/30)+($J70*'Input Bank'!P70) -> 0 | Q70: =Bobot!$P70*($I70*('Input Bank'!$K70+'Input Bank'!$L70)/30)+($J70*'Input Bank'!Q70) -> 0 | R70: =Bobot!$P70*($I70*('Input Bank'!$K70+'Input Bank'!$L70)/30)+($J70*'Input Bank'!R70) -> 0 | S70: =Bobot!$P70*($I70*('Input Bank'!$K70+'Input Bank'!$L70)/30)+($J70*'Input Bank'!S70) -> 0 | T70: =Bobot!$P70*($I70*('Input Bank'!$K70+'Input Bank'!$L70)/30)+($J70*'Input Bank'!T70) -> 0 | ... AP70: =Bobot!$P70*($I70*('Input Bank'!$K70+'Input Bank'!$L70)/30)+($J70*'Input Bank'!AP70) -> 0 | AQ70: =$J70*'Input Bank'!AQ70 -> 0 | AR70: =$J70*'Input Bank'!AR70 -> 0 | AS70: =$J70*'Input Bank'!AS70 -> 0 | AT70: =$J70*'Input Bank'!AT70 -> 0 | AU70: =$J70*'Input Bank'!AU70 -> 0 | AV70: =$J70*'Input Bank'!AV70 -> 0 | AW70: =$J70*'Input Bank'!AW70 -> 0 | AX70: =$J70*'Input Bank'!AX70 -> 0 | ... BA70: =$J70*'Input Bank'!BA70 -> 0
A71: =Bobot!P23 -> 1 | F71: 058 | G71: 2.2.3 | H71: Korporasi non-finansial | I71: =Bobot!O71 -> 0.5 | J71: =Bobot!O71 -> 0.5 | L71: =IF(Bobot!$P71=0,1,0)*('Input Bank'!L71+'Input Bank'!K71)*I71 -> 0 | M71: =Bobot!$P71*($I71*('Input Bank'!$K71+'Input Bank'!$L71)/30)+($J71*'Input Bank'!M71) -> 0 | N71: =Bobot!$P71*($I71*('Input Bank'!$K71+'Input Bank'!$L71)/30)+($J71*'Input Bank'!N71) -> 0 | O71: =Bobot!$P71*($I71*('Input Bank'!$K71+'Input Bank'!$L71)/30)+($J71*'Input Bank'!O71) -> 0 | P71: =Bobot!$P71*($I71*('Input Bank'!$K71+'Input Bank'!$L71)/30)+($J71*'Input Bank'!P71) -> 0 | Q71: =Bobot!$P71*($I71*('Input Bank'!$K71+'Input Bank'!$L71)/30)+($J71*'Input Bank'!Q71) -> 0 | R71: =Bobot!$P71*($I71*('Input Bank'!$K71+'Input Bank'!$L71)/30)+($J71*'Input Bank'!R71) -> 0 | S71: =Bobot!$P71*($I71*('Input Bank'!$K71+'Input Bank'!$L71)/30)+($J71*'Input Bank'!S71) -> 0 | T71: =Bobot!$P71*($I71*('Input Bank'!$K71+'Input Bank'!$L71)/30)+($J71*'Input Bank'!T71) -> 0 | ... AP71: =Bobot!$P71*($I71*('Input Bank'!$K71+'Input Bank'!$L71)/30)+($J71*'Input Bank'!AP71) -> 0 | AQ71: =$J71*'Input Bank'!AQ71 -> 0 | AR71: =$J71*'Input Bank'!AR71 -> 0 | AS71: =$J71*'Input Bank'!AS71 -> 0 | AT71: =$J71*'Input Bank'!AT71 -> 0 | AU71: =$J71*'Input Bank'!AU71 -> 0 | AV71: =$J71*'Input Bank'!AV71 -> 0 | AW71: =$J71*'Input Bank'!AW71 -> 0 | AX71: =$J71*'Input Bank'!AX71 -> 0 | ... BA71: =$J71*'Input Bank'!BA71 -> 0
A72: =Bobot!P25 -> 1 | F72: 059 | G72: 2.2.4 | H72: Lembaga jasa keuangan | I72: =Bobot!O72 -> 1 | J72: =Bobot!O72 -> 1 | L72: =IF(Bobot!$P72=0,1,0)*('Input Bank'!L72+'Input Bank'!K72)*I72 -> 0 | M72: =Bobot!$P72*($I72*('Input Bank'!$K72+'Input Bank'!$L72)/30)+($J72*'Input Bank'!M72) -> 0 | N72: =Bobot!$P72*($I72*('Input Bank'!$K72+'Input Bank'!$L72)/30)+($J72*'Input Bank'!N72) -> 0 | O72: =Bobot!$P72*($I72*('Input Bank'!$K72+'Input Bank'!$L72)/30)+($J72*'Input Bank'!O72) -> 0 | P72: =Bobot!$P72*($I72*('Input Bank'!$K72+'Input Bank'!$L72)/30)+($J72*'Input Bank'!P72) -> 0 | Q72: =Bobot!$P72*($I72*('Input Bank'!$K72+'Input Bank'!$L72)/30)+($J72*'Input Bank'!Q72) -> 0 | R72: =Bobot!$P72*($I72*('Input Bank'!$K72+'Input Bank'!$L72)/30)+($J72*'Input Bank'!R72) -> 0 | S72: =Bobot!$P72*($I72*('Input Bank'!$K72+'Input Bank'!$L72)/30)+($J72*'Input Bank'!S72) -> 0 | T72: =Bobot!$P72*($I72*('Input Bank'!$K72+'Input Bank'!$L72)/30)+($J72*'Input Bank'!T72) -> 0 | ... AP72: =Bobot!$P72*($I72*('Input Bank'!$K72+'Input Bank'!$L72)/30)+($J72*'Input Bank'!AP72) -> 0 | AQ72: =$J72*'Input Bank'!AQ72 -> 0 | AR72: =$J72*'Input Bank'!AR72 -> 0 | AS72: =$J72*'Input Bank'!AS72 -> 0 | AT72: =$J72*'Input Bank'!AT72 -> 0 | AU72: =$J72*'Input Bank'!AU72 -> 0 | AV72: =$J72*'Input Bank'!AV72 -> 0 | AW72: =$J72*'Input Bank'!AW72 -> 0 | AX72: =$J72*'Input Bank'!AX72 -> 0 | ... BA72: =$J72*'Input Bank'!BA72 -> 0
A73: =Bobot!#REF! -> #REF! | F73: 060 | G73: 2.2.5 | H73: Bank Indonesia | I73: =Bobot!O73 -> 1 | J73: =Bobot!O73 -> 1 | L73: =IF(Bobot!$P73=0,1,0)*('Input Bank'!L73+'Input Bank'!K73)*I73 -> 0 | M73: =Bobot!$P73*($I73*('Input Bank'!$K73+'Input Bank'!$L73)/30)+($J73*'Input Bank'!M73) -> 0 | N73: =Bobot!$P73*($I73*('Input Bank'!$K73+'Input Bank'!$L73)/30)+($J73*'Input Bank'!N73) -> 0 | O73: =Bobot!$P73*($I73*('Input Bank'!$K73+'Input Bank'!$L73)/30)+($J73*'Input Bank'!O73) -> 0 | P73: =Bobot!$P73*($I73*('Input Bank'!$K73+'Input Bank'!$L73)/30)+($J73*'Input Bank'!P73) -> 0 | Q73: =Bobot!$P73*($I73*('Input Bank'!$K73+'Input Bank'!$L73)/30)+($J73*'Input Bank'!Q73) -> 0 | R73: =Bobot!$P73*($I73*('Input Bank'!$K73+'Input Bank'!$L73)/30)+($J73*'Input Bank'!R73) -> 0 | S73: =Bobot!$P73*($I73*('Input Bank'!$K73+'Input Bank'!$L73)/30)+($J73*'Input Bank'!S73) -> 0 | T73: =Bobot!$P73*($I73*('Input Bank'!$K73+'Input Bank'!$L73)/30)+($J73*'Input Bank'!T73) -> 0 | ... AP73: =Bobot!$P73*($I73*('Input Bank'!$K73+'Input Bank'!$L73)/30)+($J73*'Input Bank'!AP73) -> 0 | AQ73: =$J73*'Input Bank'!AQ73 -> 0 | AR73: =$J73*'Input Bank'!AR73 -> 0 | AS73: =$J73*'Input Bank'!AS73 -> 0 | AT73: =$J73*'Input Bank'!AT73 -> 0 | AU73: =$J73*'Input Bank'!AU73 -> 0 | AV73: =$J73*'Input Bank'!AV73 -> 0 | AW73: =$J73*'Input Bank'!AW73 -> 0 | AX73: =$J73*'Input Bank'!AX73 -> 0 | ... BA73: =$J73*'Input Bank'!BA73 -> 0
F74: 061 | G74: 2.2.6 | H74: Entitas sektor publik | I74: =Bobot!O74 -> 0.5 | J74: =Bobot!O74 -> 0.5 | L74: =IF(Bobot!$P74=0,1,0)*('Input Bank'!L74+'Input Bank'!K74)*I74 -> 0 | M74: =Bobot!$P74*($I74*('Input Bank'!$K74+'Input Bank'!$L74)/30)+($J74*'Input Bank'!M74) -> 0 | N74: =Bobot!$P74*($I74*('Input Bank'!$K74+'Input Bank'!$L74)/30)+($J74*'Input Bank'!N74) -> 0 | O74: =Bobot!$P74*($I74*('Input Bank'!$K74+'Input Bank'!$L74)/30)+($J74*'Input Bank'!O74) -> 0 | P74: =Bobot!$P74*($I74*('Input Bank'!$K74+'Input Bank'!$L74)/30)+($J74*'Input Bank'!P74) -> 0 | Q74: =Bobot!$P74*($I74*('Input Bank'!$K74+'Input Bank'!$L74)/30)+($J74*'Input Bank'!Q74) -> 0 | R74: =Bobot!$P74*($I74*('Input Bank'!$K74+'Input Bank'!$L74)/30)+($J74*'Input Bank'!R74) -> 0 | S74: =Bobot!$P74*($I74*('Input Bank'!$K74+'Input Bank'!$L74)/30)+($J74*'Input Bank'!S74) -> 0 | T74: =Bobot!$P74*($I74*('Input Bank'!$K74+'Input Bank'!$L74)/30)+($J74*'Input Bank'!T74) -> 0 | ... AP74: =Bobot!$P74*($I74*('Input Bank'!$K74+'Input Bank'!$L74)/30)+($J74*'Input Bank'!AP74) -> 0 | AQ74: =$J74*'Input Bank'!AQ74 -> 0 | AR74: =$J74*'Input Bank'!AR74 -> 0 | AS74: =$J74*'Input Bank'!AS74 -> 0 | AT74: =$J74*'Input Bank'!AT74 -> 0 | AU74: =$J74*'Input Bank'!AU74 -> 0 | AV74: =$J74*'Input Bank'!AV74 -> 0 | AW74: =$J74*'Input Bank'!AW74 -> 0 | AX74: =$J74*'Input Bank'!AX74 -> 0 | ... BA74: =$J74*'Input Bank'!BA74 -> 0
A75: =Bobot!P28 -> 1 | F75: 062 | G75: 2.2.7 | H75: Lainnya (Pemerintah Pusat, pemerintah negara lain dan bank pembangunan multilateral) | I75: =Bobot!O75 -> 0.5 | J75: =Bobot!O75 -> 0.5 | L75: =IF(Bobot!$P75=0,1,0)*('Input Bank'!L75+'Input Bank'!K75)*I75 -> 0 | M75: =Bobot!$P75*($I75*('Input Bank'!$K75+'Input Bank'!$L75)/30)+($J75*'Input Bank'!M75) -> 0 | N75: =Bobot!$P75*($I75*('Input Bank'!$K75+'Input Bank'!$L75)/30)+($J75*'Input Bank'!N75) -> 0 | O75: =Bobot!$P75*($I75*('Input Bank'!$K75+'Input Bank'!$L75)/30)+($J75*'Input Bank'!O75) -> 0 | P75: =Bobot!$P75*($I75*('Input Bank'!$K75+'Input Bank'!$L75)/30)+($J75*'Input Bank'!P75) -> 0 | Q75: =Bobot!$P75*($I75*('Input Bank'!$K75+'Input Bank'!$L75)/30)+($J75*'Input Bank'!Q75) -> 0 | R75: =Bobot!$P75*($I75*('Input Bank'!$K75+'Input Bank'!$L75)/30)+($J75*'Input Bank'!R75) -> 0 | S75: =Bobot!$P75*($I75*('Input Bank'!$K75+'Input Bank'!$L75)/30)+($J75*'Input Bank'!S75) -> 0 | T75: =Bobot!$P75*($I75*('Input Bank'!$K75+'Input Bank'!$L75)/30)+($J75*'Input Bank'!T75) -> 0 | ... AP75: =Bobot!$P75*($I75*('Input Bank'!$K75+'Input Bank'!$L75)/30)+($J75*'Input Bank'!AP75) -> 0 | AQ75: =$J75*'Input Bank'!AQ75 -> 0 | AR75: =$J75*'Input Bank'!AR75 -> 0 | AS75: =$J75*'Input Bank'!AS75 -> 0 | AT75: =$J75*'Input Bank'!AT75 -> 0 | AU75: =$J75*'Input Bank'!AU75 -> 0 | AV75: =$J75*'Input Bank'!AV75 -> 0 | AW75: =$J75*'Input Bank'!AW75 -> 0 | AX75: =$J75*'Input Bank'!AX75 -> 0 | ... BA75: =$J75*'Input Bank'!BA75 -> 0
A76: =Bobot!P29 -> 1 | F76: 063 | G76: 2.3 | H76: FX Swaps jatuh tempo | I76: =Bobot!O76 -> 1 | J76: =Bobot!O76 -> 1 | L76: =IF(Bobot!$P76=0,1,0)*('Input Bank'!L76+'Input Bank'!K76)*I76 -> 0 | M76: =Bobot!$P76*($I76*('Input Bank'!$K76+'Input Bank'!$L76)/30)+($J76*'Input Bank'!M76) -> 0 | N76: =Bobot!$P76*($I76*('Input Bank'!$K76+'Input Bank'!$L76)/30)+($J76*'Input Bank'!N76) -> 0 | O76: =Bobot!$P76*($I76*('Input Bank'!$K76+'Input Bank'!$L76)/30)+($J76*'Input Bank'!O76) -> 0 | P76: =Bobot!$P76*($I76*('Input Bank'!$K76+'Input Bank'!$L76)/30)+($J76*'Input Bank'!P76) -> 0 | Q76: =Bobot!$P76*($I76*('Input Bank'!$K76+'Input Bank'!$L76)/30)+($J76*'Input Bank'!Q76) -> 0 | R76: =Bobot!$P76*($I76*('Input Bank'!$K76+'Input Bank'!$L76)/30)+($J76*'Input Bank'!R76) -> 0 | S76: =Bobot!$P76*($I76*('Input Bank'!$K76+'Input Bank'!$L76)/30)+($J76*'Input Bank'!S76) -> 0 | T76: =Bobot!$P76*($I76*('Input Bank'!$K76+'Input Bank'!$L76)/30)+($J76*'Input Bank'!T76) -> 0 | ... AP76: =Bobot!$P76*($I76*('Input Bank'!$K76+'Input Bank'!$L76)/30)+($J76*'Input Bank'!AP76) -> 0 | AQ76: =$J76*'Input Bank'!AQ76 -> 0 | AR76: =$J76*'Input Bank'!AR76 -> 0 | AS76: =$J76*'Input Bank'!AS76 -> 0 | AT76: =$J76*'Input Bank'!AT76 -> 0 | AU76: =$J76*'Input Bank'!AU76 -> 0 | AV76: =$J76*'Input Bank'!AV76 -> 0 | AW76: =$J76*'Input Bank'!AW76 -> 0 | AX76: =$J76*'Input Bank'!AX76 -> 0 | ... BA76: =$J76*'Input Bank'!BA76 -> 0
A77: =Bobot!P30 -> 1 | F77: 064 | G77: 2.4 | H77: Arus kas masuk dari Derivatif selain yang dilaporkan pada 2.3 | I77: =Bobot!O77 -> 1 | J77: =Bobot!O77 -> 1 | L77: =IF(Bobot!$P77=0,1,0)*('Input Bank'!L77+'Input Bank'!K77)*I77 -> 0 | M77: =Bobot!$P77*($I77*('Input Bank'!$K77+'Input Bank'!$L77)/30)+($J77*'Input Bank'!M77) -> 0 | N77: =Bobot!$P77*($I77*('Input Bank'!$K77+'Input Bank'!$L77)/30)+($J77*'Input Bank'!N77) -> 0 | O77: =Bobot!$P77*($I77*('Input Bank'!$K77+'Input Bank'!$L77)/30)+($J77*'Input Bank'!O77) -> 0 | P77: =Bobot!$P77*($I77*('Input Bank'!$K77+'Input Bank'!$L77)/30)+($J77*'Input Bank'!P77) -> 0 | Q77: =Bobot!$P77*($I77*('Input Bank'!$K77+'Input Bank'!$L77)/30)+($J77*'Input Bank'!Q77) -> 0 | R77: =Bobot!$P77*($I77*('Input Bank'!$K77+'Input Bank'!$L77)/30)+($J77*'Input Bank'!R77) -> 0 | S77: =Bobot!$P77*($I77*('Input Bank'!$K77+'Input Bank'!$L77)/30)+($J77*'Input Bank'!S77) -> 0 | T77: =Bobot!$P77*($I77*('Input Bank'!$K77+'Input Bank'!$L77)/30)+($J77*'Input Bank'!T77) -> 0 | ... AP77: =Bobot!$P77*($I77*('Input Bank'!$K77+'Input Bank'!$L77)/30)+($J77*'Input Bank'!AP77) -> 0 | AQ77: =$J77*'Input Bank'!AQ77 -> 0 | AR77: =$J77*'Input Bank'!AR77 -> 0 | AS77: =$J77*'Input Bank'!AS77 -> 0 | AT77: =$J77*'Input Bank'!AT77 -> 0 | AU77: =$J77*'Input Bank'!AU77 -> 0 | AV77: =$J77*'Input Bank'!AV77 -> 0 | AW77: =$J77*'Input Bank'!AW77 -> 0 | AX77: =$J77*'Input Bank'!AX77 -> 0 | ... BA77: =$J77*'Input Bank'!BA77 -> 0
A78: =Bobot!#REF! -> #REF! | F78: 065 | G78: 2.5 | H78: Surat berharga yang jatuh tempo | L78: =SUM(L79,L80) -> 0 | M78: =SUM(M79,M80) -> 0 | N78: =SUM(N79,N80) -> 0 | O78: =SUM(O79,O80) -> 0 | P78: =SUM(P79,P80) -> 0 | Q78: =SUM(Q79,Q80) -> 0 | R78: =SUM(R79,R80) -> 0 | S78: =SUM(S79,S80) -> 0 | ... BA78: =SUM(BA79,BA80) -> 0
A79: =Bobot!#REF! -> #REF! | F79: 066 | G79: 2.5.1 | H79: Surat berharga non-HQLA yang jatuh tempo | I79: =Bobot!O79 -> 1 | J79: =Bobot!O79 -> 1 | L79: =IF(Bobot!$P79=0,1,0)*('Input Bank'!L79+'Input Bank'!K79)*I79 -> 0 | M79: =Bobot!$P79*($I79*('Input Bank'!$K79+'Input Bank'!$L79)/30)+($J79*'Input Bank'!M79) -> 0 | N79: =Bobot!$P79*($I79*('Input Bank'!$K79+'Input Bank'!$L79)/30)+($J79*'Input Bank'!N79) -> 0 | O79: =Bobot!$P79*($I79*('Input Bank'!$K79+'Input Bank'!$L79)/30)+($J79*'Input Bank'!O79) -> 0 | P79: =Bobot!$P79*($I79*('Input Bank'!$K79+'Input Bank'!$L79)/30)+($J79*'Input Bank'!P79) -> 0 | Q79: =Bobot!$P79*($I79*('Input Bank'!$K79+'Input Bank'!$L79)/30)+($J79*'Input Bank'!Q79) -> 0 | R79: =Bobot!$P79*($I79*('Input Bank'!$K79+'Input Bank'!$L79)/30)+($J79*'Input Bank'!R79) -> 0 | S79: =Bobot!$P79*($I79*('Input Bank'!$K79+'Input Bank'!$L79)/30)+($J79*'Input Bank'!S79) -> 0 | T79: =Bobot!$P79*($I79*('Input Bank'!$K79+'Input Bank'!$L79)/30)+($J79*'Input Bank'!T79) -> 0 | ... AP79: =Bobot!$P79*($I79*('Input Bank'!$K79+'Input Bank'!$L79)/30)+($J79*'Input Bank'!AP79) -> 0 | AQ79: =$J79*'Input Bank'!AQ79 -> 0 | AR79: =$J79*'Input Bank'!AR79 -> 0 | AS79: =$J79*'Input Bank'!AS79 -> 0 | AT79: =$J79*'Input Bank'!AT79 -> 0 | AU79: =$J79*'Input Bank'!AU79 -> 0 | AV79: =$J79*'Input Bank'!AV79 -> 0 | AW79: =$J79*'Input Bank'!AW79 -> 0 | AX79: =$J79*'Input Bank'!AX79 -> 0 | ... BA79: =$J79*'Input Bank'!BA79 -> 0
A80: =Bobot!#REF! -> #REF! | F80: 067 | G80: 2.5.2 | H80: Surat berharga HQLA yang jatuh tempo | I80: =Bobot!O80 -> 0 | J80: =Bobot!O80 -> 0 | L80: =IF(Bobot!$P80=0,1,0)*('Input Bank'!L80+'Input Bank'!K80)*I80 -> 0 | M80: =Bobot!$P80*($I80*('Input Bank'!$K80+'Input Bank'!$L80)/30)+($J80*'Input Bank'!M80) -> 0 | N80: =Bobot!$P80*($I80*('Input Bank'!$K80+'Input Bank'!$L80)/30)+($J80*'Input Bank'!N80) -> 0 | O80: =Bobot!$P80*($I80*('Input Bank'!$K80+'Input Bank'!$L80)/30)+($J80*'Input Bank'!O80) -> 0 | P80: =Bobot!$P80*($I80*('Input Bank'!$K80+'Input Bank'!$L80)/30)+($J80*'Input Bank'!P80) -> 0 | Q80: =Bobot!$P80*($I80*('Input Bank'!$K80+'Input Bank'!$L80)/30)+($J80*'Input Bank'!Q80) -> 0 | R80: =Bobot!$P80*($I80*('Input Bank'!$K80+'Input Bank'!$L80)/30)+($J80*'Input Bank'!R80) -> 0 | S80: =Bobot!$P80*($I80*('Input Bank'!$K80+'Input Bank'!$L80)/30)+($J80*'Input Bank'!S80) -> 0 | T80: =Bobot!$P80*($I80*('Input Bank'!$K80+'Input Bank'!$L80)/30)+($J80*'Input Bank'!T80) -> 0 | ... AQ80: =Bobot!$P80*($I80*('Input Bank'!$K80+'Input Bank'!$L80)/30)+($J80*'Input Bank'!AQ80) -> 0 | AR80: =$J80*'Input Bank'!AR80 -> 0 | AS80: =$J80*'Input Bank'!AS80 -> 0 | AT80: =$J80*'Input Bank'!AT80 -> 0 | AU80: =$J80*'Input Bank'!AU80 -> 0 | AV80: =$J80*'Input Bank'!AV80 -> 0 | AW80: =$J80*'Input Bank'!AW80 -> 0 | AX80: =$J80*'Input Bank'!AX80 -> 0 | AY80: =$J80*'Input Bank'!AY80 -> 0 | ... BA80: =$J80*'Input Bank'!BA80 -> 0
A81: =Bobot!#REF! -> #REF! | F81: 068 | G81: 2.6 | H81: Arus Kas Masuk dari tagihan kontraktual Lainnya | I81: =Bobot!O81 -> 0.5 | J81: =Bobot!O81 -> 0.5 | L81: =IF(Bobot!$P81=0,1,0)*('Input Bank'!L81+'Input Bank'!K81)*I81 -> 0 | M81: =Bobot!$P81*($I81*('Input Bank'!$K81+'Input Bank'!$L81)/30)+($J81*'Input Bank'!M81) -> 0 | N81: =Bobot!$P81*($I81*('Input Bank'!$K81+'Input Bank'!$L81)/30)+($J81*'Input Bank'!N81) -> 0 | O81: =Bobot!$P81*($I81*('Input Bank'!$K81+'Input Bank'!$L81)/30)+($J81*'Input Bank'!O81) -> 0 | P81: =Bobot!$P81*($I81*('Input Bank'!$K81+'Input Bank'!$L81)/30)+($J81*'Input Bank'!P81) -> 0 | Q81: =Bobot!$P81*($I81*('Input Bank'!$K81+'Input Bank'!$L81)/30)+($J81*'Input Bank'!Q81) -> 0 | R81: =Bobot!$P81*($I81*('Input Bank'!$K81+'Input Bank'!$L81)/30)+($J81*'Input Bank'!R81) -> 0 | S81: =Bobot!$P81*($I81*('Input Bank'!$K81+'Input Bank'!$L81)/30)+($J81*'Input Bank'!S81) -> 0 | T81: =Bobot!$P81*($I81*('Input Bank'!$K81+'Input Bank'!$L81)/30)+($J81*'Input Bank'!T81) -> 0 | ... AP81: =Bobot!$P81*($I81*('Input Bank'!$K81+'Input Bank'!$L81)/30)+($J81*'Input Bank'!AP81) -> 0 | AQ81: =$J81*'Input Bank'!AQ81 -> 0 | AR81: =$J81*'Input Bank'!AR81 -> 0 | AS81: =$J81*'Input Bank'!AS81 -> 0 | AT81: =$J81*'Input Bank'!AT81 -> 0 | AU81: =$J81*'Input Bank'!AU81 -> 0 | AV81: =$J81*'Input Bank'!AV81 -> 0 | AW81: =$J81*'Input Bank'!AW81 -> 0 | AX81: =$J81*'Input Bank'!AX81 -> 0 | ... BA81: =$J81*'Input Bank'!BA81 -> 0
A82: =Bobot!#REF! -> #REF! | F82: 069 | G82: 2.7 | H82: Total Arus Kas Masuk | L82: =SUM(L53,L68,L76,L77,L78,L81) -> 0 | M82: =SUM(M53,M68,M76,M77,M78,M81) -> 0 | N82: =SUM(N53,N68,N76,N77,N78,N81) -> 0 | O82: =SUM(O53,O68,O76,O77,O78,O81) -> 0 | P82: =SUM(P53,P68,P76,P77,P78,P81) -> 0 | Q82: =SUM(Q53,Q68,Q76,Q77,Q78,Q81) -> 0 | R82: =SUM(R53,R68,R76,R77,R78,R81) -> 0 | S82: =SUM(S53,S68,S76,S77,S78,S81) -> 0 | ... BA82: =SUM(BA53,BA68,BA76,BA77,BA78,BA81) -> 0
A83: =Bobot!#REF! -> #REF! | F83: 070 | G83: 2.8 | H83: Net contractual gap | L83: =L51+L82 -> 0 | M83: =M51+M82 -> 0 | N83: =N51+N82 -> 0 | O83: =O51+O82 -> 0 | P83: =P51+P82 -> 0 | Q83: =Q51+Q82 -> 0 | R83: =R51+R82 -> 0 | S83: =S51+S82 -> 0 | ... BA83: =BA51+BA82 -> 0
A84: =Bobot!#REF! -> #REF! | F84: 071 | G84: 2.9 | H84: Gap arus kas keluar kumulatif netto | L84: =K84+L83 -> 0 | M84: =L84+M83 -> 0 | N84: =M84+N83 -> 0 | O84: =N84+O83 -> 0 | P84: =O84+P83 -> 0 | Q84: =P84+Q83 -> 0 | R84: =Q84+R83 -> 0 | S84: =R84+S83 -> 0 | ... BA84: =AZ84+BA83 -> 0
A85: =Bobot!P48 -> 1 | F85: 072 | G85: 3 | H85: COUNTERBALANCING CAPACITY | I85: Weight - open | J85: Weight - term | K85: Stok awal | L85: Tanpa Maturitas (Open) | M85: O/N (selain Open) | N85: Hari-2 | O85: Hari-3 | P85: Hari-4 | Q85: Hari-5 | R85: Hari-6 | S85: Hari-7 | T85: Hari-8 | U85: Hari-9 | V85: Hari-10 | W85: Hari-11 | X85: Hari-12 | Y85: Hari-13 | Z85: Hari-14 | AA85: Hari-15 | AB85: Hari-16 | AC85: Hari-17 | AD85: Hari-18 | AE85: Hari-19 | AF85: Hari-20 | AG85: Hari-21 | AH85: Hari-22 | AI85: Hari-23 | AJ85: Hari-24 | AK85: Hari-25 | AL85: Hari-26 | AM85: Hari-27 | AN85: Hari-28 | AO85: Hari-29 | AP85: Hari-30 | AQ85: > mg 4 s.d. mg 5 | AR85: > mg 5 s.d. 2 bln | AS85: > 2 bln s.d 3 bln | AT85: > 3 bln s.d 4 bln | AU85: > 4 bln s.d 5 bln | AV85: > 5 bln s.d 6 bln | AW85: > 6 bln s.d. 9 bln | AX85: > 9 bln s.d. 12 bln | AY85: > 12 bln s.d. 2 thn | AZ85: > 2 thn s.d. 5 thn | BA85: > 5 thn
A86: =Bobot!P51 -> 0 | F86: 073 | G86: 3.1 | H86: Kas dan setara kas | I86: =Bobot!O86 -> 1 | J86: =Bobot!O86 -> 1 | K86: =$J86*'Input Bank'!K86 -> 0
A87: =Bobot!P52 -> 0 | F87: 074 | G87: 3.2 | H87: Penempatan di Bank Indonesia yang dapat ditarik tanpa hambatan atau penalti | I87: =Bobot!O87 -> 1 | J87: =Bobot!O87 -> 1 | K87: =$J87*'Input Bank'!K87 -> 0 | M87: =$J87*'Input Bank'!M87 -> 0
A88: =Bobot!P53 -> 0 | F88: 075 | G88: 3.3 | H88: HQLA Level 1 berupa surat berharga | K88: =SUM(K89:K91) -> 0 | L88: =SUM(L89:L91) -> 0 | M88: =SUM(M89:M91) -> 0 | N88: =SUM(N89:N91) -> 0 | O88: =SUM(O89:O91) -> 0 | P88: =SUM(P89:P91) -> 0 | Q88: =SUM(Q89:Q91) -> 0 | R88: =SUM(R89:R91) -> 0 | ... BA88: =SUM(BA89:BA91) -> 0
F89: 076 | G89: 3.3.1 | H89: Diterbitkan atau dijamin pemerintah negara lain, bank sentral negara lain, entitas sektor publik, bank pembangunan multilateral, lembaga internasional yang memenuhi kriteria Pasal 10 ayat (1) huruf c POJK LCR | I89: =Bobot!O89 -> 1 | J89: =Bobot!O89 -> 1 | K89: =$J89*'Input Bank'!K89 -> 0 | L89: =$J89*'Input Bank'!L89 -> 0 | M89: =$J89*'Input Bank'!M89 -> 0 | N89: =$J89*'Input Bank'!N89 -> 0 | O89: =$J89*'Input Bank'!O89 -> 0 | P89: =$J89*'Input Bank'!P89 -> 0 | Q89: =$J89*'Input Bank'!Q89 -> 0 | R89: =$J89*'Input Bank'!R89 -> 0 | ... BA89: =$J89*'Input Bank'!BA89 -> 0
F90: 077 | G90: 3.3.2 | H90: Surat berharga yang diterbitkan Pemerintah Pusat dan Bank Indonesia dalam rupiah dan valuta asing yang memenuhi kriteria Pasal 10 ayat (1) huruf d dan e POJK LCR | I90: =Bobot!O90 -> 1 | J90: =Bobot!O90 -> 1 | K90: =$J90*'Input Bank'!K90 -> 0 | L90: =$J90*'Input Bank'!L90 -> 0 | M90: =$J90*'Input Bank'!M90 -> 0 | N90: =$J90*'Input Bank'!N90 -> 0 | O90: =$J90*'Input Bank'!O90 -> 0 | P90: =$J90*'Input Bank'!P90 -> 0 | Q90: =$J90*'Input Bank'!Q90 -> 0 | R90: =$J90*'Input Bank'!R90 -> 0 | ... BA90: =$J90*'Input Bank'!BA90 -> 0
F91: 078 | G91: 3.3.3 | H91: Surat berharga yang diterbitkan oleh pemerintah dan bank sentral negara lain dalam valuta asing dengan bobot risiko lebih dari 0% yang memenuhi kriteria Pasal 10 ayat (1) huruf f POJK LCR | I91: =Bobot!O91 -> 1 | J91: =Bobot!O91 -> 1 | K91: =$J91*'Input Bank'!K91 -> 0 | L91: =$J91*'Input Bank'!L91 -> 0 | M91: =$J91*'Input Bank'!M91 -> 0 | N91: =$J91*'Input Bank'!N91 -> 0 | O91: =$J91*'Input Bank'!O91 -> 0 | P91: =$J91*'Input Bank'!P91 -> 0 | Q91: =$J91*'Input Bank'!Q91 -> 0 | R91: =$J91*'Input Bank'!R91 -> 0 | ... BA91: =$J91*'Input Bank'!BA91 -> 0
A92: =Bobot!#REF! -> #REF! | F92: 079 | G92: 3.4 | H92: HQLA Level 2A | K92: =SUM(K93:K94) -> 0 | L92: =SUM(L93:L94) -> 0 | M92: =SUM(M93:M94) -> 0 | N92: =SUM(N93:N94) -> 0 | O92: =SUM(O93:O94) -> 0 | P92: =SUM(P93:P94) -> 0 | Q92: =SUM(Q93:Q94) -> 0 | R92: =SUM(R93:R94) -> 0 | ... BA92: =SUM(BA93:BA94) -> 0
F93: 080 | G93: 3.4.1 | H93: Surat Berharga diterbitkan atau dijamin pemerintah negara lain, bank sentral negara lain, entitas sektor publik, bank pembangunan multilateral, lembaga internasional yang memenuhi kriteria Pasal 11 ayat (1) huruf a POJK LCR | I93: =Bobot!O93 -> 0.85 | J93: =Bobot!O93 -> 0.85 | K93: =$J93*'Input Bank'!K93 -> 0 | L93: =$J93*'Input Bank'!L93 -> 0 | M93: =$J93*'Input Bank'!M93 -> 0 | N93: =$J93*'Input Bank'!N93 -> 0 | O93: =$J93*'Input Bank'!O93 -> 0 | P93: =$J93*'Input Bank'!P93 -> 0 | Q93: =$J93*'Input Bank'!Q93 -> 0 | R93: =$J93*'Input Bank'!R93 -> 0 | ... BA93: =$J93*'Input Bank'!BA93 -> 0
F94: 081 | G94: 3.4.2 | H94: Surat Berharga berupa surat utang yang diterbitkan oleh korporasi termasuk commercial paper dan covered bonds yang memenuhi kriteria Pasal 11 ayat (1) huruf b POJK LCR | I94: =Bobot!O94 -> 0.85 | J94: =Bobot!O94 -> 0.85 | K94: =$J94*'Input Bank'!K94 -> 0 | L94: =$J94*'Input Bank'!L94 -> 0 | M94: =$J94*'Input Bank'!M94 -> 0 | N94: =$J94*'Input Bank'!N94 -> 0 | O94: =$J94*'Input Bank'!O94 -> 0 | P94: =$J94*'Input Bank'!P94 -> 0 | Q94: =$J94*'Input Bank'!Q94 -> 0 | R94: =$J94*'Input Bank'!R94 -> 0 | ... BA94: =$J94*'Input Bank'!BA94 -> 0
A95: =Bobot!P55 -> 0 | F95: 082 | G95: 3.5 | H95: HQLA Level 2B | K95: =SUM(K96:K99) -> 0 | L95: =SUM(L96:L99) -> 0 | M95: =SUM(M96:M99) -> 0 | N95: =SUM(N96:N99) -> 0 | O95: =SUM(O96:O99) -> 0 | P95: =SUM(P96:P99) -> 0 | Q95: =SUM(Q96:Q99) -> 0 | R95: =SUM(R96:R99) -> 0 | ... BA95: =SUM(BA96:BA99) -> 0
F96: 083 | G96: 3.5.1 | H96: Efek beragun aset (EBA) berupa rumah tinggal yang memenuhi kriteria Pasal 12 ayat (1) huruf a POJK LCR | I96: =Bobot!O96 -> 0.85 | J96: =Bobot!O96 -> 0.85 | K96: =$J96*'Input Bank'!K96 -> 0 | L96: =$J96*'Input Bank'!L96 -> 0 | M96: =$J96*'Input Bank'!M96 -> 0 | N96: =$J96*'Input Bank'!N96 -> 0 | O96: =$J96*'Input Bank'!O96 -> 0 | P96: =$J96*'Input Bank'!P96 -> 0 | Q96: =$J96*'Input Bank'!Q96 -> 0 | R96: =$J96*'Input Bank'!R96 -> 0 | ... BA96: =$J96*'Input Bank'!BA96 -> 0
F97: 084 | G97: 3.5.2 | H97: Surat berharga yang diterbitkan atau dijamin oleh pemerintah negara lain, bank sentral negara lain, dan/atau entitas sektor publik yang memenuhi kriteria Pasal 12 ayat (1) huruf b POJK LCR | I97: =Bobot!O97 -> 0.85 | J97: =Bobot!O97 -> 0.85 | K97: =$J97*'Input Bank'!K97 -> 0 | L97: =$J97*'Input Bank'!L97 -> 0 | M97: =$J97*'Input Bank'!M97 -> 0 | N97: =$J97*'Input Bank'!N97 -> 0 | O97: =$J97*'Input Bank'!O97 -> 0 | P97: =$J97*'Input Bank'!P97 -> 0 | Q97: =$J97*'Input Bank'!Q97 -> 0 | R97: =$J97*'Input Bank'!R97 -> 0 | ... BA97: =$J97*'Input Bank'!BA97 -> 0
F98: 085 | G98: 3.5.3 | H98: Surat berharga berupa surat utang yang diterbitkan oleh korporasi yang memenuhi kriteria Pasal 12 ayat (1) huruf c POJK LCR | I98: =Bobot!O98 -> 0.85 | J98: =Bobot!O98 -> 0.85 | K98: =$J98*'Input Bank'!K98 -> 0 | L98: =$J98*'Input Bank'!L98 -> 0 | M98: =$J98*'Input Bank'!M98 -> 0 | N98: =$J98*'Input Bank'!N98 -> 0 | O98: =$J98*'Input Bank'!O98 -> 0 | P98: =$J98*'Input Bank'!P98 -> 0 | Q98: =$J98*'Input Bank'!Q98 -> 0 | R98: =$J98*'Input Bank'!R98 -> 0 | ... BA98: =$J98*'Input Bank'!BA98 -> 0
F99: 086 | G99: 3.5.4 | H99: Saham biasa yang dimiliki perusahaan anak bukan Bank yang memenuhi kriteria Pasal 12 ayat (1) huruf d POJK LCR | I99: =Bobot!O99 -> 0.85 | J99: =Bobot!O99 -> 0.85 | K99: =$J99*'Input Bank'!K99 -> 0 | L99: =$J99*'Input Bank'!L99 -> 0 | M99: =$J99*'Input Bank'!M99 -> 0 | N99: =$J99*'Input Bank'!N99 -> 0 | O99: =$J99*'Input Bank'!O99 -> 0 | P99: =$J99*'Input Bank'!P99 -> 0 | Q99: =$J99*'Input Bank'!Q99 -> 0 | R99: =$J99*'Input Bank'!R99 -> 0 | ... BA99: =$J99*'Input Bank'!BA99 -> 0
A100: =Bobot!#REF! -> #REF! | F100: 087 | G100: 3.6 | H100: Non-tradable asset eligible for BI facilities | I100: =Bobot!O100 -> 0 | J100: =Bobot!O100 -> 0 | K100: =$J100*'Input Bank'!K100 -> 0 | L100: =$J100*'Input Bank'!L100 -> 0 | M100: =$J100*'Input Bank'!M100 -> 0 | N100: =$J100*'Input Bank'!N100 -> 0 | O100: =$J100*'Input Bank'!O100 -> 0 | P100: =$J100*'Input Bank'!P100 -> 0 | Q100: =$J100*'Input Bank'!Q100 -> 0 | R100: =$J100*'Input Bank'!R100 -> 0 | ... BA100: =$J100*'Input Bank'!BA100 -> 0
A101: =Bobot!#REF! -> #REF! | F101: 088 | G101: 3.7 | H101: Aset tradable lainnya | I101: =Bobot!O101 -> 0 | J101: =Bobot!O101 -> 0 | K101: =$J101*'Input Bank'!K101 -> 0 | L101: =$J101*'Input Bank'!L101 -> 0 | M101: =$J101*'Input Bank'!M101 -> 0 | N101: =$J101*'Input Bank'!N101 -> 0 | O101: =$J101*'Input Bank'!O101 -> 0 | P101: =$J101*'Input Bank'!P101 -> 0 | Q101: =$J101*'Input Bank'!Q101 -> 0 | R101: =$J101*'Input Bank'!R101 -> 0 | ... BA101: =$J101*'Input Bank'!BA101 -> 0
A102: =Bobot!#REF! -> #REF! | F102: 089 | G102: 3.8 | H102: Komitmen fasilitas yang diterima namun belum ditarik | K102: =SUM(K103:K104) -> 0 | L102: =SUM(L103:L104) -> 0 | M102: =SUM(M103:M104) -> 0 | N102: =SUM(N103:N104) -> 0 | O102: =SUM(O103:O104) -> 0 | P102: =SUM(P103:P104) -> 0 | Q102: =SUM(Q103:Q104) -> 0 | R102: =SUM(R103:R104) -> 0 | ... BA102: =SUM(BA103:BA104) -> 0
A103: =Bobot!#REF! -> #REF! | F103: 090 | G103: 3.8.1 | H103: Dari PSP, PSPT, dan Perusahaan Anak | I103: =Bobot!O103 -> 0 | J103: =Bobot!O103 -> 0 | K103: =$J103*'Input Bank'!K103 -> 0 | L103: =$J103*'Input Bank'!L103 -> 0 | M103: =$J103*'Input Bank'!M103 -> 0 | N103: =$J103*'Input Bank'!N103 -> 0 | O103: =$J103*'Input Bank'!O103 -> 0 | P103: =$J103*'Input Bank'!P103 -> 0 | Q103: =$J103*'Input Bank'!Q103 -> 0 | R103: =$J103*'Input Bank'!R103 -> 0 | ... BA103: =$J103*'Input Bank'!BA103 -> 0
A104: =Bobot!#REF! -> #REF! | F104: 091 | G104: 3.8.2 | H104: Dari entitas lainnya | I104: =Bobot!O104 -> 0 | J104: =Bobot!O104 -> 0 | K104: =$J104*'Input Bank'!K104 -> 0 | L104: =$J104*'Input Bank'!L104 -> 0 | M104: =$J104*'Input Bank'!M104 -> 0 | N104: =$J104*'Input Bank'!N104 -> 0 | O104: =$J104*'Input Bank'!O104 -> 0 | P104: =$J104*'Input Bank'!P104 -> 0 | Q104: =$J104*'Input Bank'!Q104 -> 0 | R104: =$J104*'Input Bank'!R104 -> 0 | ... BA104: =$J104*'Input Bank'!BA104 -> 0
F105: 092 | G105: 3.9 | H105: Perubahan netto Counterbalancing Capacity | L105: =L86+L87+L88+L92+L95+L100+L101+L102 -> 0 | M105: =M86+M87+M88+M92+M95+M100+M101+M102 -> 0 | N105: =N86+N87+N88+N92+N95+N100+N101+N102 -> 0 | O105: =O86+O87+O88+O92+O95+O100+O101+O102 -> 0 | P105: =P86+P87+P88+P92+P95+P100+P101+P102 -> 0 | Q105: =Q86+Q87+Q88+Q92+Q95+Q100+Q101+Q102 -> 0 | R105: =R86+R87+R88+R92+R95+R100+R101+R102 -> 0 | S105: =S86+S87+S88+S92+S95+S100+S101+S102 -> 0 | ... BA105: =BA86+BA87+BA88+BA92+BA95+BA100+BA101+BA102 -> 0
A106: =Bobot!#REF! -> #REF! | F106: 093 | G106: 3.10 | H106: Kumulatif Counterbalancing Capacity | K106: =SUM(K86:K87)+K88+K92+K95+K100+K101+K102 -> 0 | L106: =K106+L105 -> 0 | M106: =L106+M105 -> 0 | N106: =M106+N105 -> 0 | O106: =N106+O105 -> 0 | P106: =O106+P105 -> 0 | Q106: =P106+Q105 -> 0 | R106: =Q106+R105 -> 0 | S106: =R106+S105 -> 0 | ... BA106: =AZ106+BA105 -> 0
A107: =Bobot!#REF! -> #REF! | F107: 094 | G107: 4 | H107: KONTINGENSI | I107: Weight - open | J107: Weight - term | K107: Stok awal | L107: Tanpa Maturitas (Open) | M107: O/N (selain Open) | N107: Hari-2 | O107: Hari-3 | P107: Hari-4 | Q107: Hari-5 | R107: Hari-6 | S107: Hari-7 | T107: Hari-8 | U107: Hari-9 | V107: Hari-10 | W107: Hari-11 | X107: Hari-12 | Y107: Hari-13 | Z107: Hari-14 | AA107: Hari-15 | AB107: Hari-16 | AC107: Hari-17 | AD107: Hari-18 | AE107: Hari-19 | AF107: Hari-20 | AG107: Hari-21 | AH107: Hari-22 | AI107: Hari-23 | AJ107: Hari-24 | AK107: Hari-25 | AL107: Hari-26 | AM107: Hari-27 | AN107: Hari-28 | AO107: Hari-29 | AP107: Hari-30 | AQ107: > mg 4 s.d. mg 5 | AR107: > mg 5 s.d. 2 bln | AS107: > 2 bln s.d 3 bln | AT107: > 3 bln s.d 4 bln | AU107: > 4 bln s.d 5 bln | AV107: > 5 bln s.d 6 bln | AW107: > 6 bln s.d. 9 bln | AX107: > 9 bln s.d. 12 bln | AY107: > 12 bln s.d. 2 thn | AZ107: > 2 thn s.d. 5 thn | BA107: > 5 thn
A108: =Bobot!#REF! -> #REF! | F108: 095 | G108: 4.1 | H108: Arus kas keluar terkait peningkatan kebutuhan likuiditas | L108: =SUM(L109:L114) -> 0 | M108: =SUM(M109:M114) -> 0 | N108: =SUM(N109:N114) -> 0 | O108: =SUM(O109:O114) -> 0 | P108: =SUM(P109:P114) -> 0 | Q108: =SUM(Q109:Q114) -> 0 | R108: =SUM(R109:R114) -> 0 | S108: =SUM(S109:S114) -> 0 | ... BA108: =SUM(BA109:BA114) -> 0
F109: 096 | G109: 4.1.1 | H109: Terkait dengan penurunan peringkat (rating) Bank dalam transaksi Pendanaan, derivatif, dan perjanjian lainnya | I109: =Bobot!O109 -> 1 | J109: =Bobot!O109 -> 1 | L109: =IF(Bobot!$P109=0,1,0)*('Input Bank'!L109+'Input Bank'!K109)*I109 -> 0 | M109: =Bobot!$P109*($I109*('Input Bank'!$K109+'Input Bank'!$L109)/30)+($J109*'Input Bank'!M109) -> 0 | N109: =Bobot!$P109*($I109*('Input Bank'!$K109+'Input Bank'!$L109)/30)+($J109*'Input Bank'!N109) -> 0 | O109: =Bobot!$P109*($I109*('Input Bank'!$K109+'Input Bank'!$L109)/30)+($J109*'Input Bank'!O109) -> 0 | P109: =Bobot!$P109*($I109*('Input Bank'!$K109+'Input Bank'!$L109)/30)+($J109*'Input Bank'!P109) -> 0 | Q109: =Bobot!$P109*($I109*('Input Bank'!$K109+'Input Bank'!$L109)/30)+($J109*'Input Bank'!Q109) -> 0 | R109: =Bobot!$P109*($I109*('Input Bank'!$K109+'Input Bank'!$L109)/30)+($J109*'Input Bank'!R109) -> 0 | S109: =Bobot!$P109*($I109*('Input Bank'!$K109+'Input Bank'!$L109)/30)+($J109*'Input Bank'!S109) -> 0 | T109: =Bobot!$P109*($I109*('Input Bank'!$K109+'Input Bank'!$L109)/30)+($J109*'Input Bank'!T109) -> 0 | ... BA109: =Bobot!$P109*($I109*('Input Bank'!$K109+'Input Bank'!$L109)/30)+($J109*'Input Bank'!BA109) -> 0
...

Sheet SPM Skenario Bank
N4: Skenario Bank 1
N5: Skenario Bank 2
K6: SKENARIO | N6: Skenario Bank 3
K7: Skenario Bank 1
K11: =TEXT(K12,"ddd") -> MM/DD/YYYY
K12: ='Header & Notes'!J10 -> MM/DD/YYYY | AQ12: =#REF!+7 -> #REF! | AR12: =AQ12+ROUNDDOWN(21/2,0) -> #REF! | AS12: =AR12+30/2 -> #REF! | AT12: =AS12+30/2 -> #REF! | AU12: =AT12+30/2 -> #REF! | AV12: =AU12+30/2 -> #REF! | AW12: =AV12+92/2 -> #REF! | AX12: =AW12+92/2 -> #REF! | AY12: =AX12+ROUNDDOWN(365/2,0) -> #REF! | AZ12: =AY12+ROUNDDOWN(3*365/2,) -> #REF! | BA12: =AZ12+3650/2 -> #REF!
F13: Kode | G13: Baris | H13: Item | I13: Weight - open | J13: Weight - term | K13: Stok awal | L13: Tanpa Maturitas (Open) | M13: O/N (selain Open) | N13: Hari-2 | O13: Hari-3 | P13: Hari-4 | Q13: Hari-5 | R13: Hari-6 | S13: Hari-7 | T13: Hari-8 | U13: Hari-9 | V13: Hari-10 | W13: Hari-11 | X13: Hari-12 | Y13: Hari-13 | Z13: Hari-14 | AA13: Hari-15 | AB13: Hari-16 | AC13: Hari-17 | AD13: Hari-18 | AE13: Hari-19 | AF13: Hari-20 | AG13: Hari-21 | AH13: Hari-22 | AI13: Hari-23 | AJ13: Hari-24 | AK13: Hari-25 | AL13: Hari-26 | AM13: Hari-27 | AN13: Hari-28 | AO13: Hari-29 | AP13: Hari-30 | AQ13: > mg 4 s.d. mg 5 | AR13: > mg 5 s.d. 2 bln | AS13: > 2 bln s.d 3 bln | AT13: > 3 bln s.d 4 bln | AU13: > 4 bln s.d 5 bln | AV13: > 5 bln s.d 6 bln | AW13: > 6 bln s.d. 9 bln | AX13: > 9 bln s.d. 12 bln | AY13: > 12 bln s.d. 2 thn | AZ13: > 2 thn s.d. 5 thn | BA13: > 5 thn
F14: 001 | G14: 1 | H14: ARUS KAS KELUAR
A15: =Bobot!#REF! -> #REF! | F15: 002 | G15: 1.1 | H15: Kewajiban yang berasal dari simpanan yang diterima | L15: =SUM(L16:L30) -> 0 | M15: =SUM(M16:M30) -> 0 | N15: =SUM(N16:N30) -> 0 | O15: =SUM(O16:O30) -> 0 | P15: =SUM(P16:P30) -> 0 | Q15: =SUM(Q16:Q30) -> 0 | R15: =SUM(R16:R30) -> 0 | S15: =SUM(S16:S30) -> 0 | ... BA15: =SUM(BA16:BA30) -> 0
A16: =Bobot!#REF! -> #REF! | F16: 003 | G16: 1.1.1 | H16: Simpanan stabil dari Nasabah Perorangan | I16: =IF($K$7="Skenario Bank 1",VLOOKUP($F16,Bobot!$F$16:$AA$180,15,0),IF($K$7="Skenario Bank 2",VLOOKUP(F16,Bobot!$F$16:$AA$180,18,0),IF($K$7="Skenario Bank 3",VLOOKUP($F16,Bobot!$F$16:$AA$180,21,0),0))) -> 0 | J16: =IF($K$7="Skenario Bank 1",VLOOKUP($F16,Bobot!$F$16:$AA$180,16,0),IF($K$7="Skenario Bank 2",VLOOKUP($F16,Bobot!$F$16:$AA$180,19,0),IF($K$7="Skenario Bank 3",VLOOKUP($F16,Bobot!$F$16:$AA$180,22,0),0))) -> 0 | L16: =IF(Bobot!$P16=0,1,0)*('Input Bank'!L16+'Input Bank'!K16)*I16 -> 0 | M16: =Bobot!$P16*($I16*('Input Bank'!$K16+'Input Bank'!$L16)/30)+($J16*'Input Bank'!M16) -> 0 | N16: =Bobot!$P16*($I16*('Input Bank'!$K16+'Input Bank'!$L16)/30)+($J16*'Input Bank'!N16) -> 0 | O16: =Bobot!$P16*($I16*('Input Bank'!$K16+'Input Bank'!$L16)/30)+($J16*'Input Bank'!O16) -> 0 | P16: =Bobot!$P16*($I16*('Input Bank'!$K16+'Input Bank'!$L16)/30)+($J16*'Input Bank'!P16) -> 0 | Q16: =Bobot!$P16*($I16*('Input Bank'!$K16+'Input Bank'!$L16)/30)+($J16*'Input Bank'!Q16) -> 0 | R16: =Bobot!$P16*($I16*('Input Bank'!$K16+'Input Bank'!$L16)/30)+($J16*'Input Bank'!R16) -> 0 | S16: =Bobot!$P16*($I16*('Input Bank'!$K16+'Input Bank'!$L16)/30)+($J16*'Input Bank'!S16) -> 0 | T16: =Bobot!$P16*($I16*('Input Bank'!$K16+'Input Bank'!$L16)/30)+($J16*'Input Bank'!T16) -> 0 | ... AP16: =Bobot!$P16*($I16*('Input Bank'!$K16+'Input Bank'!$L16)/30)+($J16*'Input Bank'!AP16) -> 0 | AQ16: =$J16*'Input Bank'!AQ16 -> 0 | AR16: =$J16*'Input Bank'!AR16 -> 0 | AS16: =$J16*'Input Bank'!AS16 -> 0 | AT16: =$J16*'Input Bank'!AT16 -> 0 | AU16: =$J16*'Input Bank'!AU16 -> 0 | AV16: =$J16*'Input Bank'!AV16 -> 0 | AW16: =$J16*'Input Bank'!AW16 -> 0 | AX16: =$J16*'Input Bank'!AX16 -> 0 | ... BA16: =$J16*'Input Bank'!BA16 -> 0
A17: =Bobot!#REF! -> #REF! | F17: 004 | G17: 1.1.2 | H17: Simpanan kurang stabil dari Nasabah Perorangan yang dijamin LPS | I17: =IF($K$7="Skenario Bank 1",VLOOKUP($F17,Bobot!$F$16:$AA$180,15,0),IF($K$7="Skenario Bank 2",VLOOKUP(F17,Bobot!$F$16:$AA$180,18,0),IF($K$7="Skenario Bank 3",VLOOKUP($F17,Bobot!$F$16:$AA$180,21,0),0))) -> 0 | J17: =IF($K$7="Skenario Bank 1",VLOOKUP($F17,Bobot!$F$16:$AA$180,16,0),IF($K$7="Skenario Bank 2",VLOOKUP($F17,Bobot!$F$16:$AA$180,19,0),IF($K$7="Skenario Bank 3",VLOOKUP($F17,Bobot!$F$16:$AA$180,22,0),0))) -> 0 | L17: =IF(Bobot!$P17=0,1,0)*('Input Bank'!L17+'Input Bank'!K17)*I17 -> 0 | M17: =Bobot!$P17*($I17*('Input Bank'!$K17+'Input Bank'!$L17)/30)+($J17*'Input Bank'!M17) -> 0 | N17: =Bobot!$P17*($I17*('Input Bank'!$K17+'Input Bank'!$L17)/30)+($J17*'Input Bank'!N17) -> 0 | O17: =Bobot!$P17*($I17*('Input Bank'!$K17+'Input Bank'!$L17)/30)+($J17*'Input Bank'!O17) -> 0 | P17: =Bobot!$P17*($I17*('Input Bank'!$K17+'Input Bank'!$L17)/30)+($J17*'Input Bank'!P17) -> 0 | Q17: =Bobot!$P17*($I17*('Input Bank'!$K17+'Input Bank'!$L17)/30)+($J17*'Input Bank'!Q17) -> 0 | R17: =Bobot!$P17*($I17*('Input Bank'!$K17+'Input Bank'!$L17)/30)+($J17*'Input Bank'!R17) -> 0 | S17: =Bobot!$P17*($I17*('Input Bank'!$K17+'Input Bank'!$L17)/30)+($J17*'Input Bank'!S17) -> 0 | T17: =Bobot!$P17*($I17*('Input Bank'!$K17+'Input Bank'!$L17)/30)+($J17*'Input Bank'!T17) -> 0 | ... AP17: =Bobot!$P17*($I17*('Input Bank'!$K17+'Input Bank'!$L17)/30)+($J17*'Input Bank'!AP17) -> 0 | AQ17: =$J17*'Input Bank'!AQ17 -> 0 | AR17: =$J17*'Input Bank'!AR17 -> 0 | AS17: =$J17*'Input Bank'!AS17 -> 0 | AT17: =$J17*'Input Bank'!AT17 -> 0 | AU17: =$J17*'Input Bank'!AU17 -> 0 | AV17: =$J17*'Input Bank'!AV17 -> 0 | AW17: =$J17*'Input Bank'!AW17 -> 0 | AX17: =$J17*'Input Bank'!AX17 -> 0 | ... BA17: =$J17*'Input Bank'!BA17 -> 0
A18: =Bobot!#REF! -> #REF! | F18: 005 | G18: 1.1.3 | H18: Simpanan kurang stabil Nasabah Perorangan yang tidak dijamin LPS | I18: =IF($K$7="Skenario Bank 1",VLOOKUP($F18,Bobot!$F$16:$AA$180,15,0),IF($K$7="Skenario Bank 2",VLOOKUP(F18,Bobot!$F$16:$AA$180,18,0),IF($K$7="Skenario Bank 3",VLOOKUP($F18,Bobot!$F$16:$AA$180,21,0),0))) -> 0 | J18: =IF($K$7="Skenario Bank 1",VLOOKUP($F18,Bobot!$F$16:$AA$180,16,0),IF($K$7="Skenario Bank 2",VLOOKUP($F18,Bobot!$F$16:$AA$180,19,0),IF($K$7="Skenario Bank 3",VLOOKUP($F18,Bobot!$F$16:$AA$180,22,0),0))) -> 0 | L18: =IF(Bobot!$P18=0,1,0)*('Input Bank'!L18+'Input Bank'!K18)*I18 -> 0 | M18: =Bobot!$P18*($I18*('Input Bank'!$K18+'Input Bank'!$L18)/30)+($J18*'Input Bank'!M18) -> 0 | N18: =Bobot!$P18*($I18*('Input Bank'!$K18+'Input Bank'!$L18)/30)+($J18*'Input Bank'!N18) -> 0 | O18: =Bobot!$P18*($I18*('Input Bank'!$K18+'Input Bank'!$L18)/30)+($J18*'Input Bank'!O18) -> 0 | P18: =Bobot!$P18*($I18*('Input Bank'!$K18+'Input Bank'!$L18)/30)+($J18*'Input Bank'!P18) -> 0 | Q18: =Bobot!$P18*($I18*('Input Bank'!$K18+'Input Bank'!$L18)/30)+($J18*'Input Bank'!Q18) -> 0 | R18: =Bobot!$P18*($I18*('Input Bank'!$K18+'Input Bank'!$L18)/30)+($J18*'Input Bank'!R18) -> 0 | S18: =Bobot!$P18*($I18*('Input Bank'!$K18+'Input Bank'!$L18)/30)+($J18*'Input Bank'!S18) -> 0 | T18: =Bobot!$P18*($I18*('Input Bank'!$K18+'Input Bank'!$L18)/30)+($J18*'Input Bank'!T18) -> 0 | ... AP18: =Bobot!$P18*($I18*('Input Bank'!$K18+'Input Bank'!$L18)/30)+($J18*'Input Bank'!AP18) -> 0 | AQ18: =$J18*'Input Bank'!AQ18 -> 0 | AR18: =$J18*'Input Bank'!AR18 -> 0 | AS18: =$J18*'Input Bank'!AS18 -> 0 | AT18: =$J18*'Input Bank'!AT18 -> 0 | AU18: =$J18*'Input Bank'!AU18 -> 0 | AV18: =$J18*'Input Bank'!AV18 -> 0 | AW18: =$J18*'Input Bank'!AW18 -> 0 | AX18: =$J18*'Input Bank'!AX18 -> 0 | ... BA18: =$J18*'Input Bank'!BA18 -> 0
F19: 006 | G19: 1.1.4 | H19: Pendanaan Stabil dari Nasabah Usaha Mikro dan Usaha Kecil | I19: =IF($K$7="Skenario Bank 1",VLOOKUP($F19,Bobot!$F$16:$AA$180,15,0),IF($K$7="Skenario Bank 2",VLOOKUP(F19,Bobot!$F$16:$AA$180,18,0),IF($K$7="Skenario Bank 3",VLOOKUP($F19,Bobot!$F$16:$AA$180,21,0),0))) -> 0 | J19: =IF($K$7="Skenario Bank 1",VLOOKUP($F19,Bobot!$F$16:$AA$180,16,0),IF($K$7="Skenario Bank 2",VLOOKUP($F19,Bobot!$F$16:$AA$180,19,0),IF($K$7="Skenario Bank 3",VLOOKUP($F19,Bobot!$F$16:$AA$180,22,0),0))) -> 0 | L19: =IF(Bobot!$P19=0,1,0)*('Input Bank'!L19+'Input Bank'!K19)*I19 -> 0 | M19: =Bobot!$P19*($I19*('Input Bank'!$K19+'Input Bank'!$L19)/30)+($J19*'Input Bank'!M19) -> 0 | N19: =Bobot!$P19*($I19*('Input Bank'!$K19+'Input Bank'!$L19)/30)+($J19*'Input Bank'!N19) -> 0 | O19: =Bobot!$P19*($I19*('Input Bank'!$K19+'Input Bank'!$L19)/30)+($J19*'Input Bank'!O19) -> 0 | P19: =Bobot!$P19*($I19*('Input Bank'!$K19+'Input Bank'!$L19)/30)+($J19*'Input Bank'!P19) -> 0 | Q19: =Bobot!$P19*($I19*('Input Bank'!$K19+'Input Bank'!$L19)/30)+($J19*'Input Bank'!Q19) -> 0 | R19: =Bobot!$P19*($I19*('Input Bank'!$K19+'Input Bank'!$L19)/30)+($J19*'Input Bank'!R19) -> 0 | S19: =Bobot!$P19*($I19*('Input Bank'!$K19+'Input Bank'!$L19)/30)+($J19*'Input Bank'!S19) -> 0 | T19: =Bobot!$P19*($I19*('Input Bank'!$K19+'Input Bank'!$L19)/30)+($J19*'Input Bank'!T19) -> 0 | ... AP19: =Bobot!$P19*($I19*('Input Bank'!$K19+'Input Bank'!$L19)/30)+($J19*'Input Bank'!AP19) -> 0 | AQ19: =$J19*'Input Bank'!AQ19 -> 0 | AR19: =$J19*'Input Bank'!AR19 -> 0 | AS19: =$J19*'Input Bank'!AS19 -> 0 | AT19: =$J19*'Input Bank'!AT19 -> 0 | AU19: =$J19*'Input Bank'!AU19 -> 0 | AV19: =$J19*'Input Bank'!AV19 -> 0 | AW19: =$J19*'Input Bank'!AW19 -> 0 | AX19: =$J19*'Input Bank'!AX19 -> 0 | ... BA19: =$J19*'Input Bank'!BA19 -> 0
A20: =Bobot!P37 -> 0 | F20: 007 | G20: 1.1.5 | H20: Pendanaan kurang Stabil dari Nasabah Usaha Mikro dan Usaha Kecil yang dijamin LPS | I20: =IF($K$7="Skenario Bank 1",VLOOKUP($F20,Bobot!$F$16:$AA$180,15,0),IF($K$7="Skenario Bank 2",VLOOKUP(F20,Bobot!$F$16:$AA$180,18,0),IF($K$7="Skenario Bank 3",VLOOKUP($F20,Bobot!$F$16:$AA$180,21,0),0))) -> 0 | J20: =IF($K$7="Skenario Bank 1",VLOOKUP($F20,Bobot!$F$16:$AA$180,16,0),IF($K$7="Skenario Bank 2",VLOOKUP($F20,Bobot!$F$16:$AA$180,19,0),IF($K$7="Skenario Bank 3",VLOOKUP($F20,Bobot!$F$16:$AA$180,22,0),0))) -> 0 | L20: =IF(Bobot!$P20=0,1,0)*('Input Bank'!L20+'Input Bank'!K20)*I20 -> 0 | M20: =Bobot!$P20*($I20*('Input Bank'!$K20+'Input Bank'!$L20)/30)+($J20*'Input Bank'!M20) -> 0 | N20: =Bobot!$P20*($I20*('Input Bank'!$K20+'Input Bank'!$L20)/30)+($J20*'Input Bank'!N20) -> 0 | O20: =Bobot!$P20*($I20*('Input Bank'!$K20+'Input Bank'!$L20)/30)+($J20*'Input Bank'!O20) -> 0 | P20: =Bobot!$P20*($I20*('Input Bank'!$K20+'Input Bank'!$L20)/30)+($J20*'Input Bank'!P20) -> 0 | Q20: =Bobot!$P20*($I20*('Input Bank'!$K20+'Input Bank'!$L20)/30)+($J20*'Input Bank'!Q20) -> 0 | R20: =Bobot!$P20*($I20*('Input Bank'!$K20+'Input Bank'!$L20)/30)+($J20*'Input Bank'!R20) -> 0 | S20: =Bobot!$P20*($I20*('Input Bank'!$K20+'Input Bank'!$L20)/30)+($J20*'Input Bank'!S20) -> 0 | T20: =Bobot!$P20*($I20*('Input Bank'!$K20+'Input Bank'!$L20)/30)+($J20*'Input Bank'!T20) -> 0 | ... AP20: =Bobot!$P20*($I20*('Input Bank'!$K20+'Input Bank'!$L20)/30)+($J20*'Input Bank'!AP20) -> 0 | AQ20: =$J20*'Input Bank'!AQ20 -> 0 | AR20: =$J20*'Input Bank'!AR20 -> 0 | AS20: =$J20*'Input Bank'!AS20 -> 0 | AT20: =$J20*'Input Bank'!AT20 -> 0 | AU20: =$J20*'Input Bank'!AU20 -> 0 | AV20: =$J20*'Input Bank'!AV20 -> 0 | AW20: =$J20*'Input Bank'!AW20 -> 0 | AX20: =$J20*'Input Bank'!AX20 -> 0 | ... BA20: =$J20*'Input Bank'!BA20 -> 0
A21: =Bobot!#REF! -> #REF! | F21: 008 | G21: 1.1.6 | H21: Pendanaan kurang Stabil dari Nasabah Usaha Mikro dan Usaha Kecil yang tidak dijamin LPS | I21: =IF($K$7="Skenario Bank 1",VLOOKUP($F21,Bobot!$F$16:$AA$180,15,0),IF($K$7="Skenario Bank 2",VLOOKUP(F21,Bobot!$F$16:$AA$180,18,0),IF($K$7="Skenario Bank 3",VLOOKUP($F21,Bobot!$F$16:$AA$180,21,0),0))) -> 0 | J21: =IF($K$7="Skenario Bank 1",VLOOKUP($F21,Bobot!$F$16:$AA$180,16,0),IF($K$7="Skenario Bank 2",VLOOKUP($F21,Bobot!$F$16:$AA$180,19,0),IF($K$7="Skenario Bank 3",VLOOKUP($F21,Bobot!$F$16:$AA$180,22,0),0))) -> 0 | L21: =IF(Bobot!$P21=0,1,0)*('Input Bank'!L21+'Input Bank'!K21)*I21 -> 0 | M21: =Bobot!$P21*($I21*('Input Bank'!$K21+'Input Bank'!$L21)/30)+($J21*'Input Bank'!M21) -> 0 | N21: =Bobot!$P21*($I21*('Input Bank'!$K21+'Input Bank'!$L21)/30)+($J21*'Input Bank'!N21) -> 0 | O21: =Bobot!$P21*($I21*('Input Bank'!$K21+'Input Bank'!$L21)/30)+($J21*'Input Bank'!O21) -> 0 | P21: =Bobot!$P21*($I21*('Input Bank'!$K21+'Input Bank'!$L21)/30)+($J21*'Input Bank'!P21) -> 0 | Q21: =Bobot!$P21*($I21*('Input Bank'!$K21+'Input Bank'!$L21)/30)+($J21*'Input Bank'!Q21) -> 0 | R21: =Bobot!$P21*($I21*('Input Bank'!$K21+'Input Bank'!$L21)/30)+($J21*'Input Bank'!R21) -> 0 | S21: =Bobot!$P21*($I21*('Input Bank'!$K21+'Input Bank'!$L21)/30)+($J21*'Input Bank'!S21) -> 0 | T21: =Bobot!$P21*($I21*('Input Bank'!$K21+'Input Bank'!$L21)/30)+($J21*'Input Bank'!T21) -> 0 | ... AP21: =Bobot!$P21*($I21*('Input Bank'!$K21+'Input Bank'!$L21)/30)+($J21*'Input Bank'!AP21) -> 0 | AQ21: =$J21*'Input Bank'!AQ21 -> 0 | AR21: =$J21*'Input Bank'!AR21 -> 0 | AS21: =$J21*'Input Bank'!AS21 -> 0 | AT21: =$J21*'Input Bank'!AT21 -> 0 | AU21: =$J21*'Input Bank'!AU21 -> 0 | AV21: =$J21*'Input Bank'!AV21 -> 0 | AW21: =$J21*'Input Bank'!AW21 -> 0 | AX21: =$J21*'Input Bank'!AX21 -> 0 | ... BA21: =$J21*'Input Bank'!BA21 -> 0
A22: =Bobot!#REF! -> #REF! | F22: 009 | G22: 1.1.7 | H22: Simpanan operasional nasabah korporasi yang dijamin LPS | I22: =IF($K$7="Skenario Bank 1",VLOOKUP($F22,Bobot!$F$16:$AA$180,15,0),IF($K$7="Skenario Bank 2",VLOOKUP(F22,Bobot!$F$16:$AA$180,18,0),IF($K$7="Skenario Bank 3",VLOOKUP($F22,Bobot!$F$16:$AA$180,21,0),0))) -> 0 | J22: =IF($K$7="Skenario Bank 1",VLOOKUP($F22,Bobot!$F$16:$AA$180,16,0),IF($K$7="Skenario Bank 2",VLOOKUP($F22,Bobot!$F$16:$AA$180,19,0),IF($K$7="Skenario Bank 3",VLOOKUP($F22,Bobot!$F$16:$AA$180,22,0),0))) -> 0 | L22: =IF(Bobot!$P22=0,1,0)*('Input Bank'!L22+'Input Bank'!K22)*I22 -> 0 | M22: =Bobot!$P22*($I22*('Input Bank'!$K22+'Input Bank'!$L22)/30)+($J22*'Input Bank'!M22) -> 0 | N22: =Bobot!$P22*($I22*('Input Bank'!$K22+'Input Bank'!$L22)/30)+($J22*'Input Bank'!N22) -> 0 | O22: =Bobot!$P22*($I22*('Input Bank'!$K22+'Input Bank'!$L22)/30)+($J22*'Input Bank'!O22) -> 0 | P22: =Bobot!$P22*($I22*('Input Bank'!$K22+'Input Bank'!$L22)/30)+($J22*'Input Bank'!P22) -> 0 | Q22: =Bobot!$P22*($I22*('Input Bank'!$K22+'Input Bank'!$L22)/30)+($J22*'Input Bank'!Q22) -> 0 | R22: =Bobot!$P22*($I22*('Input Bank'!$K22+'Input Bank'!$L22)/30)+($J22*'Input Bank'!R22) -> 0 | S22: =Bobot!$P22*($I22*('Input Bank'!$K22+'Input Bank'!$L22)/30)+($J22*'Input Bank'!S22) -> 0 | T22: =Bobot!$P22*($I22*('Input Bank'!$K22+'Input Bank'!$L22)/30)+($J22*'Input Bank'!T22) -> 0 | ... AP22: =Bobot!$P22*($I22*('Input Bank'!$K22+'Input Bank'!$L22)/30)+($J22*'Input Bank'!AP22) -> 0 | AQ22: =$J22*'Input Bank'!AQ22 -> 0 | AR22: =$J22*'Input Bank'!AR22 -> 0 | AS22: =$J22*'Input Bank'!AS22 -> 0 | AT22: =$J22*'Input Bank'!AT22 -> 0 | AU22: =$J22*'Input Bank'!AU22 -> 0 | AV22: =$J22*'Input Bank'!AV22 -> 0 | AW22: =$J22*'Input Bank'!AW22 -> 0 | AX22: =$J22*'Input Bank'!AX22 -> 0 | ... BA22: =$J22*'Input Bank'!BA22 -> 0
A23: =Bobot!P39 -> 0 | F23: 010 | G23: 1.1.8 | H23: Simpanan operasional nasabah korporasi yang tidak dijamin LPS | I23: =IF($K$7="Skenario Bank 1",VLOOKUP($F23,Bobot!$F$16:$AA$180,15,0),IF($K$7="Skenario Bank 2",VLOOKUP(F23,Bobot!$F$16:$AA$180,18,0),IF($K$7="Skenario Bank 3",VLOOKUP($F23,Bobot!$F$16:$AA$180,21,0),0))) -> 0 | J23: =IF($K$7="Skenario Bank 1",VLOOKUP($F23,Bobot!$F$16:$AA$180,16,0),IF($K$7="Skenario Bank 2",VLOOKUP($F23,Bobot!$F$16:$AA$180,19,0),IF($K$7="Skenario Bank 3",VLOOKUP($F23,Bobot!$F$16:$AA$180,22,0),0))) -> 0 | L23: =IF(Bobot!$P23=0,1,0)*('Input Bank'!L23+'Input Bank'!K23)*I23 -> 0 | M23: =Bobot!$P23*($I23*('Input Bank'!$K23+'Input Bank'!$L23)/30)+($J23*'Input Bank'!M23) -> 0 | N23: =Bobot!$P23*($I23*('Input Bank'!$K23+'Input Bank'!$L23)/30)+($J23*'Input Bank'!N23) -> 0 | O23: =Bobot!$P23*($I23*('Input Bank'!$K23+'Input Bank'!$L23)/30)+($J23*'Input Bank'!O23) -> 0 | P23: =Bobot!$P23*($I23*('Input Bank'!$K23+'Input Bank'!$L23)/30)+($J23*'Input Bank'!P23) -> 0 | Q23: =Bobot!$P23*($I23*('Input Bank'!$K23+'Input Bank'!$L23)/30)+($J23*'Input Bank'!Q23) -> 0 | R23: =Bobot!$P23*($I23*('Input Bank'!$K23+'Input Bank'!$L23)/30)+($J23*'Input Bank'!R23) -> 0 | S23: =Bobot!$P23*($I23*('Input Bank'!$K23+'Input Bank'!$L23)/30)+($J23*'Input Bank'!S23) -> 0 | T23: =Bobot!$P23*($I23*('Input Bank'!$K23+'Input Bank'!$L23)/30)+($J23*'Input Bank'!T23) -> 0 | ... AP23: =Bobot!$P23*($I23*('Input Bank'!$K23+'Input Bank'!$L23)/30)+($J23*'Input Bank'!AP23) -> 0 | AQ23: =$J23*'Input Bank'!AQ23 -> 0 | AR23: =$J23*'Input Bank'!AR23 -> 0 | AS23: =$J23*'Input Bank'!AS23 -> 0 | AT23: =$J23*'Input Bank'!AT23 -> 0 | AU23: =$J23*'Input Bank'!AU23 -> 0 | AV23: =$J23*'Input Bank'!AV23 -> 0 | AW23: =$J23*'Input Bank'!AW23 -> 0 | AX23: =$J23*'Input Bank'!AX23 -> 0 | ... BA23: =$J23*'Input Bank'!BA23 -> 0
A24: =Bobot!#REF! -> #REF! | F24: 011 | G24: 1.1.9 | H24: Penarikan Simpanan Non-Operasional dan/atau kewajiban lainnya yang bersifat non-operasional dari: | I24: =IF($K$7="Skenario Bank 1",VLOOKUP($F24,Bobot!$F$16:$AA$180,15,0),IF($K$7="Skenario Bank 2",VLOOKUP(F24,Bobot!$F$16:$AA$180,18,0),IF($K$7="Skenario Bank 3",VLOOKUP($F24,Bobot!$F$16:$AA$180,21,0),0))) -> 0 | J24: =IF($K$7="Skenario Bank 1",VLOOKUP($F24,Bobot!$F$16:$AA$180,16,0),IF($K$7="Skenario Bank 2",VLOOKUP($F24,Bobot!$F$16:$AA$180,19,0),IF($K$7="Skenario Bank 3",VLOOKUP($F24,Bobot!$F$16:$AA$180,22,0),0))) -> 0
A25: =Bobot!#REF! -> #REF! | F25: 012 | G25: 1.1.10 | H25: Bank | I25: =IF($K$7="Skenario Bank 1",VLOOKUP($F25,Bobot!$F$16:$AA$180,15,0),IF($K$7="Skenario Bank 2",VLOOKUP(F25,Bobot!$F$16:$AA$180,18,0),IF($K$7="Skenario Bank 3",VLOOKUP($F25,Bobot!$F$16:$AA$180,21,0),0))) -> 0 | J25: =IF($K$7="Skenario Bank 1",VLOOKUP($F25,Bobot!$F$16:$AA$180,16,0),IF($K$7="Skenario Bank 2",VLOOKUP($F25,Bobot!$F$16:$AA$180,19,0),IF($K$7="Skenario Bank 3",VLOOKUP($F25,Bobot!$F$16:$AA$180,22,0),0))) -> 0 | L25: =IF(Bobot!$P25=0,1,0)*('Input Bank'!L26+'Input Bank'!K25)*I25 -> 0 | M25: =Bobot!$P25*($I25*('Input Bank'!$K25+'Input Bank'!$L25)/30)+($J25*'Input Bank'!M25) -> 0 | N25: =Bobot!$P25*($I25*('Input Bank'!$K25+'Input Bank'!$L25)/30)+($J25*'Input Bank'!N25) -> 0 | O25: =Bobot!$P25*($I25*('Input Bank'!$K25+'Input Bank'!$L25)/30)+($J25*'Input Bank'!O25) -> 0 | P25: =Bobot!$P25*($I25*('Input Bank'!$K25+'Input Bank'!$L25)/30)+($J25*'Input Bank'!P25) -> 0 | Q25: =Bobot!$P25*($I25*('Input Bank'!$K25+'Input Bank'!$L25)/30)+($J25*'Input Bank'!Q25) -> 0 | R25: =Bobot!$P25*($I25*('Input Bank'!$K25+'Input Bank'!$L25)/30)+($J25*'Input Bank'!R25) -> 0 | S25: =Bobot!$P25*($I25*('Input Bank'!$K25+'Input Bank'!$L25)/30)+($J25*'Input Bank'!S25) -> 0 | T25: =Bobot!$P25*($I25*('Input Bank'!$K25+'Input Bank'!$L25)/30)+($J25*'Input Bank'!T25) -> 0 | ... AP25: =Bobot!$P25*($I25*('Input Bank'!$K25+'Input Bank'!$L25)/30)+($J25*'Input Bank'!AP25) -> 0 | AQ25: =$J25*'Input Bank'!AQ25 -> 0 | AR25: =$J25*'Input Bank'!AR25 -> 0 | AS25: =$J25*'Input Bank'!AS25 -> 0 | AT25: =$J25*'Input Bank'!AT25 -> 0 | AU25: =$J25*'Input Bank'!AU25 -> 0 | AV25: =$J25*'Input Bank'!AV25 -> 0 | AW25: =$J25*'Input Bank'!AW25 -> 0 | AX25: =$J25*'Input Bank'!AX25 -> 0 | ... BA25: =$J25*'Input Bank'!BA25 -> 0
A26: =Bobot!#REF! -> #REF! | F26: 013 | G26: 1.1.11 | H26: LJK lainnya | I26: =IF($K$7="Skenario Bank 1",VLOOKUP($F26,Bobot!$F$16:$AA$180,15,0),IF($K$7="Skenario Bank 2",VLOOKUP(F26,Bobot!$F$16:$AA$180,18,0),IF($K$7="Skenario Bank 3",VLOOKUP($F26,Bobot!$F$16:$AA$180,21,0),0))) -> 0 | J26: =IF($K$7="Skenario Bank 1",VLOOKUP($F26,Bobot!$F$16:$AA$180,16,0),IF($K$7="Skenario Bank 2",VLOOKUP($F26,Bobot!$F$16:$AA$180,19,0),IF($K$7="Skenario Bank 3",VLOOKUP($F26,Bobot!$F$16:$AA$180,22,0),0))) -> 0 | L26: =IF(Bobot!$P26=0,1,0)*('Input Bank'!L26+'Input Bank'!K26)*I26 -> 0 | M26: =Bobot!$P26*($I26*('Input Bank'!$K26+'Input Bank'!$L26)/30)+($J26*'Input Bank'!M26) -> 0 | N26: =Bobot!$P26*($I26*('Input Bank'!$K26+'Input Bank'!$L26)/30)+($J26*'Input Bank'!N26) -> 0 | O26: =Bobot!$P26*($I26*('Input Bank'!$K26+'Input Bank'!$L26)/30)+($J26*'Input Bank'!O26) -> 0 | P26: =Bobot!$P26*($I26*('Input Bank'!$K26+'Input Bank'!$L26)/30)+($J26*'Input Bank'!P26) -> 0 | Q26: =Bobot!$P26*($I26*('Input Bank'!$K26+'Input Bank'!$L26)/30)+($J26*'Input Bank'!Q26) -> 0 | R26: =Bobot!$P26*($I26*('Input Bank'!$K26+'Input Bank'!$L26)/30)+($J26*'Input Bank'!R26) -> 0 | S26: =Bobot!$P26*($I26*('Input Bank'!$K26+'Input Bank'!$L26)/30)+($J26*'Input Bank'!S26) -> 0 | T26: =Bobot!$P26*($I26*('Input Bank'!$K26+'Input Bank'!$L26)/30)+($J26*'Input Bank'!T26) -> 0 | ... AP26: =Bobot!$P26*($I26*('Input Bank'!$K26+'Input Bank'!$L26)/30)+($J26*'Input Bank'!AP26) -> 0 | AQ26: =$J26*'Input Bank'!AQ26 -> 0 | AR26: =$J26*'Input Bank'!AR26 -> 0 | AS26: =$J26*'Input Bank'!AS26 -> 0 | AT26: =$J26*'Input Bank'!AT26 -> 0 | AU26: =$J26*'Input Bank'!AU26 -> 0 | AV26: =$J26*'Input Bank'!AV26 -> 0 | AW26: =$J26*'Input Bank'!AW26 -> 0 | AX26: =$J26*'Input Bank'!AX26 -> 0 | ... BA26: =$J26*'Input Bank'!BA26 -> 0
A27: =Bobot!#REF! -> #REF! | F27: 014 | G27: 1.1.12 | H27: Korporasi non-finansial yang dijamin LPS | I27: =IF($K$7="Skenario Bank 1",VLOOKUP($F27,Bobot!$F$16:$AA$180,15,0),IF($K$7="Skenario Bank 2",VLOOKUP(F27,Bobot!$F$16:$AA$180,18,0),IF($K$7="Skenario Bank 3",VLOOKUP($F27,Bobot!$F$16:$AA$180,21,0),0))) -> 0 | J27: =IF($K$7="Skenario Bank 1",VLOOKUP($F27,Bobot!$F$16:$AA$180,16,0),IF($K$7="Skenario Bank 2",VLOOKUP($F27,Bobot!$F$16:$AA$180,19,0),IF($K$7="Skenario Bank 3",VLOOKUP($F27,Bobot!$F$16:$AA$180,22,0),0))) -> 0 | L27: =IF(Bobot!$P27=0,1,0)*('Input Bank'!L27+'Input Bank'!K27)*I27 -> 0 | M27: =Bobot!$P27*($I27*('Input Bank'!$K27+'Input Bank'!$L27)/30)+($J27*'Input Bank'!M27) -> 0 | N27: =Bobot!$P27*($I27*('Input Bank'!$K27+'Input Bank'!$L27)/30)+($J27*'Input Bank'!N27) -> 0 | O27: =Bobot!$P27*($I27*('Input Bank'!$K27+'Input Bank'!$L27)/30)+($J27*'Input Bank'!O27) -> 0 | P27: =Bobot!$P27*($I27*('Input Bank'!$K27+'Input Bank'!$L27)/30)+($J27*'Input Bank'!P27) -> 0 | Q27: =Bobot!$P27*($I27*('Input Bank'!$K27+'Input Bank'!$L27)/30)+($J27*'Input Bank'!Q27) -> 0 | R27: =Bobot!$P27*($I27*('Input Bank'!$K27+'Input Bank'!$L27)/30)+($J27*'Input Bank'!R27) -> 0 | S27: =Bobot!$P27*($I27*('Input Bank'!$K27+'Input Bank'!$L27)/30)+($J27*'Input Bank'!S27) -> 0 | T27: =Bobot!$P27*($I27*('Input Bank'!$K27+'Input Bank'!$L27)/30)+($J27*'Input Bank'!T27) -> 0 | ... AP27: =Bobot!$P27*($I27*('Input Bank'!$K27+'Input Bank'!$L27)/30)+($J27*'Input Bank'!AP27) -> 0 | AQ27: =$J27*'Input Bank'!AQ27 -> 0 | AR27: =$J27*'Input Bank'!AR27 -> 0 | AS27: =$J27*'Input Bank'!AS27 -> 0 | AT27: =$J27*'Input Bank'!AT27 -> 0 | AU27: =$J27*'Input Bank'!AU27 -> 0 | AV27: =$J27*'Input Bank'!AV27 -> 0 | AW27: =$J27*'Input Bank'!AW27 -> 0 | AX27: =$J27*'Input Bank'!AX27 -> 0 | ... BA27: =$J27*'Input Bank'!BA27 -> 0
A28: =Bobot!#REF! -> #REF! | F28: 015 | G28: 1.1.13 | H28: Korporasi non-finansial yang tidak dijamin LPS | I28: =IF($K$7="Skenario Bank 1",VLOOKUP($F28,Bobot!$F$16:$AA$180,15,0),IF($K$7="Skenario Bank 2",VLOOKUP(F28,Bobot!$F$16:$AA$180,18,0),IF($K$7="Skenario Bank 3",VLOOKUP($F28,Bobot!$F$16:$AA$180,21,0),0))) -> 0 | J28: =IF($K$7="Skenario Bank 1",VLOOKUP($F28,Bobot!$F$16:$AA$180,16,0),IF($K$7="Skenario Bank 2",VLOOKUP($F28,Bobot!$F$16:$AA$180,19,0),IF($K$7="Skenario Bank 3",VLOOKUP($F28,Bobot!$F$16:$AA$180,22,0),0))) -> 0 | L28: =IF(Bobot!$P28=0,1,0)*('Input Bank'!L28+'Input Bank'!K28)*I28 -> 0 | M28: =Bobot!$P28*($I28*('Input Bank'!$K28+'Input Bank'!$L28)/30)+($J28*'Input Bank'!M28) -> 0 | N28: =Bobot!$P28*($I28*('Input Bank'!$K28+'Input Bank'!$L28)/30)+($J28*'Input Bank'!N28) -> 0 | O28: =Bobot!$P28*($I28*('Input Bank'!$K28+'Input Bank'!$L28)/30)+($J28*'Input Bank'!O28) -> 0 | P28: =Bobot!$P28*($I28*('Input Bank'!$K28+'Input Bank'!$L28)/30)+($J28*'Input Bank'!P28) -> 0 | Q28: =Bobot!$P28*($I28*('Input Bank'!$K28+'Input Bank'!$L28)/30)+($J28*'Input Bank'!Q28) -> 0 | R28: =Bobot!$P28*($I28*('Input Bank'!$K28+'Input Bank'!$L28)/30)+($J28*'Input Bank'!R28) -> 0 | S28: =Bobot!$P28*($I28*('Input Bank'!$K28+'Input Bank'!$L28)/30)+($J28*'Input Bank'!S28) -> 0 | T28: =Bobot!$P28*($I28*('Input Bank'!$K28+'Input Bank'!$L28)/30)+($J28*'Input Bank'!T28) -> 0 | ... AP28: =Bobot!$P28*($I28*('Input Bank'!$K28+'Input Bank'!$L28)/30)+($J28*'Input Bank'!AP28) -> 0 | AQ28: =$J28*'Input Bank'!AQ28 -> 0 | AR28: =$J28*'Input Bank'!AR28 -> 0 | AS28: =$J28*'Input Bank'!AS28 -> 0 | AT28: =$J28*'Input Bank'!AT28 -> 0 | AU28: =$J28*'Input Bank'!AU28 -> 0 | AV28: =$J28*'Input Bank'!AV28 -> 0 | AW28: =$J28*'Input Bank'!AW28 -> 0 | AX28: =$J28*'Input Bank'!AX28 -> 0 | ... BA28: =$J28*'Input Bank'!BA28 -> 0
A29: =Bobot!#REF! -> #REF! | F29: 016 | G29: 1.1.14 | H29: Pemerintah pusat, Bank Indonesia, multilateral dan entitas publik yang dijamin LPS | I29: =IF($K$7="Skenario Bank 1",VLOOKUP($F29,Bobot!$F$16:$AA$180,15,0),IF($K$7="Skenario Bank 2",VLOOKUP(F29,Bobot!$F$16:$AA$180,18,0),IF($K$7="Skenario Bank 3",VLOOKUP($F29,Bobot!$F$16:$AA$180,21,0),0))) -> 0 | J29: =IF($K$7="Skenario Bank 1",VLOOKUP($F29,Bobot!$F$16:$AA$180,16,0),IF($K$7="Skenario Bank 2",VLOOKUP($F29,Bobot!$F$16:$AA$180,19,0),IF($K$7="Skenario Bank 3",VLOOKUP($F29,Bobot!$F$16:$AA$180,22,0),0))) -> 0 | L29: =IF(Bobot!$P29=0,1,0)*('Input Bank'!L29+'Input Bank'!K29)*I29 -> 0 | M29: =Bobot!$P29*($I29*('Input Bank'!$K29+'Input Bank'!$L29)/30)+($J29*'Input Bank'!M29) -> 0 | N29: =Bobot!$P29*($I29*('Input Bank'!$K29+'Input Bank'!$L29)/30)+($J29*'Input Bank'!N29) -> 0 | O29: =Bobot!$P29*($I29*('Input Bank'!$K29+'Input Bank'!$L29)/30)+($J29*'Input Bank'!O29) -> 0 | P29: =Bobot!$P29*($I29*('Input Bank'!$K29+'Input Bank'!$L29)/30)+($J29*'Input Bank'!P29) -> 0 | Q29: =Bobot!$P29*($I29*('Input Bank'!$K29+'Input Bank'!$L29)/30)+($J29*'Input Bank'!Q29) -> 0 | R29: =Bobot!$P29*($I29*('Input Bank'!$K29+'Input Bank'!$L29)/30)+($J29*'Input Bank'!R29) -> 0 | S29: =Bobot!$P29*($I29*('Input Bank'!$K29+'Input Bank'!$L29)/30)+($J29*'Input Bank'!S29) -> 0 | T29: =Bobot!$P29*($I29*('Input Bank'!$K29+'Input Bank'!$L29)/30)+($J29*'Input Bank'!T29) -> 0 | ... AP29: =Bobot!$P29*($I29*('Input Bank'!$K29+'Input Bank'!$L29)/30)+($J29*'Input Bank'!AP29) -> 0 | AQ29: =$J29*'Input Bank'!AQ29 -> 0 | AR29: =$J29*'Input Bank'!AR29 -> 0 | AS29: =$J29*'Input Bank'!AS29 -> 0 | AT29: =$J29*'Input Bank'!AT29 -> 0 | AU29: =$J29*'Input Bank'!AU29 -> 0 | AV29: =$J29*'Input Bank'!AV29 -> 0 | AW29: =$J29*'Input Bank'!AW29 -> 0 | AX29: =$J29*'Input Bank'!AX29 -> 0 | ... BA29: =$J29*'Input Bank'!BA29 -> 0
A30: =Bobot!#REF! -> #REF! | F30: 017 | G30: 1.1.15 | H30: Pemerintah pusat, Bank Indonesia, multilateral dan entitas publik yang tidak dijamin LPS | I30: =IF($K$7="Skenario Bank 1",VLOOKUP($F30,Bobot!$F$16:$AA$180,15,0),IF($K$7="Skenario Bank 2",VLOOKUP(F30,Bobot!$F$16:$AA$180,18,0),IF($K$7="Skenario Bank 3",VLOOKUP($F30,Bobot!$F$16:$AA$180,21,0),0))) -> 0 | J30: =IF($K$7="Skenario Bank 1",VLOOKUP($F30,Bobot!$F$16:$AA$180,16,0),IF($K$7="Skenario Bank 2",VLOOKUP($F30,Bobot!$F$16:$AA$180,19,0),IF($K$7="Skenario Bank 3",VLOOKUP($F30,Bobot!$F$16:$AA$180,22,0),0))) -> 0 | L30: =IF(Bobot!$P30=0,1,0)*('Input Bank'!L30+'Input Bank'!K30)*I30 -> 0 | M30: =Bobot!$P30*($I30*('Input Bank'!$K30+'Input Bank'!$L30)/30)+($J30*'Input Bank'!M30) -> 0 | N30: =Bobot!$P30*($I30*('Input Bank'!$K30+'Input Bank'!$L30)/30)+($J30*'Input Bank'!N30) -> 0 | O30: =Bobot!$P30*($I30*('Input Bank'!$K30+'Input Bank'!$L30)/30)+($J30*'Input Bank'!O30) -> 0 | P30: =Bobot!$P30*($I30*('Input Bank'!$K30+'Input Bank'!$L30)/30)+($J30*'Input Bank'!P30) -> 0 | Q30: =Bobot!$P30*($I30*('Input Bank'!$K30+'Input Bank'!$L30)/30)+($J30*'Input Bank'!Q30) -> 0 | R30: =Bobot!$P30*($I30*('Input Bank'!$K30+'Input Bank'!$L30)/30)+($J30*'Input Bank'!R30) -> 0 | S30: =Bobot!$P30*($I30*('Input Bank'!$K30+'Input Bank'!$L30)/30)+($J30*'Input Bank'!S30) -> 0 | T30: =Bobot!$P30*($I30*('Input Bank'!$K30+'Input Bank'!$L30)/30)+($J30*'Input Bank'!T30) -> 0 | ... AP30: =Bobot!$P30*($I30*('Input Bank'!$K30+'Input Bank'!$L30)/30)+($J30*'Input Bank'!AP30) -> 0 | AQ30: =$J30*'Input Bank'!AQ30 -> 0 | AR30: =$J30*'Input Bank'!AR30 -> 0 | AS30: =$J30*'Input Bank'!AS30 -> 0 | AT30: =$J30*'Input Bank'!AT30 -> 0 | AU30: =$J30*'Input Bank'!AU30 -> 0 | AV30: =$J30*'Input Bank'!AV30 -> 0 | AW30: =$J30*'Input Bank'!AW30 -> 0 | AX30: =$J30*'Input Bank'!AX30 -> 0 | ... BA30: =$J30*'Input Bank'!BA30 -> 0
A31: =Bobot!P31 -> 0 | F31: 018 | G31: 1.2 | H31: Kewajiban terkait efek yang diterbitkan | L31: =SUM(L32:L33) -> 0 | M31: =SUM(M32:M33) -> 0 | N31: =SUM(N32:N33) -> 0 | O31: =SUM(O32:O33) -> 0 | P31: =SUM(P32:P33) -> 0 | Q31: =SUM(Q32:Q33) -> 0 | R31: =SUM(R32:R33) -> 0 | S31: =SUM(S32:S33) -> 0 | ... BA31: =SUM(BA32:BA33) -> 0
A32: =Bobot!P32 -> 0 | F32: 019 | G32: 1.2.1 | H32: Surat berharga berupa surat utang yang diterbitkan Bank tanpa agunan | I32: =IF($K$7="Skenario Bank 1",VLOOKUP($F32,Bobot!$F$16:$AA$180,15,0),IF($K$7="Skenario Bank 2",VLOOKUP(F32,Bobot!$F$16:$AA$180,18,0),IF($K$7="Skenario Bank 3",VLOOKUP($F32,Bobot!$F$16:$AA$180,21,0),0))) -> 0 | J32: =IF($K$7="Skenario Bank 1",VLOOKUP($F32,Bobot!$F$16:$AA$180,16,0),IF($K$7="Skenario Bank 2",VLOOKUP($F32,Bobot!$F$16:$AA$180,19,0),IF($K$7="Skenario Bank 3",VLOOKUP($F32,Bobot!$F$16:$AA$180,22,0),0))) -> 0 | L32: =IF(Bobot!$P32=0,1,0)*('Input Bank'!L32+'Input Bank'!K32)*I32 -> 0 | M32: =$J32*'Input Bank'!M32 -> 0 | N32: =$J32*'Input Bank'!N32 -> 0 | O32: =$J32*'Input Bank'!O32 -> 0 | P32: =$J32*'Input Bank'!P32 -> 0 | Q32: =$J32*'Input Bank'!Q32 -> 0 | R32: =$J32*'Input Bank'!R32 -> 0 | S32: =$J32*'Input Bank'!S32 -> 0 | T32: =$J32*'Input Bank'!T32 -> 0 | ... BA32: =$J32*'Input Bank'!BA32 -> 0
A33: =Bobot!#REF! -> #REF! | F33: 020 | G33: 1.2.2 | H33: Lainnya | I33: =IF($K$7="Skenario Bank 1",VLOOKUP($F33,Bobot!$F$16:$AA$180,15,0),IF($K$7="Skenario Bank 2",VLOOKUP(F33,Bobot!$F$16:$AA$180,18,0),IF($K$7="Skenario Bank 3",VLOOKUP($F33,Bobot!$F$16:$AA$180,21,0),0))) -> 0 | J33: =IF($K$7="Skenario Bank 1",VLOOKUP($F33,Bobot!$F$16:$AA$180,16,0),IF($K$7="Skenario Bank 2",VLOOKUP($F33,Bobot!$F$16:$AA$180,19,0),IF($K$7="Skenario Bank 3",VLOOKUP($F33,Bobot!$F$16:$AA$180,22,0),0))) -> 0 | L33: =IF(Bobot!$P33=0,1,0)*('Input Bank'!L33+'Input Bank'!K33)*I33 -> 0 | M33: =$J33*'Input Bank'!M33 -> 0 | N33: =$J33*'Input Bank'!N33 -> 0 | O33: =$J33*'Input Bank'!O33 -> 0 | P33: =$J33*'Input Bank'!P33 -> 0 | Q33: =$J33*'Input Bank'!Q33 -> 0 | R33: =$J33*'Input Bank'!R33 -> 0 | S33: =$J33*'Input Bank'!S33 -> 0 | T33: =$J33*'Input Bank'!T33 -> 0 | ... BA33: =$J33*'Input Bank'!BA33 -> 0
F34: 021 | G34: 1.3 | H34: Pendanaan dengan agunan (secured funding) | L34: =SUM(L35,L42) -> 0 | M34: =SUM(M35,M42) -> 0 | N34: =SUM(N35,N42) -> 0 | O34: =SUM(O35,O42) -> 0 | P34: =SUM(P35,P42) -> 0 | Q34: =SUM(Q35,Q42) -> 0 | R34: =SUM(R35,R42) -> 0 | S34: =SUM(S35,S42) -> 0 | ... BA34: =SUM(BA35,BA42) -> 0
A35: =Bobot!#REF! -> #REF! | F35: 022 | G35: 1.3.1 | H35: Kewajiban timbul dari secured funding atau transaksi pasar modal dengan pihak lawan selain Bank Indonesia: | L35: =SUM(L36:L41) -> 0 | M35: =SUM(M36:M41) -> 0 | N35: =SUM(N36:N41) -> 0 | O35: =SUM(O36:O41) -> 0 | P35: =SUM(P36:P41) -> 0 | Q35: =SUM(Q36:Q41) -> 0 | R35: =SUM(R36:R41) -> 0 | S35: =SUM(S36:S41) -> 0 | ... BA35: =SUM(BA36:BA41) -> 0
A36: =Bobot!P33 -> 0 | F36: 023 | G36: 1.3.2 | H36: Transaksi dilakukan dengan agunan HQLA Level 1 | I36: =IF($K$7="Skenario Bank 1",VLOOKUP($F36,Bobot!$F$16:$AA$180,15,0),IF($K$7="Skenario Bank 2",VLOOKUP(F36,Bobot!$F$16:$AA$180,18,0),IF($K$7="Skenario Bank 3",VLOOKUP($F36,Bobot!$F$16:$AA$180,21,0),0))) -> 0 | J36: =IF($K$7="Skenario Bank 1",VLOOKUP($F36,Bobot!$F$16:$AA$180,16,0),IF($K$7="Skenario Bank 2",VLOOKUP($F36,Bobot!$F$16:$AA$180,19,0),IF($K$7="Skenario Bank 3",VLOOKUP($F36,Bobot!$F$16:$AA$180,22,0),0))) -> 0 | L36: =IF(Bobot!$P36=0,1,0)*('Input Bank'!L36+'Input Bank'!K36)*I36 -> 0 | M36: =Bobot!$P36*($I36*('Input Bank'!$K36+'Input Bank'!$L36)/30)+($J36*'Input Bank'!M36) -> 0 | N36: =Bobot!$P36*($I36*('Input Bank'!$K36+'Input Bank'!$L36)/30)+($J36*'Input Bank'!N36) -> 0 | O36: =Bobot!$P36*($I36*('Input Bank'!$K36+'Input Bank'!$L36)/30)+($J36*'Input Bank'!O36) -> 0 | P36: =Bobot!$P36*($I36*('Input Bank'!$K36+'Input Bank'!$L36)/30)+($J36*'Input Bank'!P36) -> 0 | Q36: =Bobot!$P36*($I36*('Input Bank'!$K36+'Input Bank'!$L36)/30)+($J36*'Input Bank'!Q36) -> 0 | R36: =Bobot!$P36*($I36*('Input Bank'!$K36+'Input Bank'!$L36)/30)+($J36*'Input Bank'!R36) -> 0 | S36: =Bobot!$P36*($I36*('Input Bank'!$K36+'Input Bank'!$L36)/30)+($J36*'Input Bank'!S36) -> 0 | T36: =Bobot!$P36*($I36*('Input Bank'!$K36+'Input Bank'!$L36)/30)+($J36*'Input Bank'!T36) -> 0 | ... AP36: =Bobot!$P36*($I36*('Input Bank'!$K36+'Input Bank'!$L36)/30)+($J36*'Input Bank'!AP36) -> 0 | AQ36: =$J36*'Input Bank'!AQ36 -> 0 | AR36: =$J36*'Input Bank'!AR36 -> 0 | AS36: =$J36*'Input Bank'!AS36 -> 0 | AT36: =$J36*'Input Bank'!AT36 -> 0 | AU36: =$J36*'Input Bank'!AU36 -> 0 | AV36: =$J36*'Input Bank'!AV36 -> 0 | AW36: =$J36*'Input Bank'!AW36 -> 0 | AX36: =$J36*'Input Bank'!AX36 -> 0 | ... BA36: =$J36*'Input Bank'!BA36 -> 0
A37: =Bobot!P34 -> 0 | F37: 024 | G37: 1.3.3 | H37: Transaksi dilakukan dengan agunan HQLA Level 2A | I37: =IF($K$7="Skenario Bank 1",VLOOKUP($F37,Bobot!$F$16:$AA$180,15,0),IF($K$7="Skenario Bank 2",VLOOKUP(F37,Bobot!$F$16:$AA$180,18,0),IF($K$7="Skenario Bank 3",VLOOKUP($F37,Bobot!$F$16:$AA$180,21,0),0))) -> 0 | J37: =IF($K$7="Skenario Bank 1",VLOOKUP($F37,Bobot!$F$16:$AA$180,16,0),IF($K$7="Skenario Bank 2",VLOOKUP($F37,Bobot!$F$16:$AA$180,19,0),IF($K$7="Skenario Bank 3",VLOOKUP($F37,Bobot!$F$16:$AA$180,22,0),0))) -> 0 | L37: =IF(Bobot!$P37=0,1,0)*('Input Bank'!L37+'Input Bank'!K37)*I37 -> 0 | M37: =Bobot!$P37*($I37*('Input Bank'!$K37+'Input Bank'!$L37)/30)+($J37*'Input Bank'!M37) -> 0 | N37: =Bobot!$P37*($I37*('Input Bank'!$K37+'Input Bank'!$L37)/30)+($J37*'Input Bank'!N37) -> 0 | O37: =Bobot!$P37*($I37*('Input Bank'!$K37+'Input Bank'!$L37)/30)+($J37*'Input Bank'!O37) -> 0 | P37: =Bobot!$P37*($I37*('Input Bank'!$K37+'Input Bank'!$L37)/30)+($J37*'Input Bank'!P37) -> 0 | Q37: =Bobot!$P37*($I37*('Input Bank'!$K37+'Input Bank'!$L37)/30)+($J37*'Input Bank'!Q37) -> 0 | R37: =Bobot!$P37*($I37*('Input Bank'!$K37+'Input Bank'!$L37)/30)+($J37*'Input Bank'!R37) -> 0 | S37: =Bobot!$P37*($I37*('Input Bank'!$K37+'Input Bank'!$L37)/30)+($J37*'Input Bank'!S37) -> 0 | T37: =Bobot!$P37*($I37*('Input Bank'!$K37+'Input Bank'!$L37)/30)+($J37*'Input Bank'!T37) -> 0 | ... AP37: =Bobot!$P37*($I37*('Input Bank'!$K37+'Input Bank'!$L37)/30)+($J37*'Input Bank'!AP37) -> 0 | AQ37: =$J37*'Input Bank'!AQ37 -> 0 | AR37: =$J37*'Input Bank'!AR37 -> 0 | AS37: =$J37*'Input Bank'!AS37 -> 0 | AT37: =$J37*'Input Bank'!AT37 -> 0 | AU37: =$J37*'Input Bank'!AU37 -> 0 | AV37: =$J37*'Input Bank'!AV37 -> 0 | AW37: =$J37*'Input Bank'!AW37 -> 0 | AX37: =$J37*'Input Bank'!AX37 -> 0 | ... BA37: =$J37*'Input Bank'!BA37 -> 0
F38: 025 | G38: 1.3.4 | H38: Transaksi dilakukan dengan Pemerintah Pusat atau entitas sektor publik yang memiliki bobot risiko paling tinggi 20% atau bank pembangunan multilateral, dengan agunan selain HQLA Level 1 atau HQLA Level 2A | I38: =IF($K$7="Skenario Bank 1",VLOOKUP($F38,Bobot!$F$16:$AA$180,15,0),IF($K$7="Skenario Bank 2",VLOOKUP(F38,Bobot!$F$16:$AA$180,18,0),IF($K$7="Skenario Bank 3",VLOOKUP($F38,Bobot!$F$16:$AA$180,21,0),0))) -> 0 | J38: =IF($K$7="Skenario Bank 1",VLOOKUP($F38,Bobot!$F$16:$AA$180,16,0),IF($K$7="Skenario Bank 2",VLOOKUP($F38,Bobot!$F$16:$AA$180,19,0),IF($K$7="Skenario Bank 3",VLOOKUP($F38,Bobot!$F$16:$AA$180,22,0),0))) -> 0 | L38: =IF(Bobot!$P38=0,1,0)*('Input Bank'!L38+'Input Bank'!K38)*I38 -> 0 | M38: =Bobot!$P38*($I38*('Input Bank'!$K38+'Input Bank'!$L38)/30)+($J38*'Input Bank'!M38) -> 0 | N38: =Bobot!$P38*($I38*('Input Bank'!$K38+'Input Bank'!$L38)/30)+($J38*'Input Bank'!N38) -> 0 | O38: =Bobot!$P38*($I38*('Input Bank'!$K38+'Input Bank'!$L38)/30)+($J38*'Input Bank'!O38) -> 0 | P38: =Bobot!$P38*($I38*('Input Bank'!$K38+'Input Bank'!$L38)/30)+($J38*'Input Bank'!P38) -> 0 | Q38: =Bobot!$P38*($I38*('Input Bank'!$K38+'Input Bank'!$L38)/30)+($J38*'Input Bank'!Q38) -> 0 | R38: =Bobot!$P38*($I38*('Input Bank'!$K38+'Input Bank'!$L38)/30)+($J38*'Input Bank'!R38) -> 0 | S38: =Bobot!$P38*($I38*('Input Bank'!$K38+'Input Bank'!$L38)/30)+($J38*'Input Bank'!S38) -> 0 | T38: =Bobot!$P38*($I38*('Input Bank'!$K38+'Input Bank'!$L38)/30)+($J38*'Input Bank'!T38) -> 0 | ... AP38: =Bobot!$P38*($I38*('Input Bank'!$K38+'Input Bank'!$L38)/30)+($J38*'Input Bank'!AP38) -> 0 | AQ38: =$J38*'Input Bank'!AQ38 -> 0 | AR38: =$J38*'Input Bank'!AR38 -> 0 | AS38: =$J38*'Input Bank'!AS38 -> 0 | AT38: =$J38*'Input Bank'!AT38 -> 0 | AU38: =$J38*'Input Bank'!AU38 -> 0 | AV38: =$J38*'Input Bank'!AV38 -> 0 | AW38: =$J38*'Input Bank'!AW38 -> 0 | AX38: =$J38*'Input Bank'!AX38 -> 0 | ... BA38: =$J38*'Input Bank'!BA38 -> 0
A39: =Bobot!P36 -> 0 | F39: 026 | G39: 1.3.5 | H39: Transaksi dilakukan dengan agunan HQLA Level 2B berupa EBA | I39: =IF($K$7="Skenario Bank 1",VLOOKUP($F39,Bobot!$F$16:$AA$180,15,0),IF($K$7="Skenario Bank 2",VLOOKUP(F39,Bobot!$F$16:$AA$180,18,0),IF($K$7="Skenario Bank 3",VLOOKUP($F39,Bobot!$F$16:$AA$180,21,0),0))) -> 0 | J39: =IF($K$7="Skenario Bank 1",VLOOKUP($F39,Bobot!$F$16:$AA$180,16,0),IF($K$7="Skenario Bank 2",VLOOKUP($F39,Bobot!$F$16:$AA$180,19,0),IF($K$7="Skenario Bank 3",VLOOKUP($F39,Bobot!$F$16:$AA$180,22,0),0))) -> 0 | L39: =IF(Bobot!$P39=0,1,0)*('Input Bank'!L39+'Input Bank'!K39)*I39 -> 0 | M39: =Bobot!$P39*($I39*('Input Bank'!$K39+'Input Bank'!$L39)/30)+($J39*'Input Bank'!M39) -> 0 | N39: =Bobot!$P39*($I39*('Input Bank'!$K39+'Input Bank'!$L39)/30)+($J39*'Input Bank'!N39) -> 0 | O39: =Bobot!$P39*($I39*('Input Bank'!$K39+'Input Bank'!$L39)/30)+($J39*'Input Bank'!O39) -> 0 | P39: =Bobot!$P39*($I39*('Input Bank'!$K39+'Input Bank'!$L39)/30)+($J39*'Input Bank'!P39) -> 0 | Q39: =Bobot!$P39*($I39*('Input Bank'!$K39+'Input Bank'!$L39)/30)+($J39*'Input Bank'!Q39) -> 0 | R39: =Bobot!$P39*($I39*('Input Bank'!$K39+'Input Bank'!$L39)/30)+($J39*'Input Bank'!R39) -> 0 | S39: =Bobot!$P39*($I39*('Input Bank'!$K39+'Input Bank'!$L39)/30)+($J39*'Input Bank'!S39) -> 0 | T39: =Bobot!$P39*($I39*('Input Bank'!$K39+'Input Bank'!$L39)/30)+($J39*'Input Bank'!T39) -> 0 | ... AP39: =Bobot!$P39*($I39*('Input Bank'!$K39+'Input Bank'!$L39)/30)+($J39*'Input Bank'!AP39) -> 0 | AQ39: =$J39*'Input Bank'!AQ39 -> 0 | AR39: =$J39*'Input Bank'!AR39 -> 0 | AS39: =$J39*'Input Bank'!AS39 -> 0 | AT39: =$J39*'Input Bank'!AT39 -> 0 | AU39: =$J39*'Input Bank'!AU39 -> 0 | AV39: =$J39*'Input Bank'!AV39 -> 0 | AW39: =$J39*'Input Bank'!AW39 -> 0 | AX39: =$J39*'Input Bank'!AX39 -> 0 | ... BA39: =$J39*'Input Bank'!BA39 -> 0
A40: =Bobot!#REF! -> #REF! | F40: 027 | G40: 1.3.6 | H40: Transaksi dilakukan dengan agunan HQLA Level 2B berupa selain EBA | I40: =IF($K$7="Skenario Bank 1",VLOOKUP($F40,Bobot!$F$16:$AA$180,15,0),IF($K$7="Skenario Bank 2",VLOOKUP(F40,Bobot!$F$16:$AA$180,18,0),IF($K$7="Skenario Bank 3",VLOOKUP($F40,Bobot!$F$16:$AA$180,21,0),0))) -> 0 | J40: =IF($K$7="Skenario Bank 1",VLOOKUP($F40,Bobot!$F$16:$AA$180,16,0),IF($K$7="Skenario Bank 2",VLOOKUP($F40,Bobot!$F$16:$AA$180,19,0),IF($K$7="Skenario Bank 3",VLOOKUP($F40,Bobot!$F$16:$AA$180,22,0),0))) -> 0 | L40: =IF(Bobot!$P40=0,1,0)*('Input Bank'!L40+'Input Bank'!K40)*I40 -> 0 | M40: =Bobot!$P40*($I40*('Input Bank'!$K40+'Input Bank'!$L40)/30)+($J40*'Input Bank'!M40) -> 0 | N40: =Bobot!$P40*($I40*('Input Bank'!$K40+'Input Bank'!$L40)/30)+($J40*'Input Bank'!N40) -> 0 | O40: =Bobot!$P40*($I40*('Input Bank'!$K40+'Input Bank'!$L40)/30)+($J40*'Input Bank'!O40) -> 0 | P40: =Bobot!$P40*($I40*('Input Bank'!$K40+'Input Bank'!$L40)/30)+($J40*'Input Bank'!P40) -> 0 | Q40: =Bobot!$P40*($I40*('Input Bank'!$K40+'Input Bank'!$L40)/30)+($J40*'Input Bank'!Q40) -> 0 | R40: =Bobot!$P40*($I40*('Input Bank'!$K40+'Input Bank'!$L40)/30)+($J40*'Input Bank'!R40) -> 0 | S40: =Bobot!$P40*($I40*('Input Bank'!$K40+'Input Bank'!$L40)/30)+($J40*'Input Bank'!S40) -> 0 | T40: =Bobot!$P40*($I40*('Input Bank'!$K40+'Input Bank'!$L40)/30)+($J40*'Input Bank'!T40) -> 0 | ... AP40: =Bobot!$P40*($I40*('Input Bank'!$K40+'Input Bank'!$L40)/30)+($J40*'Input Bank'!AP40) -> 0 | AQ40: =$J40*'Input Bank'!AQ40 -> 0 | AR40: =$J40*'Input Bank'!AR40 -> 0 | AS40: =$J40*'Input Bank'!AS40 -> 0 | AT40: =$J40*'Input Bank'!AT40 -> 0 | AU40: =$J40*'Input Bank'!AU40 -> 0 | AV40: =$J40*'Input Bank'!AV40 -> 0 | AW40: =$J40*'Input Bank'!AW40 -> 0 | AX40: =$J40*'Input Bank'!AX40 -> 0 | ... BA40: =$J40*'Input Bank'!BA40 -> 0
A41: =Bobot!#REF! -> #REF! | F41: 028 | G41: 1.3.7 | H41: Transaksi dilakukan dengan agunan selain HQLA | I41: =IF($K$7="Skenario Bank 1",VLOOKUP($F41,Bobot!$F$16:$AA$180,15,0),IF($K$7="Skenario Bank 2",VLOOKUP(F41,Bobot!$F$16:$AA$180,18,0),IF($K$7="Skenario Bank 3",VLOOKUP($F41,Bobot!$F$16:$AA$180,21,0),0))) -> 0 | J41: =IF($K$7="Skenario Bank 1",VLOOKUP($F41,Bobot!$F$16:$AA$180,16,0),IF($K$7="Skenario Bank 2",VLOOKUP($F41,Bobot!$F$16:$AA$180,19,0),IF($K$7="Skenario Bank 3",VLOOKUP($F41,Bobot!$F$16:$AA$180,22,0),0))) -> 0 | L41: =IF(Bobot!$P41=0,1,0)*('Input Bank'!L41+'Input Bank'!K41)*I41 -> 0 | M41: =Bobot!$P41*($I41*('Input Bank'!$K41+'Input Bank'!$L41)/30)+($J41*'Input Bank'!M41) -> 0 | N41: =Bobot!$P41*($I41*('Input Bank'!$K41+'Input Bank'!$L41)/30)+($J41*'Input Bank'!N41) -> 0 | O41: =Bobot!$P41*($I41*('Input Bank'!$K41+'Input Bank'!$L41)/30)+($J41*'Input Bank'!O41) -> 0 | P41: =Bobot!$P41*($I41*('Input Bank'!$K41+'Input Bank'!$L41)/30)+($J41*'Input Bank'!P41) -> 0 | Q41: =Bobot!$P41*($I41*('Input Bank'!$K41+'Input Bank'!$L41)/30)+($J41*'Input Bank'!Q41) -> 0 | R41: =Bobot!$P41*($I41*('Input Bank'!$K41+'Input Bank'!$L41)/30)+($J41*'Input Bank'!R41) -> 0 | S41: =Bobot!$P41*($I41*('Input Bank'!$K41+'Input Bank'!$L41)/30)+($J41*'Input Bank'!S41) -> 0 | T41: =Bobot!$P41*($I41*('Input Bank'!$K41+'Input Bank'!$L41)/30)+($J41*'Input Bank'!T41) -> 0 | ... AP41: =Bobot!$P41*($I41*('Input Bank'!$K41+'Input Bank'!$L41)/30)+($J41*'Input Bank'!AP41) -> 0 | AQ41: =$J41*'Input Bank'!AQ41 -> 0 | AR41: =$J41*'Input Bank'!AR41 -> 0 | AS41: =$J41*'Input Bank'!AS41 -> 0 | AT41: =$J41*'Input Bank'!AT41 -> 0 | AU41: =$J41*'Input Bank'!AU41 -> 0 | AV41: =$J41*'Input Bank'!AV41 -> 0 | AW41: =$J41*'Input Bank'!AW41 -> 0 | AX41: =$J41*'Input Bank'!AX41 -> 0 | ... BA41: =$J41*'Input Bank'!BA41 -> 0
F42: 029 | G42: 1.3.8 | H42: Kewajiban timbul dari secured funding atau transaksi pasar modal dengan Bank Indonesia sebagai pihak lawan: | L42: =SUM(L43:L47) -> 0 | M42: =SUM(M43:M47) -> 0 | N42: =SUM(N43:N47) -> 0 | O42: =SUM(O43:O47) -> 0 | P42: =SUM(P43:P47) -> 0 | Q42: =SUM(Q43:Q47) -> 0 | R42: =SUM(R43:R47) -> 0 | S42: =SUM(S43:S47) -> 0 | ... BA42: =SUM(BA43:BA47) -> 0
F43: 030 | G43: 1.3.9 | H43: Transaksi dilakukan dengan agunan HQLA Level 1 | I43: =IF($K$7="Skenario Bank 1",VLOOKUP($F43,Bobot!$F$16:$AA$180,15,0),IF($K$7="Skenario Bank 2",VLOOKUP(F43,Bobot!$F$16:$AA$180,18,0),IF($K$7="Skenario Bank 3",VLOOKUP($F43,Bobot!$F$16:$AA$180,21,0),0))) -> 0 | J43: =IF($K$7="Skenario Bank 1",VLOOKUP($F43,Bobot!$F$16:$AA$180,16,0),IF($K$7="Skenario Bank 2",VLOOKUP($F43,Bobot!$F$16:$AA$180,19,0),IF($K$7="Skenario Bank 3",VLOOKUP($F43,Bobot!$F$16:$AA$180,22,0),0))) -> 0 | L43: =IF(Bobot!$P43=0,1,0)*('Input Bank'!L43+'Input Bank'!K43)*I43 -> 0 | M43: =Bobot!$P43*($I43*('Input Bank'!$K43+'Input Bank'!$L43)/30)+($J43*'Input Bank'!M43) -> 0 | N43: =Bobot!$P43*($I43*('Input Bank'!$K43+'Input Bank'!$L43)/30)+($J43*'Input Bank'!N43) -> 0 | O43: =Bobot!$P43*($I43*('Input Bank'!$K43+'Input Bank'!$L43)/30)+($J43*'Input Bank'!O43) -> 0 | P43: =Bobot!$P43*($I43*('Input Bank'!$K43+'Input Bank'!$L43)/30)+($J43*'Input Bank'!P43) -> 0 | Q43: =Bobot!$P43*($I43*('Input Bank'!$K43+'Input Bank'!$L43)/30)+($J43*'Input Bank'!Q43) -> 0 | R43: =Bobot!$P43*($I43*('Input Bank'!$K43+'Input Bank'!$L43)/30)+($J43*'Input Bank'!R43) -> 0 | S43: =Bobot!$P43*($I43*('Input Bank'!$K43+'Input Bank'!$L43)/30)+($J43*'Input Bank'!S43) -> 0 | T43: =Bobot!$P43*($I43*('Input Bank'!$K43+'Input Bank'!$L43)/30)+($J43*'Input Bank'!T43) -> 0 | ... AP43: =Bobot!$P43*($I43*('Input Bank'!$K43+'Input Bank'!$L43)/30)+($J43*'Input Bank'!AP43) -> 0 | AQ43: =$J43*'Input Bank'!AQ43 -> 0 | AR43: =$J43*'Input Bank'!AR43 -> 0 | AS43: =$J43*'Input Bank'!AS43 -> 0 | AT43: =$J43*'Input Bank'!AT43 -> 0 | AU43: =$J43*'Input Bank'!AU43 -> 0 | AV43: =$J43*'Input Bank'!AV43 -> 0 | AW43: =$J43*'Input Bank'!AW43 -> 0 | AX43: =$J43*'Input Bank'!AX43 -> 0 | ... BA43: =$J43*'Input Bank'!BA43 -> 0
F44: 031 | G44: 1.3.10 | H44: Transaksi dilakukan dengan agunan HQLA Level 2A | I44: =IF($K$7="Skenario Bank 1",VLOOKUP($F44,Bobot!$F$16:$AA$180,15,0),IF($K$7="Skenario Bank 2",VLOOKUP(F44,Bobot!$F$16:$AA$180,18,0),IF($K$7="Skenario Bank 3",VLOOKUP($F44,Bobot!$F$16:$AA$180,21,0),0))) -> 0 | J44: =IF($K$7="Skenario Bank 1",VLOOKUP($F44,Bobot!$F$16:$AA$180,16,0),IF($K$7="Skenario Bank 2",VLOOKUP($F44,Bobot!$F$16:$AA$180,19,0),IF($K$7="Skenario Bank 3",VLOOKUP($F44,Bobot!$F$16:$AA$180,22,0),0))) -> 0 | L44: =IF(Bobot!$P44=0,1,0)*('Input Bank'!L44+'Input Bank'!K44)*I44 -> 0 | M44: =Bobot!$P44*($I44*('Input Bank'!$K44+'Input Bank'!$L44)/30)+($J44*'Input Bank'!M44) -> 0 | N44: =Bobot!$P44*($I44*('Input Bank'!$K44+'Input Bank'!$L44)/30)+($J44*'Input Bank'!N44) -> 0 | O44: =Bobot!$P44*($I44*('Input Bank'!$K44+'Input Bank'!$L44)/30)+($J44*'Input Bank'!O44) -> 0 | P44: =Bobot!$P44*($I44*('Input Bank'!$K44+'Input Bank'!$L44)/30)+($J44*'Input Bank'!P44) -> 0 | Q44: =Bobot!$P44*($I44*('Input Bank'!$K44+'Input Bank'!$L44)/30)+($J44*'Input Bank'!Q44) -> 0 | R44: =Bobot!$P44*($I44*('Input Bank'!$K44+'Input Bank'!$L44)/30)+($J44*'Input Bank'!R44) -> 0 | S44: =Bobot!$P44*($I44*('Input Bank'!$K44+'Input Bank'!$L44)/30)+($J44*'Input Bank'!S44) -> 0 | T44: =Bobot!$P44*($I44*('Input Bank'!$K44+'Input Bank'!$L44)/30)+($J44*'Input Bank'!T44) -> 0 | ... AP44: =Bobot!$P44*($I44*('Input Bank'!$K44+'Input Bank'!$L44)/30)+($J44*'Input Bank'!AP44) -> 0 | AQ44: =$J44*'Input Bank'!AQ44 -> 0 | AR44: =$J44*'Input Bank'!AR44 -> 0 | AS44: =$J44*'Input Bank'!AS44 -> 0 | AT44: =$J44*'Input Bank'!AT44 -> 0 | AU44: =$J44*'Input Bank'!AU44 -> 0 | AV44: =$J44*'Input Bank'!AV44 -> 0 | AW44: =$J44*'Input Bank'!AW44 -> 0 | AX44: =$J44*'Input Bank'!AX44 -> 0 | ... BA44: =$J44*'Input Bank'!BA44 -> 0
